Workbook
Name AA: #REF!
Name GG: #REF!
Name ID: #REF!
Name ID: #REF!
Name ID: #REF!
Name ID: [1]입출고!#REF!
Name YY: #REF!
Name 계산서: #REF!
Name 계산서: #REF!
Name 계산서: #REF!
Name 계산서: [1]입출고!#REF!
Name 계약금: #REF!
Name 계약금: #REF!
Name 계약금: #REF!
Name 계약금: [1]입출고!#REF!
Name 광택: #REF!
Name 광택: #REF!
Name 광택: #REF!
Name 광택: [1]입출고!#REF!
Name 구분입력: [2]수출현황_종합!$G$2
Name 구분입력2: [2]수출현황_종합!$G$3
Name 기준날짜: [2]수출현황_종합!$J$3
Name 기준월: [2]수출현황_종합!$C$3
Name 기타: #REF!
Name 기타: #REF!
Name 기타: #REF!
Name 기타: [1]입출고!#REF!
Name ㄴㅇㄹ: #REF!
Name 년도: [2]수출현황_종합!$B$3
Name 등급: #REF!
Name 등급: #REF!
Name 등급: #REF!
Name 등급: [1]입출고!#REF!
Name 말소날짜: #REF!
Name 말소날짜: #REF!
Name 말소날짜: #REF!
Name 말소날짜: [1]입출고!#REF!
Name 말소증2: [1]입출고!#REF!
Name 매입가: #REF!
Name 매입가: #REF!
Name 매입가: #REF!
Name 매입가: [1]입출고!#REF!
Name 매입날짜: #REF!
Name 매입날짜: #REF!
Name 매입날짜: #REF!
Name 매입날짜: [1]입출고!#REF!
Name 메다: #REF!
Name 메다: #REF!
Name 메다: #REF!
Name 메다: [1]입출고!#REF!
Name 미수: #REF!
Name 미수: #REF!
Name 미수: #REF!
Name 미수: [1]입출고!#REF!
Name 바이어연락처: #REF!
Name 바이어연락처: #REF!
Name 바이어연락처: #REF!
Name 바이어연락처: [1]입출고!#REF!
Name 변속기: #REF!
Name 변속기: #REF!

Sheet 달러 판매현황
A1: NO | B1: 구입일자 | C1: EVOQUE | D1: 30무0996 | E1: CHASSIS NUMBER | F1: 판매자 정보 | G1: 계약금 | H1: 바이어 회사명 | I1: 고객컨사이니 | J1: 고객 ID / 비즈니스 넘버 | K1: 전화번호 | L1: 나라 | M1: 구입금액 | N1: 매도비 | O1: 총 구입금액 | P1: 유로 | Q1: 상태 | R1: 판매보고 여부 | S1: 입금여부 | T1: 판매금액 | U1: 환율 1$ | V1: 운임 | W1: 커미션 | X1: 디스카운트 | Y1: 부가세 | Z1: 판매 총 합계 | AA1: 입금합계 | AB1: 미수금 | AC1: 메모 | AD1: 메모 | AE1: 입금날짜01 | AF1: 정산01 | AG1: 입금날짜02 | AH1: 정산02 | AI1: 입금날짜03 | AJ1: 정산03 | AK1: 적립금 사용 | AL1: 선수금 | AM1: 말소/면허 | AN1: 탁송 | AO1: 캐리어 | AP1: 쇼링 | AQ1: 기타 | AR1: 합계 | AS1: 정산판매금 원화 | AT1: 판매마진 | AU1: 부가세 마진 | AV1: 총 마진 | AW1: 지급액 | AX1: 서류공제 | AY1: 비용공제 | AZ1: 실지급액 | BA1: 돈받은거
A2: 1 | B2: 45970 | C2: A4 | D2: 22러6510 | E2: WAUZZZ8K0CA054269 | F2: 카팡 / 김동영 | H2: AUTO-ANDI | I2: Andi Cereku | J2: M34710201A | K2: 696688738 | L2: Albania | M2: 4300000 | N2: 0 | O2: =M2+N2 -> 4300000 | P2: USD | Q2: 출고 | R2: 완 | S2: 입금완료 | T2: 3030 | U2: 1443 | V2: 1670 | Z2: =SUM(T2,V2:Y2) -> 4700 | AA2: =SUM(AF2+AH2+AJ2+AK2-AL2) -> 0 | AB2: =SUM(AA2-Z2) -> -4700 | AM2: 35000 | AN2: 30000 | AR2: =SUM(AM2:AQ2) -> 65000 | AS2: =SUM(Z2-V2)*U2-AR2 -> 4307290 | AT2: =SUM(AS2-O2) -> 7290 | AU2: =SUM(M2*0.09) -> 387000 | AV2: =SUM(AT2:AU2)/2 -> 197145 | AW2: =AV2-(AV2*10%) -> 177430.5 | AX2: 50000 | AZ2: =SUM(AW2-AX2-AY2) -> 127430.5
A3: 2 | B3: 45970 | C3: A6 35 TDI | D3: 06어6962 | E3: WAUZZZ4G0JN115661 | F3: 하이앤드 / 김기헌 | H3: Faturat Net Sh.p.k | I3: Faturat Net Sh.p.k | J3: 811577636 | K3: +38349930085, +38344371274 | L3: Kosovo | M3: 17960000 | N3: 440000 | O3: =M3+N3 -> 18400000 | P3: USD | Q3: 출고 | R3: 완 | S3: 입금완료 | T3: 12430 | U3: 1443 | V3: 1670 | Z3: =SUM(T3,V3:Y3) -> 14100 | AA3: =SUM(AF3+AH3+AJ3+AK3-AL3) -> 0 | AB3: =SUM(AA3-Z3) -> -14100 | AM3: 35000 | AN3: 30000 | AR3: =SUM(AM3:AQ3) -> 65000 | AS3: =SUM(Z3-V3)*U3-AR3 -> 17871490 | AT3: =SUM(AS3-O3) -> -528510 | AU3: =SUM(M3*0.09) -> 1616400 | AV3: =SUM(AT3:AU3)/2 -> 543945 | AW3: =AV3-(AV3*10%) -> 489550.5 | AX3: 50000 | AZ3: =SUM(AW3-AX3-AY3) -> 439550.5
A4: 3 | B4: 45978 | C4: TUCSON | D4: 154라1419 | E4: KMHJ2814BGU023329 | F4: 이동근 ( 단독명의 ) | H4: AUTO-ANDI | I4: Andi Cereku | J4: M34710201A | K4: 696688738 | L4: Albania | M4: 8600000 | N4: 0 | O4: =M4+N4 -> 8600000 | P4: USD | Q4: 출고 | R4: 완 | S4: 입금완료 | T4: 6080 | U4: 1451 | V4: 1770 | Z4: =SUM(T4,V4:Y4) -> 7850 | AA4: =SUM(AF4+AH4+AJ4+AK4-AL4) -> 0 | AB4: =SUM(AA4-Z4) -> -7850 | AM4: 35000 | AN4: 30000 | AR4: =SUM(AM4:AQ4) -> 65000 | AS4: =SUM(Z4-V4)*U4-AR4 -> 8757080 | AT4: =SUM(AS4-O4) -> 157080 | AU4: =SUM(M4*0.09) -> 774000 | AV4: =SUM(AT4:AU4)/2 -> 465540 | AW4: =AV4-(AV4*10%) -> 418986 | AX4: 50000 | AZ4: =SUM(AW4-AX4-AY4) -> 368986
A5: 4 | B5: 45978 | C5: A6 3.0TDI | D5: 229누1701 | E5: WAUZZZ4G8EN159977 | F5: 열린모터스 / 장재완 | H5: AUTO-ANDI | I5: Andi Cereku | J5: M34710201A | K5: 696688738 | L5: Albania | M5: 4200000 | N5: 440000 | O5: =M5+N5 -> 4640000 | P5: USD | Q5: 출고 | R5: 완 | S5: 입금완료 | T5: 3280 | U5: 1455 | V5: 1670 | Z5: =SUM(T5,V5:Y5) -> 4950 | AA5: =SUM(AF5+AH5+AJ5+AK5-AL5) -> 0 | AB5: =SUM(AA5-Z5) -> -4950 | AM5: 35000 | AN5: 30000 | AR5: =SUM(AM5:AQ5) -> 65000 | AS5: =SUM(Z5-V5)*U5-AR5 -> 4707400 | AT5: =SUM(AS5-O5) -> 67400 | AU5: =SUM(M5*0.09) -> 378000 | AV5: =SUM(AT5:AU5)/2 -> 222700 | AW5: =AV5-(AV5*10%) -> 200430 | AX5: 50000 | AZ5: =SUM(AW5-AX5-AY5) -> 150430
A6: 5 | B6: 45978 | C6: GOLF | D6: 154두4776 | E6: WVWZZZ1KZDW080415 | F6: 레인보우 / 김태균 | H6: AUTO-ANDI | I6: Andi Cereku | J6: M34710201A | K6: 696688738 | L6: Albania | M6: 4300000 | N6: 440000 | O6: =M6+N6 -> 4740000 | P6: USD | Q6: 출고 | R6: 완 | S6: 입금완료 | T6: 3180 | U6: 1455 | V6: 1670 | Z6: =SUM(T6,V6:Y6) -> 4850 | AA6: =SUM(AF6+AH6+AJ6+AK6-AL6) -> 0 | AB6: =SUM(AA6-Z6) -> -4850 | AM6: 35000 | AN6: 30000 | AR6: =SUM(AM6:AQ6) -> 65000 | AS6: =SUM(Z6-V6)*U6-AR6 -> 4561900 | AT6: =SUM(AS6-O6) -> -178100 | AU6: =SUM(M6*0.09) -> 387000 | AV6: =SUM(AT6:AU6)/2 -> 104450 | AW6: =AV6-(AV6*10%) -> 94005 | AX6: 50000 | AZ6: =SUM(AW6-AX6-AY6) -> 44005
A7: 6 | B7: 45979 | C7: A8 4.2 FSI quattro | D7: 64나2492 | E7: WAUZZZ4H4B002161 | F7: 왕카 / 이민우 | H7: Myzejen Zajaku | L7: Albania (신규) | M7: 7100000 | N7: 0 | O7: =M7+N7 -> 7100000 | Q7: 출고 | R7: 완 | S7: 입금완료 | T7: 5382 | U7: 1457 | Z7: =SUM(T7,V7:Y7) -> 5382 | AA7: =SUM(AF7+AH7+AJ7+AK7-AL7) -> 0 | AB7: =SUM(AA7-Z7) -> -5382 | AM7: 35000 | AN7: 30000 | AR7: =SUM(AM7:AQ7) -> 65000 | AS7: =SUM(Z7-V7)*U7-AR7 -> 7776574 | AT7: =SUM(AS7-O7) -> 676574 | AU7: =SUM(M7*0.09) -> 639000 | AV7: =SUM(AT7:AU7)/2 -> 657787 | AW7: =AV7-(AV7*10%) -> 592008.3 | AX7: 50000 | AZ7: =SUM(AW7-AX7-AY7) -> 542008.3
A8: 7 | B8: 45981 | C8: 730D xDrive M Sport Package | D8: 335루1767 | E8: WBA7S4107LCE80376 | F8: 오토웨이브 김경호 | H8: Faturat Net Sh.p.k | I8: Faturat Net Sh.p.k | J8: 811577636 | K8: +38349930085, +38344371274 | L8: Kosovo | M8: 53600000 | N8: 0 | O8: =M8+N8 -> 53600000 | P8: USD | Q8: 출고 | R8: 완 | S8: 입금완료 | T8: 35330 | U8: 1453 | Z8: =SUM(T8,V8:Y8) -> 35330 | AA8: =SUM(AF8+AH8+AJ8+AK8-AL8) -> 0 | AB8: =SUM(AA8-Z8) -> -35330 | AM8: 35000 | AN8: 30000 | AR8: =SUM(AM8:AQ8) -> 65000 | AS8: =SUM(Z8-V8)*U8-AR8 -> 51269490 | AT8: =SUM(AS8-O8) -> -2330510 | AU8: =SUM(M8*0.09) -> 4824000 | AV8: =SUM(AT8:AU8)/2 -> 1246745 | AW8: =AV8-(AV8*10%) -> 1122070.5 | AX8: 50000 | AZ8: =SUM(AW8-AX8-AY8) -> 1072070.5
A9: 8 | B9: 45985 | C9: TIGUAN | D9: 35어2331 | E9: WVGZZZ5NZCW067974 | F9: 레인보우 / 박주용 | H9: AUTO-ANDI | I9: Andi Cereku | J9: M34710201A | K9: 696688738 | L9: Albania | M9: 5800000 | N9: 440000 | O9: =M9+N9 -> 6240000 | P9: USD | Q9: 출고 | R9: 완 | S9: 입금완료 | T9: 4180 | U9: 1455 | V9: 1770 | Z9: =SUM(T9,V9:Y9) -> 5950 | AA9: =SUM(AF9+AH9+AJ9+AK9-AL9) -> 0 | AB9: =SUM(AA9-Z9) -> -5950 | AM9: 35000 | AN9: 30000 | AR9: =SUM(AM9:AQ9) -> 65000 | AS9: =SUM(Z9-V9)*U9-AR9 -> 6016900 | AT9: =SUM(AS9-O9) -> -223100 | AU9: =SUM(M9*0.09) -> 522000 | AV9: =SUM(AT9:AU9)/2 -> 149450 | AW9: =AV9-(AV9*10%) -> 134505 | AX9: 50000 | AZ9: =SUM(AW9-AX9-AY9) -> 84505
A10: 9 | B10: 45986 | C10: A4 2.0 TDI | D10: 23누7083 | E10: WAUZZZ8K8EA084462 | F10: 카카오토샵 / 김대환 | H10: AUTO-ANDI | I10: Andi Cereku | J10: M34710201A | K10: 696688738 | L10: Albania | M10: 6840000 | N10: 0 | O10: =M10+N10 -> 6840000 | P10: USD | Q10: 출고 | R10: 완 | S10: 입금완료 | T10: 4680 | U10: 1455 | V10: 1670 | Z10: =SUM(T10,V10:Y10) -> 6350 | AA10: =SUM(AF10+AH10+AJ10+AK10-AL10) -> 0 | AB10: =SUM(AA10-Z10) -> -6350 | AM10: 35000 | AN10: 30000 | AR10: =SUM(AM10:AQ10) -> 65000 | AS10: =SUM(Z10-V10)*U10-AR10 -> 6744400 | AT10: =SUM(AS10-O10) -> -95600 | AU10: =SUM(M10*0.09) -> 615600 | AV10: =SUM(AT10:AU10)/2 -> 260000 | AW10: =AV10-(AV10*10%) -> 234000 | AX10: 50000 | AZ10: =SUM(AW10-AX10-AY10) -> 184000 | BA10: 0
A11: 10 | B11: 45986 | C11: TUCSON | D11: 60너2048 | E11: KMHJU81VBAU079072 | F11: 서청주자동차 / 이태곤 | H11: AUTO-ANDI | I11: Andi Cereku | J11: M34710201A | K11: 696688738 | L11: Albania | M11: 4850000 | N11: 0 | O11: =M11+N11 -> 4850000 | P11: USD | Q11: 출고 | R11: 완 | S11: 입금완료 | T11: 3430 | U11: 1455 | V11: 1770 | Z11: =SUM(T11,V11:Y11) -> 5200 | AA11: =SUM(AF11+AH11+AJ11+AK11-AL11) -> 0 | AB11: =SUM(AA11-Z11) -> -5200 | AM11: 35000 | AN11: 30000 | AR11: =SUM(AM11:AQ11) -> 65000 | AS11: =SUM(Z11-V11)*U11-AR11 -> 4925650 | AT11: =SUM(AS11-O11) -> 75650 | AU11: =SUM(M11*0.09) -> 436500 | AV11: =SUM(AT11:AU11)/2 -> 256075 | AW11: =AV11-(AV11*10%) -> 230467.5 | AX11: 50000 | AZ11: =SUM(AW11-AX11-AY11) -> 180467.5 | BA11: 0
A12: 11 | B12: 45989 | C12: TIGUAN | D12: 17두 7937 | E12: WVGZZZ5NZJW932354 | F12: 리본카 최은선 | H12: Faturat Net Sh.p.k | I12: Faturat Net Sh.p.k | J12: 811577636 | K12: +38349930085, +38344371274 | L12: Kosovo | M12: 21140000 | N12: 0 | O12: =M12+N12 -> 21140000 | P12: USD | Q12: 출고 | R12: 완 | S12: 입금완료 | T12: 13880 | U12: 1448 | V12: 1770 | Z12: =SUM(T12,V12:Y12) -> 15650 | AA12: =SUM(AF12+AH12+AJ12+AK12-AL12) -> 0 | AB12: =SUM(AA12-Z12) -> -15650 | AM12: 35000 | AN12: 30000 | AR12: =SUM(AM12:AQ12) -> 65000 | AS12: =SUM(Z12-V12)*U12-AR12 -> 20033240 | AT12: =SUM(AS12-O12) -> -1106760 | AU12: =SUM(M12*0.09) -> 1902600 | AV12: =SUM(AT12:AU12)/2 -> 397920 | AW12: =AV12-(AV12*10%) -> 358128 | AX12: 50000 | AZ12: =SUM(AW12-AX12-AY12) -> 308128 | BA12: 0
A13: 12 | B13: 46358 | C13: TIGUAN | D13: 252너3597 | E13: WVGZZZ5NZJW951937 | F13: 우리모터스 지경철 | H13: Faturat Net Sh.p.k | I13: Faturat Net Sh.p.k | J13: 811577636 | K13: +38349930085, +38344371274 | L13: Kosovo | M13: 18000000 | N13: 300000 | O13: =M13+N13 -> 18300000 | P13: USD | Q13: 출고 | R13: 완 | S13: 입금완료 | T13: 12075 | U13: 1456 | V13: 1770 | Z13: =SUM(T13,V13:Y13) -> 13845 | AA13: =SUM(AF13+AH13+AJ13+AK13-AL13) -> 0 | AB13: =SUM(AA13-Z13) -> -13845 | AM13: 35000 | AN13: 30000 | AR13: =SUM(AM13:AQ13) -> 65000 | AS13: =SUM(Z13-V13)*U13-AR13 -> 17516200 | AT13: =SUM(AS13-O13) -> -783800 | AU13: =SUM(M13*0.09) -> 1620000 | AV13: =SUM(AT13:AU13)/2 -> 418100 | AW13: =AV13-(AV13*10%) -> 376290 | AX13: 50000 | AZ13: =SUM(AW13-AX13-AY13) -> 326290
A14: 13 | B14: 45999 | C14: A6 | D14: 28러9364 | E14: WAUZZZ4G1CN123674 | F14: 다정자동차 / 이경범 | H14: AUTO-ANDI | I14: Andi Cereku | J14: M34710201A | K14: 696688738 | L14: Albania | M14: 5600000 | N14: 0 | O14: =M14+N14 -> 5600000 | P14: USD | Q14: 출고 | R14: 완 | S14: 입금완료 | T14: 3930 | U14: 1461 | V14: 1670 | Z14: =SUM(T14,V14:Y14) -> 5600 | AA14: =SUM(AF14+AH14+AJ14+AK14-AL14) -> 0 | AB14: =SUM(AA14-Z14) -> -5600 | AM14: 35000 | AN14: 30000 | AR14: =SUM(AM14:AQ14) -> 65000 | AS14: =SUM(Z14-V14)*U14-AR14 -> 5676730 | AT14: =SUM(AS14-O14) -> 76730 | AU14: =SUM(M14*0.09) -> 504000 | AV14: =SUM(AT14:AU14)/2 -> 290365 | AW14: =AV14-(AV14*10%) -> 261328.5 | AX14: 50000 | AZ14: =SUM(AW14-AX14-AY14) -> 211328.5
A15: 14 | B15: 46002 | C15: TUCSON | D15: 11고5126 | E15: KMHJ381ABGU010115 | F15: 대양모터스 / 김남길 | H15: AUTO-ANDI | I15: Andi Cereku | J15: M34710201A | K15: 696688738 | L15: Albania | M15: 8100000 | N15: 440000 | O15: =M15+N15 -> 8540000 | P15: USD | Q15: 출고 | R15: 완 | S15: 입금완료 | T15: 5630 | U15: 1453 | V15: 1770 | Z15: =SUM(T15,V15:Y15) -> 7400 | AA15: =SUM(AF15+AH15+AJ15+AK15-AL15) -> 0 | AB15: =SUM(AA15-Z15) -> -7400 | AM15: 35000 | AN15: 30000 | AR15: =SUM(AM15:AQ15) -> 65000 | AS15: =SUM(Z15-V15)*U15-AR15 -> 8115390 | AT15: =SUM(AS15-O15) -> -424610 | AU15: =SUM(M15*0.09) -> 729000 | AV15: =SUM(AT15:AU15)/2 -> 152195 | AW15: =AV15-(AV15*10%) -> 136975.5 | AX15: 50000 | AZ15: =SUM(AW15-AX15-AY15) -> 86975.5
A16: 15 | B16: 46002 | C16: Grand Cherokee | D16: 68우 8964 | E16: 1J8HR58N27C686873 | F16: 다정모터스 / 김효남 | H16: AUTO-ANDI | I16: Andi Cereku | J16: M34710201A | K16: 696688738 | L16: Albania | M16: 4900000 | N16: 0 | O16: =M16+N16 -> 4900000 | P16: USD | Q16: 출고 | R16: 완 | S16: 입금완료 | T16: 3430 | U16: 1453 | V16: 1870 | Z16: =SUM(T16,V16:Y16) -> 5300 | AA16: =SUM(AF16+AH16+AJ16+AK16-AL16) -> 0 | AB16: =SUM(AA16-Z16) -> -5300 | AM16: 35000 | AN16: 30000 | AR16: =SUM(AM16:AQ16) -> 65000 | AS16: =SUM(Z16-V16)*U16-AR16 -> 4918790 | AT16: =SUM(AS16-O16) -> 18790 | AU16: =SUM(M16*0.09) -> 441000 | AV16: =SUM(AT16:AU16)/2 -> 229895 | AW16: =AV16-(AV16*10%) -> 206905.5 | AX16: 50000 | AZ16: =SUM(AW16-AX16-AY16) -> 156905.5
A17: 16 | B17: 46005 | C17: PORTER | D17: 841더3420 | E17: KMFZCZ7KAEU969321 | F17: 드림카마켓 / 이승호 | H17: AUTO-ANDI | I17: Andi Cereku | J17: M34710201A | K17: 696688738 | L17: Albania | M17: 5400000 | N17: 0 | O17: =M17+N17 -> 5400000 | P17: USD | Q17: 출고 | R17: 완 | S17: 입금완료 | T17: 3730 | U17: 1463 | V17: 1870 | Z17: =SUM(T17,V17:Y17) -> 5600 | AA17: =SUM(AF17+AH17+AJ17+AK17-AL17) -> 0 | AB17: =SUM(AA17-Z17) -> -5600 | AM17: 35000 | AN17: 30000 | AR17: =SUM(AM17:AQ17) -> 65000 | AS17: =SUM(Z17-V17)*U17-AR17 -> 5391990 | AT17: =SUM(AS17-O17) -> -8010 | AU17: =SUM(M17*0.09) -> 486000 | AV17: =SUM(AT17:AU17)/2 -> 238995 | AW17: =AV17-(AV17*10%) -> 215095.5 | AX17: 50000 | AZ17: =SUM(AW17-AX17-AY17) -> 165095.5
A18: 17 | B18: 46015 | C18: A6 3.0 TDI | D18: 39수0127 | E18: WAUZZZ4G3DN066671 | F18: 솔카 / 남승우 | H18: AUTO-ANDI | I18: Andi Cereku | J18: M34710201A | K18: 696688738 | L18: Albania | M18: 4800000 | N18: 440000 | O18: =M18+N18 -> 5240000 | P18: USD | Q18: 출고 | R18: 완 | S18: 입금완료 | T18: 4030 | U18: 1443 | V18: 1670 | Z18: =SUM(T18,V18:Y18) -> 5700 | AA18: =SUM(AF18+AH18+AJ18+AK18-AL18) -> 0 | AB18: =SUM(AA18-Z18) -> -5700 | AM18: 35000 | AN18: 30000 | AR18: =SUM(AM18:AQ18) -> 65000 | AS18: =SUM(Z18-V18)*U18-AR18 -> 5750290 | AT18: =SUM(AS18-O18) -> 510290 | AU18: =SUM(M18*0.09) -> 432000 | AV18: =SUM(AT18:AU18)/2 -> 471145 | AW18: =AV18-(AV18*10%) -> 424030.5 | AX18: 50000 | AZ18: =SUM(AW18-AX18-AY18) -> 374030.5
A19: 18 | B19: 46015 | C19: A6 3.0 TDI | D19: 56버0718 | E19: WAUZZZ4GXGN144836 | F19: 시대모터스 / 원종길 | H19: Faturat Net Sh.p.k | I19: Faturat Net Sh.p.k | J19: 811577636 | K19: +38349930085, +38344371274 | L19: Kosovo | M19: 14900000 | N19: 0 | O19: =M19+N19 -> 14900000 | P19: USD | Q19: 출고 | R19: 완 | S19: 입금완료 | T19: 9930 | U19: 1443 | V19: 1670 | Z19: =SUM(T19,V19:Y19) -> 11600 | AA19: =SUM(AF19+AH19+AJ19+AK19-AL19) -> 0 | AB19: =SUM(AA19-Z19) -> -11600 | AM19: 35000 | AN19: 30000 | AR19: =SUM(AM19:AQ19) -> 65000 | AS19: =SUM(Z19-V19)*U19-AR19 -> 14263990 | AT19: =SUM(AS19-O19) -> -636010 | AU19: =SUM(M19*0.09) -> 1341000 | AV19: =SUM(AT19:AU19)/2 -> 352495 | AW19: =AV19-(AV19*10%) -> 317245.5 | AX19: 50000 | AZ19: =SUM(AW19-AX19-AY19) -> 267245.5
A20: 19 | B20: 46015 | C20: TIGUAN | D20: 19거3283 | E20: WVGZZZ5NZCW593157 | F20: 수호모터스 / 배현진 | H20: AUTO-ANDI | I20: Andi Cereku | J20: M34710201A | K20: 696688738 | L20: Albania | M20: 6700000 | N20: 440000 | O20: =M20+N20 -> 7140000 | P20: USD | Q20: 출고 | R20: 완 | S20: 입금완료 | T20: 4830 | U20: 1443 | V20: 1770 | Z20: =SUM(T20,V20:Y20) -> 6600 | AA20: =SUM(AF20+AH20+AJ20+AK20-AL20) -> 0 | AB20: =SUM(AA20-Z20) -> -6600 | AM20: 35000 | AN20: 30000 | AR20: =SUM(AM20:AQ20) -> 65000 | AS20: =SUM(Z20-V20)*U20-AR20 -> 6904690 | AT20: =SUM(AS20-O20) -> -235310 | AU20: =SUM(M20*0.09) -> 603000 | AV20: =SUM(AT20:AU20)/2 -> 183845 | AW20: =AV20-(AV20*10%) -> 165460.5 | AX20: 50000 | AZ20: =SUM(AW20-AX20-AY20) -> 115460.5
A21: 20 | B21: 46015 | C21: TIGUAN | D21: 15노9510 | E21: WVGZZZ5NZGW534985 | F21: 오토웨이브 / 이문주 | H21: AUTO-ANDI | I21: Andi Cereku | J21: M34710201A | K21: 696688738 | L21: Albania | M21: 5400000 | N21: 0 | O21: =M21+N21 -> 5400000 | P21: USD | Q21: 출고 | R21: 완 | S21: 입금완료 | T21: 3730 | U21: 1443 | V21: 1770 | Z21: =SUM(T21,V21:Y21) -> 5500 | AA21: =SUM(AF21+AH21+AJ21+AK21-AL21) -> 0 | AB21: =SUM(AA21-Z21) -> -5500 | AM21: 35000 | AN21: 30000 | AR21: =SUM(AM21:AQ21) -> 65000 | AS21: =SUM(Z21-V21)*U21-AR21 -> 5317390 | AT21: =SUM(AS21-O21) -> -82610 | AU21: =SUM(M21*0.09) -> 486000 | AV21: =SUM(AT21:AU21)/2 -> 201695 | AW21: =AV21-(AV21*10%) -> 181525.5 | AX21: 50000
A22: 21 | B22: 46024 | C22: 320D GT | D22: 54라5106 | E22: WBA8T5103H816870 | F22: 태양모터스 / 이은선 | H22: Faturat Net Sh.p.k | I22: Faturat Net Sh.p.k | J22: 811577636 | K22: +38349930085, +38344371274 | L22: Kosovo | M22: 16400000 | N22: 440000 | O22: =M22+N22 -> 16840000 | P22: USD | Q22: 출고 | R22: 완 | S22: 입금완료 | T22: 11330 | U22: 1430 | V22: 1670 | Z22: =SUM(T22,V22:Y22) -> 13000 | AA22: =SUM(AF22+AH22+AJ22+AK22-AL22) -> 0 | AB22: =SUM(AA22-Z22) -> -13000 | AM22: 35000 | AN22: 30000 | AR22: =SUM(AM22:AQ22) -> 65000 | AS22: =SUM(Z22-V22)*U22-AR22 -> 16136900 | AT22: =SUM(AS22-O22) -> -703100 | AU22: =SUM(M22*0.09) -> 1476000 | AV22: =SUM(AT22:AU22)/2 -> 386450 | AW22: =AV22-(AV22*10%) -> 347805 | AX22: 50000 | AZ22: =SUM(AW22-AX22-AY22) -> 297805
A23: 22 | B23: 46024 | C23: TIGUAN | D23: 57어2189 | E23: WVGZZZ5NZEW568536 | F23: 제이모션 / 안태건 | H23: AUTO-ANDI | I23: Andi Cereku | J23: M34710201A | K23: 696688738 | L23: Albania | M23: 7600000 | N23: 0 | O23: =M23+N23 -> 7600000 | P23: USD | Q23: 출고 | R23: 완 | S23: 입금완료 | T23: 5230 | U23: 1426 | V23: 1770 | Z23: =SUM(T23,V23:Y23) -> 7000 | AA23: =SUM(AF23+AH23+AJ23+AK23-AL23) -> 0 | AB23: =SUM(AA23-Z23) -> -7000 | AM23: 35000 | AN23: 30000 | AR23: =SUM(AM23:AQ23) -> 65000 | AS23: =SUM(Z23-V23)*U23-AR23 -> 7392980 | AT23: =SUM(AS23-O23) -> -207020 | AU23: =SUM(M23*0.09) -> 684000 | AV23: =SUM(AT23:AU23)/2 -> 238490 | AW23: =AV23-(AV23*10%) -> 214641 | AX23: 50000 | AZ23: =SUM(AW23-AX23-AY23) -> 164641
A24: 23 | B24: 46024 | C24: TIGUAN | D24: 35버1628 | E24: WVGZZZ5NZBW045756 | F24: 이삼두 | H24: AUTO-ANDI | I24: Andi Cereku | J24: M34710201A | K24: 696688738 | L24: Albania | M24: 4000000 | N24: 0 | O24: =M24+N24 -> 4000000 | P24: USD | Q24: 출고 | R24: 완 | S24: 입금완료 | T24: 2930 | U24: 1430 | V24: 1770 | Z24: =SUM(T24,V24:Y24) -> 4700 | AA24: =SUM(AF24+AH24+AJ24+AK24-AL24) -> 0 | AB24: =SUM(AA24-Z24) -> -4700 | AD24: 개인 매입 건 | AM24: 35000 | AN24: 30000 | AR24: =SUM(AM24:AQ24) -> 65000 | AS24: =SUM(Z24-V24)*U24-AR24 -> 4124900 | AT24: =SUM(AS24-O24) -> 124900 | AU24: =SUM(M24*0.09) -> 360000 | AV24: =SUM(AT24:AU24)/2 -> 242450 | AW24: =AV24-(AV24*10%) -> 218205 | AX24: 50000 | AZ24: =SUM(AW24-AX24-AY24) -> 168205
A25: 24 | B25: 46027 | C25: TIGUAN | D25: 23두3351 | E25: WVGZZZ5NZDW604961 | F25: 유레카 / 박경철 | H25: AUTO-ANDI | I25: Andi Cereku | J25: M34710201A | K25: 696688738 | L25: Albania | M25: 6200000 | N25: 440000 | O25: =M25+N25 -> 6640000 | P25: USD | Q25: 출고 | R25: 완 | S25: 입금완료 | T25: 4880 | U25: 1435 | V25: 1770 | Z25: =SUM(T25,V25:Y25) -> 6650 | AA25: =SUM(AF25+AH25+AJ25+AK25-AL25) -> 0 | AB25: =SUM(AA25-Z25) -> -6650 | AM25: 35000 | AN25: 30000 | AR25: =SUM(AM25:AQ25) -> 65000 | AS25: =SUM(Z25-V25)*U25-AR25 -> 6937800 | AT25: =SUM(AS25-O25) -> 297800 | AU25: =SUM(M25*0.09) -> 558000 | AV25: =SUM(AT25:AU25)/2 -> 427900 | AW25: =AV25-(AV25*10%) -> 385110 | AX25: 50000 | AZ25: =SUM(AW25-AX25-AY25) -> 335110
A26: 25 | B26: 46028 | C26: Q5 | D26: 63무0374 | E26: WAUZZZ8R5F114452 | F26: 다정모터스 / 김다정 | H26: AUTO-ANDI | I26: Andi Cereku | J26: M34710201A | K26: 696688738 | L26: Albania | M26: 9500000 | N26: 0 | O26: =M26+N26 -> 9500000 | P26: USD | Q26: 출고 | R26: 완 | S26: 입금완료 | T26: 6530 | U26: 1435 | V26: 1770 | Z26: =SUM(T26,V26:Y26) -> 8300 | AA26: =SUM(AF26+AH26+AJ26+AK26-AL26) -> 0 | AB26: =SUM(AA26-Z26) -> -8300 | AM26: 35000 | AN26: 30000 | AR26: =SUM(AM26:AQ26) -> 65000 | AS26: =SUM(Z26-V26)*U26-AR26 -> 9305550 | AT26: =SUM(AS26-O26) -> -194450 | AU26: =SUM(M26*0.09) -> 855000 | AV26: =SUM(AT26:AU26)/2 -> 330275 | AW26: =AV26-(AV26*10%) -> 297247.5 | AX26: 50000 | AZ26: =SUM(AW26-AX26-AY26) -> 247247.5
A27: 26 | B27: 46028 | C27: QM6 | D27: 21도7330 | E27: KNME5C2M2HP011609 | F27: 카즈모터스 / 손성연 | H27: Faturat Net Sh.p.k | I27: Faturat Net Sh.p.k | J27: 811577636 | K27: +38349930085, +38344371274 | L27: Kosovo | M27: 8500000 | N27: 0 | O27: =M27+N27 -> 8500000 | P27: USD | Q27: 출고 | R27: 완 | S27: 입금완료 | T27: 5980 | U27: 1432 | V27: 1770 | Z27: =SUM(T27,V27:Y27) -> 7750 | AA27: =SUM(AF27+AH27+AJ27+AK27-AL27) -> 0 | AB27: =SUM(AA27-Z27) -> -7750 | AM27: 35000 | AN27: 30000 | AR27: =SUM(AM27:AQ27) -> 65000 | AS27: =SUM(Z27-V27)*U27-AR27 -> 8498360 | AT27: =SUM(AS27-O27) -> -1640 | AU27: =SUM(M27*0.09) -> 765000 | AV27: =SUM(AT27:AU27)/2 -> 381680 | AW27: =AV27-(AV27*10%) -> 343512 | AX27: 50000 | AZ27: =SUM(AW27-AX27-AY27) -> 293512
A28: 27 | B28: 46028 | C28: TUCSON | D28: 68주5530 | E28: KMHJ3815GGU067550 | F28: 삼일모터스 / 박홍균 | H28: AUTO-ANDI | I28: Andi Cereku | J28: M34710201A | K28: 696688738 | L28: Albania | M28: 6500000 | N28: 0 | O28: =M28+N28 -> 6500000 | P28: USD | Q28: 출고 | R28: 완 | S28: 입금완료 | T28: 4530 | U28: 1435 | V28: 1770 | Z28: =SUM(T28,V28:Y28) -> 6300 | AA28: =SUM(AF28+AH28+AJ28+AK28-AL28) -> 0 | AB28: =SUM(AA28-Z28) -> -6300 | AM28: 35000 | AN28: 30000 | AR28: =SUM(AM28:AQ28) -> 65000 | AS28: =SUM(Z28-V28)*U28-AR28 -> 6435550 | AT28: =SUM(AS28-O28) -> -64450 | AU28: =SUM(M28*0.09) -> 585000 | AV28: =SUM(AT28:AU28)/2 -> 260275 | AW28: =AV28-(AV28*10%) -> 234247.5 | AX28: 50000 | AZ28: =SUM(AW28-AX28-AY28) -> 184247.5
A29: 28 | B29: 46030 | C29: A6 45 TDI | D29: 243도6391 | E29: WAUZZZF25LN051265 | F29: 스카이모터스 원주희 | H29: AUTO-ANDI | I29: Andi Cereku | J29: M34710201A | K29: 696688738 | L29: Albania | M29: 31200000 | N29: 0 | O29: =M29+N29 -> 31200000 | P29: USD | Q29: 출고 | R29: 완 | S29: 입금완료 | T29: 20830 | U29: 1435 | V29: 1670 | Z29: =SUM(T29,V29:Y29) -> 22500 | AA29: =SUM(AF29+AH29+AJ29+AK29-AL29) -> 0 | AB29: =SUM(AA29-Z29) -> -22500 | AM29: 35000 | AN29: 30000 | AR29: =SUM(AM29:AQ29) -> 65000 | AS29: =SUM(Z29-V29)*U29-AR29 -> 29826050 | AT29: =SUM(AS29-O29) -> -1373950 | AU29: =SUM(M29*0.09) -> 2808000 | AV29: =SUM(AT29:AU29)/2 -> 717025 | AW29: =AV29-(AV29*10%) -> 645322.5 | AX29: 50000 | AZ29: =SUM(AW29-AX29-AY29) -> 595322.5
A30: 29 | B30: 46031 | C30: Velar D300 | D30: 46라2219 | E30: SALYA2BK1JA732832 | F30: 아이오토스 / 선민중 | H30: Faturat Net Sh.p.k | I30: Faturat Net Sh.p.k | J30: 811577636 | K30: +38349930085, +38344371274 | L30: Kosovo | M30: 32660000 | N30: 0 | O30: =M30+N30 -> 32660000 | P30: USD | Q30: 출고 | R30: 완 | S30: 입금완료 | T30: 22030 | U30: 1435 | Z30: =SUM(T30,V30:Y30) -> 22030 | AA30: =SUM(AF30+AH30+AJ30+AK30-AL30) -> 0 | AB30: =SUM(AA30-Z30) -> -22030 | AM30: 35000 | AN30: 30000 | AR30: =SUM(AM30:AQ30) -> 65000 | AS30: =SUM(Z30-V30)*U30-AR30 -> 31548050 | AT30: =SUM(AS30-O30) -> -1111950 | AU30: =SUM(M30*0.09) -> 2939400 | AV30: =SUM(AT30:AU30)/2 -> 913725 | AW30: =AV30-(AV30*10%) -> 822352.5 | AX30: 50000 | AZ30: =SUM(AW30-AX30-AY30) -> 772352.5
A31: 30 | B31: 46032 | C31: A6 40 TDI | D31: 35다0560 | E31: WAUZZZ4GXGN021988 | F31: 강창희 | H31: AUTO-ANDI | I31: Andi Cereku | J31: M34710201A | K31: 696688738 | L31: Albania | M31: 7100000 | N31: 0 | O31: =M31+N31 -> 7100000 | P31: USD | Q31: 출고 | R31: 완 | S31: 입금완료 | T31: 5230 | U31: 1439 | V31: 1670 | Z31: =SUM(T31,V31:Y31) -> 6900 | AA31: =SUM(AF31+AH31+AJ31+AK31-AL31) -> 0 | AB31: =SUM(AA31-Z31) -> -6900 | AM31: 35000 | AN31: 30000 | AR31: =SUM(AM31:AQ31) -> 65000 | AS31: =SUM(Z31-V31)*U31-AR31 -> 7460970 | AT31: =SUM(AS31-O31) -> 360970 | AU31: =SUM(M31*0.09) -> 639000 | AV31: =SUM(AT31:AU31)/2 -> 499985 | AW31: =AV31-(AV31*10%) -> 449986.5 | AX31: 50000 | AZ31: =SUM(AW31-AX31-AY31) -> 399986.5
A32: 31 | B32: 46035 | C32: C-CLASS | D32: 47소5093 | E32: WDDWF0EB6FF125289 | F32: 셀링오토 곽철희 | H32: AUTO-ANDI | I32: Andi Cereku | J32: M34710201A | K32: 696688738 | L32: Albania | M32: 10400000 | N32: 0 | O32: =M32+N32 -> 10400000 | P32: USD | Q32: 출고 | R32: 완 | S32: 입금완료 | T32: 7030 | U32: 1465 | V32: 1670 | Z32: =SUM(T32,V32:Y32) -> 8700 | AA32: =SUM(AF32+AH32+AJ32+AK32-AL32) -> 0 | AB32: =SUM(AA32-Z32) -> -8700 | AM32: 35000 | AN32: 30000 | AR32: =SUM(AM32:AQ32) -> 65000 | AS32: =SUM(Z32-V32)*U32-AR32 -> 10233950 | AT32: =SUM(AS32-O32) -> -166050 | AU32: =SUM(M32*0.09) -> 936000 | AV32: =SUM(AT32:AU32)/2 -> 384975 | AW32: =AV32-(AV32*10%) -> 346477.5 | AX32: 50000 | AZ32: =SUM(AW32-AX32-AY32) -> 296477.5
A33: 32 | B33: 46037 | C33: Q5 | D33: 63버1609 | E33: WAUZZZ8R8FA064534 | F33: 주식회사 회성무역 | H33: AUTO-ANDI | I33: Andi Cereku | J33: M34710201A | K33: 696688738 | L33: Albania | M33: 8600000 | N33: 0 | O33: =M33+N33 -> 8600000 | P33: USD | Q33: 출고 | R33: 완 | S33: 입금완료 | T33: 5930 | U33: 1465 | V33: 1770 | Z33: =SUM(T33,V33:Y33) -> 7700 | AA33: =SUM(AF33+AH33+AJ33+AK33-AL33) -> 0 | AB33: =SUM(AA33-Z33) -> -7700 | AM33: 35000 | AN33: 30000 | AR33: =SUM(AM33:AQ33) -> 65000 | AS33: =SUM(Z33-V33)*U33-AR33 -> 8622450 | AT33: =SUM(AS33-O33) -> 22450 | AU33: =SUM(M33*0.09) -> 774000 | AV33: =SUM(AT33:AU33)/2 -> 398225 | AW33: =AV33-(AV33*10%) -> 358402.5 | AX33: 50000 | AZ33: =SUM(AW33-AX33-AY33) -> 308402.5
A34: 33 | B34: 46049 | C34: 320D GT | D34: 38거3214 | E34: WBA8T5102JG819703 | F34: MS 모터스 / 황용연 | H34: Faturat Net Sh.p.k | I34: Faturat Net Sh.p.k | J34: 811577636 | K34: +38349930085, +38344371274 | L34: Kosovo | M34: 10500000 | N34: 0 | O34: =M34+N34 -> 10500000 | P34: USD | Q34: 출고 | R34: 완 | S34: 입금완료 | T34: 7080 | U34: 1454 | Z34: =SUM(T34,V34:Y34) -> 7080 | AA34: =SUM(AF34+AH34+AJ34+AK34-AL34) -> 0 | AB34: =SUM(AA34-Z34) -> -7080 | AM34: 35000 | AN34: 30000 | AR34: =SUM(AM34:AQ34) -> 65000 | AS34: =SUM(Z34-V34)*U34-AR34 -> 10229320 | AT34: =SUM(AS34-O34) -> -270680 | AU34: =SUM(M34*0.09) -> 945000 | AV34: =SUM(AT34:AU34)/2 -> 337160 | AW34: =AV34-(AV34*10%) -> 303444 | AX34: 50000 | AZ34: =SUM(AW34-AX34-AY34) -> 253444
A35: 34 | B35: 46054 | C35: A7 45 TDI | D35: 54서2846 | E35: WAUZZZ4G9FN006056 | F35: 셀링오토 / 곽철희 | H35: AUTO-ANDI | I35: Andi Cereku | J35: M34710201A | K35: 696688738 | L35: Albania | M35: 8300000 | N35: 0 | O35: =M35+N35 -> 8300000 | P35: USD | Q35: 출고 | R35: 완 | S35: 입금완료 | T35: 5930 | U35: 1439 | V35: 1670 | Z35: =SUM(T35,V35:Y35) -> 7600 | AA35: =SUM(AF35+AH35+AJ35+AK35-AL35) -> 0 | AB35: =SUM(AA35-Z35) -> -7600 | AM35: 35000 | AN35: 30000 | AR35: =SUM(AM35:AQ35) -> 65000 | AS35: =SUM(Z35-V35)*U35-AR35 -> 8468270 | AT35: =SUM(AS35-O35) -> 168270 | AU35: =SUM(M35*0.09) -> 747000 | AV35: =SUM(AT35:AU35)/2 -> 457635 | AW35: =AV35-(AV35*10%) -> 411871.5 | AX35: 50000 | AZ35: =SUM(AW35-AX35-AY35) -> 361871.5
A36: 35 | B36: 46054 | C36: C-CLASS | D36: 362다7392 | E36: WDDWF0EB7FF111353 | F36: 하이앤드모터스 / 배형빈 | H36: AUTO-ANDI | I36: Andi Cereku | J36: M34710201A | K36: 696688738 | L36: Albania | M36: 11800000 | N36: 0 | O36: =M36+N36 -> 11800000 | P36: USD | Q36: 출고 | R36: 완 | S36: 입금완료 | T36: 7980 | U36: 1439 | V36: 1670 | Z36: =SUM(T36,V36:Y36) -> 9650 | AA36: =SUM(AF36+AH36+AJ36+AK36-AL36) -> 0 | AB36: =SUM(AA36-Z36) -> -9650 | AM36: 35000 | AN36: 30000 | AR36: =SUM(AM36:AQ36) -> 65000 | AS36: =SUM(Z36-V36)*U36-AR36 -> 11418220 | AT36: =SUM(AS36-O36) -> -381780 | AU36: =SUM(M36*0.09) -> 1062000 | AV36: =SUM(AT36:AU36)/2 -> 340110 | AW36: =AV36-(AV36*10%) -> 306099 | AX36: 50000 | AZ36: =SUM(AW36-AX36-AY36) -> 256099
A37: 36 | B37: 46056 | C37: GLE350 D | D37: 33너2761 | E37: WDCED2EB4HA069189 | F37: 대박모터스 / 윤창기 | H37: AUTO-ANDI | I37: Andi Cereku | J37: M34710201A | K37: 696688738 | L37: Albania | M37: 27700000 | N37: 0 | O37: =M37+N37 -> 27700000 | P37: USD | Q37: 출고 | R37: 완 | S37: 입금완료 | T37: 18330 | U37: 1439 | V37: 1870 | Z37: =SUM(T37,V37:Y37) -> 20200 | AA37: =SUM(AF37+AH37+AJ37+AK37-AL37) -> 0 | AB37: =SUM(AA37-Z37) -> -20200 | AM37: 35000 | AN37: 30000 | AR37: =SUM(AM37:AQ37) -> 65000 | AS37: =SUM(Z37-V37)*U37-AR37 -> 26311870 | AT37: =SUM(AS37-O37) -> -1388130 | AU37: =SUM(M37*0.09) -> 2493000 | AV37: =SUM(AT37:AU37)/2 -> 552435 | AW37: =AV37-(AV37*10%) -> 497191.5 | AX37: 50000 | AZ37: =SUM(AW37-AX37-AY37) -> 447191.5
A38: 37 | B38: 46072 | C38: Passat GT 2.0TDI | D38: 280조1895 | E38: WWWZZZ3CZNE028333 | F38: 준모터스 / 김미란 | H38: Faturat Net Sh.p.k | I38: Faturat Net Sh.p.k | J38: 811577636 | K38: +38349930085, +38344371274 | L38: Kosovo | M38: 24400000 | N38: 0 | O38: =M38+N38 -> 24400000 | P38: USD | Q38: 출고 | R38: 완 | S38: 입금완료 | T38: 16630 | U38: 1436 | Z38: =SUM(T38,V38:Y38) -> 16630 | AA38: =SUM(AF38+AH38+AJ38+AK38-AL38) -> 0 | AB38: =SUM(AA38-Z38) -> -16630 | AM38: 35000 | AN38: 30000 | AR38: =SUM(AM38:AQ38) -> 65000 | AS38: =SUM(Z38-V38)*U38-AR38 -> 23815680 | AT38: =SUM(AS38-O38) -> -584320 | AU38: =SUM(M38*0.09) -> 2196000 | AV38: =SUM(AT38:AU38)/2 -> 805840 | AW38: =AV38-(AV38*10%) -> 725256 | AX38: 50000 | AZ38: =SUM(AW38-AX38-AY38) -> 675256
A39: 38 | B39: 46072 | C39: GRANDEUR | D39: 176다7273 | E39: KMHN341FBPA055016 | F39: 신원모터스 / 원도형 | H39: AUTO-ANDI | I39: Meta andi | J39: J00629078J | K39: 696688738 | L39: Albania | M39: 23200000 | N39: 0 | O39: =M39+N39 -> 23200000 | P39: USD | Q39: 출고 | R39: 완 | S39: 입금완료 | T39: 15480 | U39: 1436 | V39: 1370 | Z39: =SUM(T39,V39:Y39) -> 16850 | AA39: =SUM(AF39+AH39+AJ39+AK39-AL39) -> 0 | AB39: =SUM(AA39-Z39) -> -16850 | AM39: 35000 | AN39: 30000 | AR39: =SUM(AM39:AQ39) -> 65000 | AS39: =SUM(Z39-V39)*U39-AR39 -> 22164280 | AT39: =SUM(AS39-O39) -> -1035720 | AU39: =SUM(M39*0.09) -> 2088000 | AV39: =SUM(AT39:AU39)/2 -> 526140 | AW39: =AV39-(AV39*10%) -> 473526 | AX39: 50000 | AZ39: =SUM(AW39-AX39-AY39) -> 423526
A40: 39 | B40: 46076 | C40: A4 | D40: 64노9633 | E40: WAUZZZ8K9EA097754 | F40: 서진모터스 / 이수욱 | H40: AUTO-ANDI | I40: Markeci Federiko | J40: K80110056Q | K40: 696688738 | L40: Albania | M40: 5700000 | N40: 0 | O40: =M40+N40 -> 5700000 | Q40: 출고 | R40: 완 | S40: 입금완료 | T40: 3900 | U40: 1434 | V40: 1370 | Z40: =SUM(T40,V40:Y40) -> 5270 | AA40: =SUM(AF40+AH40+AJ40+AK40-AL40) -> 0 | AB40: =SUM(AA40-Z40) -> -5270 | AM40: 35000 | AN40: 30000 | AR40: =SUM(AM40:AQ40) -> 65000 | AS40: =SUM(Z40-V40)*U40-AR40 -> 5527600 | AT40: =SUM(AS40-O40) -> -172400 | AU40: =SUM(M40*0.09) -> 513000 | AV40: =SUM(AT40:AU40)/2 -> 170300 | AW40: =AV40-(AV40*10%) -> 153270 | AX40: 50000 | AZ40: =SUM(AW40-AX40-AY40) -> 103270
A41: 40 | B41: 46076 | C41: TIGUAN | D41: 08부3328 | E41: WVGZZZ5NZGW530185 | F41: 레인보우 / 김태균 | H41: AUTO-ANDI | I41: Markeci Federiko | J41: K80110056Q | K41: 696688738 | L41: Albania | M41: 6700000 | N41: 440000 | O41: =M41+N41 -> 7140000 | Q41: 출고 | R41: 완 | S41: 입금완료 | T41: 4930 | U41: 1434 | V41: 1470 | Z41: =SUM(T41,V41:Y41) -> 6400 | AA41: =SUM(AF41+AH41+AJ41+AK41-AL41) -> 0 | AB41: =SUM(AA41-Z41) -> -6400 | AM41: 35000 | AN41: 30000 | AR41: =SUM(AM41:AQ41) -> 65000 | AS41: =SUM(Z41-V41)*U41-AR41 -> 7004620 | AT41: =SUM(AS41-O41) -> -135380 | AU41: =SUM(M41*0.09) -> 603000 | AV41: =SUM(AT41:AU41)/2 -> 233810 | AW41: =AV41-(AV41*10%) -> 210429 | AX41: 50000 | AZ41: =SUM(AW41-AX41-AY41) -> 160429
A42: 41 | B42: 46076 | C42: TUCSON | D42: 32서1679 | E42: KMHJ381ABGU107203 | F42: 일등중고차 / 박종혁 | H42: AUTO-ANDI | I42: Andi Cereku | J42: M34710201A | K42: 696688738 | L42: Albania | M42: 7900000 | N42: 0 | O42: =M42+N42 -> 7900000 | Q42: 출고 | R42: 완 | S42: 입금완료 | T42: 5380 | U42: 1434 | V42: 1470 | Z42: =SUM(T42,V42:Y42) -> 6850 | AA42: =SUM(AF42+AH42+AJ42+AK42-AL42) -> 0 | AB42: =SUM(AA42-Z42) -> -6850 | AM42: 35000 | AN42: 30000 | AR42: =SUM(AM42:AQ42) -> 65000 | AS42: =SUM(Z42-V42)*U42-AR42 -> 7649920 | AT42: =SUM(AS42-O42) -> -250080 | AU42: =SUM(M42*0.09) -> 711000 | AV42: =SUM(AT42:AU42)/2 -> 230460 | AW42: =AV42-(AV42*10%) -> 207414 | AX42: 50000 | AZ42: =SUM(AW42-AX42-AY42) -> 157414
A43: 42 | B43: 46080 | C43: A6 | D43: 172서3544 | E43: WAUZZZF24LN027166 | F43: 에어라인오토 / 김수종 | H43: Faturat Net Sh.p.k | I43: Faturat Net Sh.p.k | J43: 811577636 | K43: +38349930085, +38344371274 | L43: Kosovo | M43: 31900000 | N43: 0 | O43: =M43+N43 -> 31900000 | Q43: 출고 | R43: 완 | S43: 입금완료 | T43: 21730 | U43: 1409 | V43: 1370 | Z43: =SUM(T43,V43:Y43) -> 23100 | AA43: =SUM(AF43+AH43+AJ43+AK43-AL43) -> 0 | AB43: =SUM(AA43-Z43) -> -23100 | AM43: 35000 | AN43: 30000 | AR43: =SUM(AM43:AQ43) -> 65000 | AS43: =SUM(Z43-V43)*U43-AR43 -> 30552570 | AT43: =SUM(AS43-O43) -> -1347430 | AU43: =SUM(M43*0.09) -> 2871000 | AV43: =SUM(AT43:AU43)/2 -> 761785 | AW43: =AV43-(AV43*10%) -> 685606.5 | AX43: 50000 | AZ43: =SUM(AW43-AX43-AY43) -> 635606.5
A44: 43 | B44: 46080 | C44: TIGUAN | D44: 184무2284 | E44: WVGZZZ5NEW506780 | F44: 대한모터스 / 김정우 | H44: AUTO-ANDI | I44: Andi Cereku | J44: M34710201A | K44: 696688738 | L44: Albania | M44: 5900000 | N44: 0 | O44: =M44+N44 -> 5900000 | Q44: 출고 | R44: 완 | S44: 입금완료 | T44: 4330 | U44: 1409 | V44: 1470 | Z44: =SUM(T44,V44:Y44) -> 5800 | AA44: =SUM(AF44+AH44+AJ44+AK44-AL44) -> 0 | AB44: =SUM(AA44-Z44) -> -5800 | AM44: 35000 | AN44: 30000 | AR44: =SUM(AM44:AQ44) -> 65000 | AS44: =SUM(Z44-V44)*U44-AR44 -> 6035970 | AT44: =SUM(AS44-O44) -> 135970 | AU44: =SUM(M44*0.09) -> 531000 | AV44: =SUM(AT44:AU44)/2 -> 333485 | AW44: =AV44-(AV44*10%) -> 300136.5 | AX44: 50000 | AZ44: =SUM(AW44-AX44-AY44) -> 250136.5
A45: 44 | B45: 46085 | C45: TIGUAN | D45: 116수7419 | E45: WVGZZZ5NZLW824483 | H45: Faturat Net Sh.p.k | I45: Faturat Net Sh.p.k | J45: 811577636 | K45: +38349930085, +38344371274 | L45: Kosovo | M45: 19200000 | N45: 440000 | O45: =M45+N45 -> 19640000 | Q45: 출고 | R45: 완 | S45: 입금완료 | T45: 12830 | U45: 1463 | V45: 1470 | Z45: =SUM(T45,V45:Y45) -> 14300 | AA45: =SUM(AF45+AH45+AJ45+AK45-AL45) -> 0 | AB45: =SUM(AA45-Z45) -> -14300 | AM45: 35000 | AN45: 30000 | AR45: =SUM(AM45:AQ45) -> 65000 | AS45: =SUM(Z45-V45)*U45-AR45 -> 18705290 | AT45: =SUM(AS45-O45) -> -934710 | AU45: =SUM(M45*0.09) -> 1728000 | AV45: =SUM(AT45:AU45)/2 -> 396645 | AW45: =AV45-(AV45*10%) -> 356980.5 | AX45: 50000 | AZ45: =SUM(AW45-AX45-AY45) -> 306980.5
A46: 45 | B46: 46085 | C46: A6 | D46: 397무3797 | E46: WAUZZZF25LN064453 | F46: 스카이모터스 / 송민서 | H46: Faturat Net Sh.p.k | I46: Faturat Net Sh.p.k | J46: 811577636 | K46: +38349930085, +38344371274 | L46: Kosovo | M46: 29900000 | N46: 0 | O46: =M46+N46 -> 29900000 | Q46: 출고 | R46: 완 | S46: 입금완료 | T46: 19530 | U46: 1463 | V46: 1370 | Z46: =SUM(T46,V46:Y46) -> 20900 | AA46: =SUM(AF46+AH46+AJ46+AK46-AL46) -> 0 | AB46: =SUM(AA46-Z46) -> -20900 | AM46: 35000 | AN46: 30000 | AR46: =SUM(AM46:AQ46) -> 65000 | AS46: =SUM(Z46-V46)*U46-AR46 -> 28507390 | AT46: =SUM(AS46-O46) -> -1392610 | AU46: =SUM(M46*0.09) -> 2691000 | AV46: =SUM(AT46:AU46)/2 -> 649195 | AW46: =AV46-(AV46*10%) -> 584275.5 | AX46: 50000 | AZ46: =SUM(AW46-AX46-AY46) -> 534275.5
A47: 46 | B47: 46086 | C47: SANTAFE | D47: 58루8645 | E47: KMHSW81UBDU091784 | F47: 카울렛 / 김진영 | H47: AUTO-ANDI | I47: Andi Cereku | J47: M34710201A | K47: 696688738 | L47: Albania | M47: 7100000 | N47: 0 | O47: =M47+N47 -> 7100000 | Q47: 출고 | R47: 완 | S47: 입금완료 | T47: 4730 | U47: 1463 | V47: 1470 | Z47: =SUM(T47,V47:Y47) -> 6200 | AA47: =SUM(AF47+AH47+AJ47+AK47-AL47) -> 0 | AB47: =SUM(AA47-Z47) -> -6200 | AM47: 35000 | AN47: 30000 | AR47: =SUM(AM47:AQ47) -> 65000 | AS47: =SUM(Z47-V47)*U47-AR47 -> 6854990 | AT47: =SUM(AS47-O47) -> -245010 | AU47: =SUM(M47*0.09) -> 639000 | AV47: =SUM(AT47:AU47)/2 -> 196995 | AW47: =AV47-(AV47*10%) -> 177295.5 | AX47: 50000 | AZ47: =SUM(AW47-AX47-AY47) -> 127295.5
A48: 47 | B48: 46086 | C48: SANTAFE | D48: 63마3976 | E48: KMHSW81XDDU170661 | F48: 인연모터스 / 김석원 | H48: AUTO-ANDI | I48: Andi Cereku | J48: M34710201A | K48: 696688738 | L48: Albania | M48: 6600000 | N48: 0 | O48: =M48+N48 -> 6600000 | Q48: 출고 | R48: 완 | S48: 입금완료 | T48: 4530 | U48: 1463 | V48: 1470 | Z48: =SUM(T48,V48:Y48) -> 6000 | AA48: =SUM(AF48+AH48+AJ48+AK48-AL48) -> 0 | AB48: =SUM(AA48-Z48) -> -6000 | AM48: 35000 | AN48: 30000 | AR48: =SUM(AM48:AQ48) -> 65000 | AS48: =SUM(Z48-V48)*U48-AR48 -> 6562390 | AT48: =SUM(AS48-O48) -> -37610 | AU48: =SUM(M48*0.09) -> 594000 | AV48: =SUM(AT48:AU48)/2 -> 278195 | AW48: =AV48-(AV48*10%) -> 250375.5 | AX48: 50000 | AZ48: =SUM(AW48-AX48-AY48) -> 200375.5
A49: 48 | B49: 46087 | C49: S60 | D49: 15오2380 | E49: YV1FS79B0J2463418 | F49: 차모터스 / 장현수 | H49: Faturat Net Sh.p.k | I49: Faturat Net Sh.p.k | J49: 811577636 | K49: +38349930085, +38344371274 | L49: Kosovo | M49: 7000000 | N49: 0 | O49: =M49+N49 -> 7000000 | Q49: 출고 | R49: 완 | S49: 입금완료 | T49: 4880 | U49: 1449 | V49: 1370 | Z49: =SUM(T49,V49:Y49) -> 6250 | AA49: =SUM(AF49+AH49+AJ49+AK49-AL49) -> 0 | AB49: =SUM(AA49-Z49) -> -6250 | AM49: 35000 | AN49: 30000 | AR49: =SUM(AM49:AQ49) -> 65000 | AS49: =SUM(Z49-V49)*U49-AR49 -> 7006120 | AT49: =SUM(AS49-O49) -> 6120 | AU49: =SUM(M49*0.09) -> 630000 | AV49: =SUM(AT49:AU49)/2 -> 318060 | AW49: =AV49-(AV49*10%) -> 286254 | AX49: 50000 | AZ49: =SUM(AW49-AX49-AY49) -> 236254
A50: 49 | B50: 46092 | C50: TUCSON | D50: 61수5927 | E50: KMHJ281ABGU011230 | F50: 엠앤제이오토모빌/ 공민은 | H50: AUTO-ANDI | I50: Andi Cereku | J50: M34710201A | K50: 696688738 | L50: Albania | M50: 9900000 | N50: 0 | O50: =M50+N50 -> 9900000 | Q50: 출고 | R50: 완 | S50: 입금완료 | T50: 6630 | U50: 1452 | V50: 1470 | Z50: =SUM(T50,V50:Y50) -> 8100 | AA50: =SUM(AF50+AH50+AJ50+AK50-AL50) -> 0 | AB50: =SUM(AA50-Z50) -> -8100 | AM50: 35000 | AN50: 30000 | AR50: =SUM(AM50:AQ50) -> 65000 | AS50: =SUM(Z50-V50)*U50-AR50 -> 9561760 | AT50: =SUM(AS50-O50) -> -338240 | AU50: =SUM(M50*0.09) -> 891000 | AV50: =SUM(AT50:AU50)/2 -> 276380 | AW50: =AV50-(AV50*10%) -> 248742 | AX50: 50000 | AZ50: =SUM(AW50-AX50-AY50) -> 198742
A51: 50 | B51: 46093 | C51: TUCSON | D51: 04너4140 | E51: KMHJ381ABHU474661 | F51: 하나모터스 / 이승태 | H51: AUTO-ANDI | I51: Andi Cereku | J51: M34710201A | K51: 696688738 | L51: Albania | M51: 11200000 | N51: 0 | O51: =M51+N51 -> 11200000 | Q51: 출고 | R51: 완 | S51: 입금완료 | T51: 7430 | U51: 1452 | V51: 1470 | Z51: =SUM(T51,V51:Y51) -> 8900 | AA51: =SUM(AF51+AH51+AJ51+AK51-AL51) -> 0 | AB51: =SUM(AA51-Z51) -> -8900 | AM51: 35000 | AN51: 30000 | AR51: =SUM(AM51:AQ51) -> 65000 | AS51: =SUM(Z51-V51)*U51-AR51 -> 10723360 | AT51: =SUM(AS51-O51) -> -476640 | AU51: =SUM(M51*0.09) -> 1008000 | AV51: =SUM(AT51:AU51)/2 -> 265680 | AW51: =AV51-(AV51*10%) -> 239112 | AX51: 50000 | AZ51: =SUM(AW51-AX51-AY51) -> 189112
A52: 51 | B52: 46096 | C52: A4 | D52: 57고9546 | E52: WAUZZZ8K1DN040360 | F52: 엠앤제이오토모빌/ 공민은 | H52: AUTO-ANDI | I52: Andi Cereku | J52: M34710201A | K52: 696688738 | L52: Albania | M52: 5700000 | N52: 0 | O52: =M52+N52 -> 5700000 | Q52: 출고 | R52: 완 | S52: 입금완료 | T52: 3830 | U52: 1484 | V52: 1370 | Z52: =SUM(T52,V52:Y52) -> 5200 | AA52: =SUM(AF52+AH52+AJ52+AK52-AL52) -> 0 | AB52: =SUM(AA52-Z52) -> -5200 | AM52: 35000 | AN52: 30000 | AR52: =SUM(AM52:AQ52) -> 65000 | AS52: =SUM(Z52-V52)*U52-AR52 -> 5618720 | AT52: =SUM(AS52-O52) -> -81280 | AU52: =SUM(M52*0.09) -> 513000 | AV52: =SUM(AT52:AU52)/2 -> 215860 | AW52: =AV52-(AV52*10%) -> 194274 | AX52: 50000 | AZ52: =SUM(AW52-AX52-AY52) -> 144274
A53: 52 | B53: 46096 | C53: A3 | D53: 63더6087 | E53: WAUZZZ8V7F1050752 | F53: 세이프티중고차 / 조성건 | H53: AUTO-ANDI | I53: Andi Cereku | J53: M34710201A | K53: 696688738 | L53: Albania | M53: 9100000 | N53: 0 | O53: =M53+N53 -> 9100000 | Q53: 출고 | R53: 완 | S53: 입금완료 | T53: 6030 | U53: 1484 | V53: 1370 | Z53: =SUM(T53,V53:Y53) -> 7400 | AA53: =SUM(AF53+AH53+AJ53+AK53-AL53) -> 0 | AB53: =SUM(AA53-Z53) -> -7400 | AM53: 35000 | AN53: 30000 | AR53: =SUM(AM53:AQ53) -> 65000 | AS53: =SUM(Z53-V53)*U53-AR53 -> 8883520 | AT53: =SUM(AS53-O53) -> -216480 | AU53: =SUM(M53*0.09) -> 819000 | AV53: =SUM(AT53:AU53)/2 -> 301260 | AW53: =AV53-(AV53*10%) -> 271134 | AX53: 50000 | AZ53: =SUM(AW53-AX53-AY53) -> 221134
A54: 53 | B54: 46096 | C54: GOLF | D54: 47두2956 | E54: WVWZZZAUZEW122285 | F54: 개인매입 | H54: AUTO-ANDI | I54: Andi Cereku | J54: M34710201A | K54: 696688738 | L54: Albania | M54: 7100000 | N54: 0 | O54: =M54+N54 -> 7100000 | Q54: 출고 | R54: 완 | S54: 입금완료 | T54: 4780 | U54: 1484 | V54: 1370 | Z54: =SUM(T54,V54:Y54) -> 6150 | AA54: =SUM(AF54+AH54+AJ54+AK54-AL54) -> 0 | AB54: =SUM(AA54-Z54) -> -6150 | AM54: 35000 | AN54: 30000 | AR54: =SUM(AM54:AQ54) -> 65000 | AS54: =SUM(Z54-V54)*U54-AR54 -> 7028520 | AT54: =SUM(AS54-O54) -> -71480 | AU54: =SUM(M54*0.09) -> 639000 | AV54: =SUM(AT54:AU54)/2 -> 283760 | AW54: =AV54-(AV54*10%) -> 255384 | AX54: 50000 | AZ54: =SUM(AW54-AX54-AY54) -> 205384
A55: 54 | B55: 46096 | C55: A6 | D55: 33더4257 | E55: WAUZZZ4G6JN061542 | F55: 늘바른 / 김윤호 | H55: Faturat Net Sh.p.k | I55: Faturat Net Sh.p.k | J55: 811577636 | K55: +38349930085, +38344371274 | L55: Kosovo | M55: 16500000 | N55: 440000 | O55: =M55+N55 -> 16940000 | Q55: 출고 | R55: 완 | S55: 입금완료 | T55: 10930 | U55: 1482 | V55: 1370 | Z55: =SUM(T55,V55:Y55) -> 12300 | AA55: =SUM(AF55+AH55+AJ55+AK55-AL55) -> 0 | AB55: =SUM(AA55-Z55) -> -12300 | AM55: 35000 | AN55: 30000 | AR55: =SUM(AM55:AQ55) -> 65000 | AS55: =SUM(Z55-V55)*U55-AR55 -> 16133260 | AT55: =SUM(AS55-O55) -> -806740 | AU55: =SUM(M55*0.09) -> 1485000 | AV55: =SUM(AT55:AU55)/2 -> 339130 | AW55: =AV55-(AV55*10%) -> 305217 | AX55: 50000 | AZ55: =SUM(AW55-AX55-AY55) -> 255217
A56: 55 | B56: 46100 | C56: Discovery Sports | D56: 49서0198 | E56: SALCA2BN1GH582080 | F56: 서울모터스 / 곽광도 | H56: Faturat Net Sh.p.k | I56: Faturat Net Sh.p.k | J56: 811577636 | K56: +38349930085, +38344371274 | L56: Kosovo | M56: 9000000 | N56: 440000 | O56: =M56+N56 -> 9440000 | Q56: 출고 | R56: 완 | S56: 입금완료 | T56: 6210 | U56: 1485 | V56: 1590 | Z56: =SUM(T56,V56:Y56) -> 7800 | AA56: =SUM(AF56+AH56+AJ56+AK56-AL56) -> 0 | AB56: =SUM(AA56-Z56) -> -7800 | AM56: 35000 | AN56: 30000 | AR56: =SUM(AM56:AQ56) -> 65000 | AS56: =SUM(Z56-V56)*U56-AR56 -> 9156850 | AT56: =SUM(AS56-O56) -> -283150 | AU56: =SUM(M56*0.09) -> 810000 | AV56: =SUM(AT56:AU56)/2 -> 263425 | AW56: =AV56-(AV56*10%) -> 237082.5 | AX56: 50000 | AZ56: =SUM(AW56-AX56-AY56) -> 187082.5
A57: 56 | B57: 46099 | C57: A42.0 TDI | D57: 08누8815 | E57: WAUZZZ8K0DN023677 | F57: 와이비모터스/안소정 | H57: AUTO-ANDI | I57: Andi Cereku | J57: M34710201A | K57: 696688738 | L57: Albania | M57: 5200000 | N57: 0 | O57: =M57+N57 -> 5200000 | Q57: 출고 | R57: 완 | S57: 입금완료 | T57: 3510 | U57: 1485 | V57: 1490 | Z57: =SUM(T57,V57:Y57) -> 5000 | AA57: =SUM(AF57+AH57+AJ57+AK57-AL57) -> 0 | AB57: =SUM(AA57-Z57) -> -5000 | AM57: 35000 | AN57: 30000 | AR57: =SUM(AM57:AQ57) -> 65000 | AS57: =SUM(Z57-V57)*U57-AR57 -> 5147350 | AT57: =SUM(AS57-O57) -> -52650 | AU57: =SUM(M57*0.09) -> 468000 | AV57: =SUM(AT57:AU57)/2 -> 207675 | AW57: =AV57-(AV57*10%) -> 186907.5 | AX57: 50000 | AZ57: =SUM(AW57-AX57-AY57) -> 136907.5
A58: 57 | B58: 46111 | C58: C63 S | D58: 31구0183 | E58: WDDWF8HB1GF307364 | F58: 이볼트모터스/황태현 | H58: Manouchehr Mirzaei | I58: Mikael Mirzaei | J58: 17069739709 | K58: +4748606275 | L58: Norway | M58: 47500000 | N58: 0 | O58: =M58+N58 -> 47500000 | Q58: 출고 | R58: 완 | S58: 입금완료 | T58: 32400 | U58: 1494 | V58: 0 | Z58: =SUM(T58,V58:Y58) -> 32400 | AA58: =SUM(AF58+AH58+AJ58+AK58-AL58) -> 0 | AB58: =SUM(AA58-Z58) -> -32400 | AM58: 35000 | AN58: 30000 | AR58: =SUM(AM58:AQ58) -> 65000 | AS58: =SUM(Z58-V58)*U58-AR58 -> 48340600 | AT58: =SUM(AS58-O58) -> 840600 | AU58: =SUM(M58*0.09) -> 4275000 | AV58: =SUM(AT58:AU58)/2 -> 2557800 | AW58: =AV58-(AV58*10%) -> 2302020 | AX58: 50000 | AZ58: =SUM(AW58-AX58-AY58) -> 2252020
A59: 58 | B59: 46122 | C59: TIGUAN | D59: 42거3455 | E59: WVGZZZ5NZCW610180 | F59: 프리오토 | H59: AUTO-ANDI | I59: STOJANI ANDI | J59: J1046010R | K59: 696688738 | L59: Albania | M59: 6300000 | N59: 0 | O59: =M59+N59 -> 6300000 | Q59: 출고 | R59: 완 | S59: 입금완료 | T59: 4010 | U59: 1470 | V59: 1590 | Z59: =SUM(T59,V59:Y59) -> 5600 | AA59: =SUM(AF59+AH59+AJ59+AK59-AL59) -> 0 | AB59: =SUM(AA59-Z59) -> -5600 | AM59: 35000 | AN59: 30000 | AR59: =SUM(AM59:AQ59) -> 65000 | AS59: =SUM(Z59-V59)*U59-AR59 -> 5829700 | AT59: =SUM(AS59-O59) -> -470300 | AU59: =SUM(M59*0.09) -> 567000 | AV59: =SUM(AT59:AU59)/2 -> 48350 | AW59: =AV59-(AV59*10%) -> 43515 | AX59: 50000 | AZ59: =SUM(AW59-AX59-AY59) -> -6485
A60: 59 | B60: 46124 | C60: GLC220D 4 MATIC COUPE | D60: 57루4400 | E60: WDC0J0FB0HF213507 | F60: ㈜셀링오토 | G60: 회사 통장 50만원 | H60: Faturat Net Sh.p.k | I60: Faturat Net Sh.p.k | J60: 811577636 | K60: +38349930085, +38344371274 | L60: Kosovo | M60: 27600000 | N60: 440000 | O60: =M60+N60 -> 28040000 | Q60: 출고 | R60: 완 | S60: 입금완료 | T60: =20400-1590 -> 18810 | U60: 1472 | V60: 1590 | Z60: =SUM(T60,V60:Y60) -> 20400 | AA60: =SUM(AF60+AH60+AJ60+AK60-AL60) -> 0 | AB60: =SUM(AA60-Z60) -> -20400 | AM60: 35000 | AN60: 30000 | AR60: =SUM(AM60:AQ60) -> 65000 | AS60: =SUM(Z60-V60)*U60-AR60 -> 27623320 | AT60: =SUM(AS60-O60) -> -416680 | AU60: =SUM(M60*0.09) -> 2484000 | AV60: =SUM(AT60:AU60)/2 -> 1033660 | AW60: =AV60-(AV60*10%) -> 930294 | AX60: 50000 | AZ60: =SUM(AW60-AX60-AY60) -> 880294
A61: 60 | B61: 46124 | C61: A4 | D61: 184머6635 | E61: WAUZZZF42KA125314 | F61: ㈜지모터스 | G61: 회사 통장 50만원 | H61: Faturat Net Sh.p.k | I61: Faturat Net Sh.p.k | J61: 811577636 | K61: +38349930085, +38344371274 | L61: Kosovo | M61: 21560000 | N61: 440000 | O61: =M61+N61 -> 22000000 | Q61: 출고 | R61: 완 | S61: 입금완료 | T61: =15800-1490 -> 14310 | U61: 1472 | V61: 1490 | Z61: =SUM(T61,V61:Y61) -> 15800 | AA61: =SUM(AF61+AH61+AJ61+AK61-AL61) -> 0 | AB61: =SUM(AA61-Z61) -> -15800 | AM61: 35000 | AN61: 30000 | AR61: =SUM(AM61:AQ61) -> 65000 | AS61: =SUM(Z61-V61)*U61-AR61 -> 20999320 | AT61: =SUM(AS61-O61) -> -1000680 | AU61: =SUM(M61*0.09) -> 1940400 | AV61: =SUM(AT61:AU61)/2 -> 469860 | AW61: =AV61-(AV61*10%) -> 422874 | AX61: 50000 | AZ61: =SUM(AW61-AX61-AY61) -> 372874
A62: 61 | B62: 46124 | C62: E220 d 4Matic | D62: 27더8058 | E62: WDDZF0FBXHA269021 | F62: ㈜솔카 | G62: 이용빈 50만원 | H62: Faturat Net Sh.p.k | I62: Faturat Net Sh.p.k | J62: 811577636 | K62: +38349930085, +38344371274 | L62: Kosovo | M62: =20800000-N61 -> 20360000 | N62: 440000 | O62: =M62+N62 -> 20800000 | Q62: 출고 | R62: 완 | S62: 입금완료 | T62: =15000-1490 -> 13510 | U62: 1470 | V62: 1490 | Z62: =SUM(T62,V62:Y62) -> 15000 | AA62: =SUM(AF62+AH62+AJ62+AK62-AL62) -> 0 | AB62: =SUM(AA62-Z62) -> -15000 | AM62: 35000 | AN62: 30000 | AR62: =SUM(AM62:AQ62) -> 65000 | AS62: =SUM(Z62-V62)*U62-AR62 -> 19794700 | AT62: =SUM(AS62-O62) -> -1005300 | AU62: =SUM(M62*0.09) -> 1832400 | AV62: =SUM(AT62:AU62)/2 -> 413550 | AW62: =AV62-(AV62*10%) -> 372195 | AX62: 50000 | AZ62: =SUM(AW62-AX62-AY62) -> 322195
A63: 62 | B63: 46127 | C63: c220 | D63: 17머9076 | E63: WDDWF0EBXHR237711 | F63: (주)벧엘자동차2 | G63: 회사 통장 100만원 | H63: Faturat Net Sh.p.k | I63: Faturat Net Sh.p.k | J63: 811577636 | K63: +38349930085, +38344371274 | L63: Kosovo | M63: =17800000-440000 -> 17360000 | N63: 440000 | O63: =M63+N63 -> 17800000 | Q63: 출고 | R63: 완 | S63: 입금완료 | T63: =13250-1490 -> 11760 | U63: 1460 | V63: 1490 | Z63: =SUM(T63,V63:Y63) -> 13250 | AA63: =SUM(AF63+AH63+AJ63+AK63-AL63) -> 0 | AB63: =SUM(AA63-Z63) -> -13250 | AM63: 35000 | AN63: 30000 | AR63: =SUM(AM63:AQ63) -> 65000 | AS63: =SUM(Z63-V63)*U63-AR63 -> 17104600 | AT63: =SUM(AS63-O63) -> -695400 | AU63: =SUM(M63*0.09) -> 1562400 | AV63: =SUM(AT63:AU63)/2 -> 433500 | AW63: =AV63-(AV63*10%) -> 390150 | AX63: 50000 | AZ63: =SUM(AW63-AX63-AY63) -> 340150
A64: 63 | B64: 46131 | C64: TUCSON | D64: 41너5794 | E64: KMHJT81VBFU077098 | F64: ㈜정이모터스 | G64: 이용빈 50만원 | H64: AUTO-ANDI | I64: STOJANI ANDI | J64: J1046010R | K64: 696688738 | L64: Albania | M64: =4540000-N64 -> 4100000 | N64: 440000 | O64: =M64+N64 -> 4540000 | Q64: 출고 | R64: 완 | S64: 입금완료 | T64: =4650-1590 -> 3060 | U64: 1455 | V64: 1590 | Z64: =SUM(T64,V64:Y64) -> 4650 | AA64: =SUM(AF64+AH64+AJ64+AK64-AL64) -> 0 | AB64: =SUM(AA64-Z64) -> -4650 | AM64: 35000 | AN64: 30000 | AR64: =SUM(AM64:AQ64) -> 65000 | AS64: =SUM(Z64-V64)*U64-AR64 -> 4387300 | AT64: =SUM(AS64-O64) -> -152700 | AU64: =SUM(M64*0.09) -> 369000 | AV64: =SUM(AT64:AU64)/2 -> 108150 | AW64: =AV64-(AV64*10%) -> 97335 | AX64: 50000 | AZ64: =SUM(AW64-AX64-AY64) -> 47335
A65: 64 | B65: 46142 | C65: GLC220D 4 MATIC | D65: 28주6031 | E65: WDC0G0FB0JF405319 | F65: ㈜ 플랜오토 | G65: 이용빈 100만원 | H65: Faturat Net Sh.p.k | I65: Faturat Net Sh.p.k | J65: 811577636 | K65: +38349930085, +38344371274 | L65: Kosovo | M65: =27000000-N63 -> 26560000 | N65: 440000 | O65: =M65+N65 -> 27000000 | Q65: 출고 | R65: 완 | S65: 입금완료 | T65: =19000-V65 -> 17410 | U65: 1471 | V65: 1590 | Z65: =SUM(T65,V65:Y65) -> 19000 | AA65: =SUM(AF65+AH65+AJ65+AK65-AL65) -> 0 | AB65: =SUM(AA65-Z65) -> -19000 | AM65: 35000 | AN65: 30000 | AR65: =SUM(AM65:AQ65) -> 65000 | AS65: =SUM(Z65-V65)*U65-AR65 -> 25545110 | AT65: =SUM(AS65-O65) -> -1454890 | AU65: =SUM(M65*0.09) -> 2390400 | AV65: =SUM(AT65:AU65)/2 -> 467755 | AW65: =AV65-(AV65*10%) -> 420979.5 | AX65: 50000 | AZ65: =SUM(AW65-AX65-AY65) -> 370979.5
A66: 65 | B66: 46145 | C66: cla 200cdi | D66: 151어5617 | E66: WDDSJ0JB1FN208329 | F66: ㈜신원자동차 | G66: ㈜신원자동차 | H66: AUTO-ANDI | I66: Andi Cereku | J66: M34710201A | K66: 696688738 | L66: Albania | M66: =6900000-N65 -> 6460000 | N66: 440000 | O66: =M66+N66 -> 6900000 | Q66: 출고 | R66: 완 | S66: 입금완료 | T66: =6300-V66 -> 4810 | U66: 1463 | V66: 1490 | Z66: =SUM(T66,V66:Y66) -> 6300 | AA66: =SUM(AF66+AH66+AJ66+AK66-AL66) -> 0 | AB66: =SUM(AA66-Z66) -> -6300 | AM66: 35000 | AN66: 30000 | AR66: =SUM(AM66:AQ66) -> 65000 | AS66: =SUM(Z66-V66)*U66-AR66 -> 6972030 | AT66: =SUM(AS66-O66) -> 72030 | AU66: =SUM(M66*0.09) -> 581400 | AV66: =SUM(AT66:AU66)/2 -> 326715 | AW66: =AV66-(AV66*10%) -> 294043.5 | AX66: 50000 | AZ66: =SUM(AW66-AX66-AY66) -> 244043.5
A67: 66 | B67: 46158 | C67: A3 | D67: 30다7034 | E67: WAUZZZ8V6F1143696 | F67: BJ MOTORS | G67: 이용빈50 | H67: AUTO-ANDI | I67: Andi Cereku | J67: M34710201A | K67: 696688738 | L67: Albania | M67: 5230000 | N67: 0 | O67: =M67+N67 -> 5230000 | Q67: 출고 | R67: 완 | S67: 입금완료 | T67: 3550 | U67: 1485 | V67: 1640 | Z67: =SUM(T67,V67:Y67) -> 5190 | AA67: =SUM(AF67+AH67+AJ67+AK67-AL67) -> 0 | AB67: =SUM(AA67-Z67) -> -5190 | AM67: 35000 | AN67: 30000 | AR67: =SUM(AM67:AQ67) -> 65000 | AS67: =SUM(Z67-V67)*U67-AR67 -> 5206750 | AT67: =SUM(AS67-O67) -> -23250 | AU67: =SUM(M67*0.09) -> 470700 | AV67: =SUM(AT67:AU67)/2 -> 223725 | AW67: =AV67-(AV67*10%) -> 201352.5 | AX67: 50000 | AZ67: =SUM(AW67-AX67-AY67) -> 151352.5
A68: 67 | B68: 46158 | C68: A6 | D68: 48조9417 | E68: WAUZZZ4G3FN022107 | F68: 카우자동차 | G68: 이용빈50 | H68: AUTO-ANDI | I68: Andi Cereku | J68: M34710201A | K68: 696688738 | L68: Albania | M68: 6000000 | N68: 0 | O68: =M68+N68 -> 6000000 | Q68: 출고 | R68: 완 | S68: 입금완료 | T68: 4060 | U68: 1485 | V68: 1640 | Z68: =SUM(T68,V68:Y68) -> 5700 | AA68: =SUM(AF68+AH68+AJ68+AK68-AL68) -> 0 | AB68: =SUM(AA68-Z68) -> -5700 | AM68: 35000 | AN68: 30000 | AR68: =SUM(AM68:AQ68) -> 65000 | AS68: =SUM(Z68-V68)*U68-AR68 -> 5964100 | AT68: =SUM(AS68-O68) -> -35900 | AU68: =SUM(M68*0.09) -> 540000 | AV68: =SUM(AT68:AU68)/2 -> 252050 | AW68: =AV68-(AV68*10%) -> 226845 | AX68: 50000 | AZ68: =SUM(AW68-AX68-AY68) -> 176845
A69: 68 | B69: 46158 | C69: TUCSON | D69: 05나0998 | E69: KMHJ381ABGU059215 | F69: GM컴퍼니 / 박혜준 | G69: 이용빈50 | H69: AUTO-ANDI | I69: Andi Cereku | J69: M34710201A | K69: 696688738 | L69: Albania | M69: 10100000 | N69: 440000 | O69: =M69+N69 -> 10540000 | Q69: 출고 | R69: 완 | S69: 입금완료 | T69: 6810 | U69: 1485 | V69: 1740 | Z69: =SUM(T69,V69:Y69) -> 8550 | AA69: =SUM(AF69+AH69+AJ69+AK69-AL69) -> 0 | AB69: =SUM(AA69-Z69) -> -8550 | AM69: 35000 | AN69: 30000 | AR69: =SUM(AM69:AQ69) -> 65000 | AS69: =SUM(Z69-V69)*U69-AR69 -> 10047850 | AT69: =SUM(AS69-O69) -> -492150 | AU69: =SUM(M69*0.09) -> 909000 | AV69: =SUM(AT69:AU69)/2 -> 208425 | AW69: =AV69-(AV69*10%) -> 187582.5 | AX69: 50000 | AZ69: =SUM(AW69-AX69-AY69) -> 137582.5
A70: 69 | B70: 46168 | C70: TIGUAN | D70: 14다1307 | E70: WVGZZZ5NZFW561214 | F70: 에이스모터스/정재형 | G70: 회사50 | H70: AUTO-ANDI | I70: Andi Cereku | J70: M34710201A | K70: 696688738 | L70: Albania | M70: 5100000 | O70: =M70+N70 -> 5100000 | Q70: 출고 | R70: 완 | S70: 입금완료 | T70: 3360 | U70: 1485 | V70: 1740 | Z70: =SUM(T70,V70:Y70) -> 5100 | AA70: =SUM(AF70+AH70+AJ70+AK70-AL70) -> 0 | AB70: =SUM(AA70-Z70) -> -5100 | AM70: 35000 | AN70: 30000 | AR70: =SUM(AM70:AQ70) -> 65000 | AS70: =SUM(Z70-V70)*U70-AR70 -> 4924600 | AT70: =SUM(AS70-O70) -> -175400 | AU70: =SUM(M70*0.09) -> 459000 | AV70: =SUM(AT70:AU70)/2 -> 141800 | AW70: =AV70-(AV70*10%) -> 127620 | AX70: 50000 | AZ70: =SUM(AW70-AX70-AY70) -> 77620
A71: 70 | B71: 46177 | C71: A7 3.0 TDI | D71: 31모3452 | E71: WAUZZZ4GXDN089977 | F71: 카팡 / 김동영 | G71: 용빈50 | H71: AUTO-ANDI | I71: Andi Cereku | J71: M34710201A | K71: 696688738 | L71: Albania | M71: 7200000 | N71: 0 | O71: =M71+N71 -> 7200000 | Q71: 출고 | R71: 완 | S71: 입금완료 | T71: 4660 | U71: 1513 | V71: 1640 | Z71: =SUM(T71,V71:Y71) -> 6300 | AA71: =SUM(AF71+AH71+AJ71+AK71-AL71) -> 0 | AB71: =SUM(AA71-Z71) -> -6300 | AM71: 35000 | AN71: 30000 | AR71: =SUM(AM71:AQ71) -> 65000 | AS71: =SUM(Z71-V71)*U71-AR71 -> 6985580 | AT71: =SUM(AS71-O71) -> -214420 | AU71: =SUM(M71*0.09) -> 648000 | AV71: =SUM(AT71:AU71)/2 -> 216790 | AW71: =AV71-(AV71*10%) -> 195111 | AX71: 50000 | AZ71: =SUM(AW71-AX71-AY71) -> 145111
A72: 71 | B72: 46177 | C72: TUCSON | D72: 26노7548 | E72: KMHJ281ABGU017913 | F72: 정카 / 김정태 | G72: 용빈50 | H72: AUTO-ANDI | I72: Andi Cereku | J72: M34710201A | K72: 696688738 | L72: Albania | M72: 8300000 | N72: 0 | O72: =M72+N72 -> 8300000 | Q72: 출고 | R72: 완 | S72: 입금완료 | T72: 5560 | U72: 1513 | V72: 1740 | Z72: =SUM(T72,V72:Y72) -> 7300 | AA72: =SUM(AF72+AH72+AJ72+AK72-AL72) -> 0 | AB72: =SUM(AA72-Z72) -> -7300 | AM72: 35000 | AN72: 30000 | AR72: =SUM(AM72:AQ72) -> 65000 | AS72: =SUM(Z72-V72)*U72-AR72 -> 8347280 | AT72: =SUM(AS72-O72) -> 47280 | AU72: =SUM(M72*0.09) -> 747000 | AV72: =SUM(AT72:AU72)/2 -> 397140 | AW72: =AV72-(AV72*10%) -> 357426 | AX72: 50000 | AZ72: =SUM(AW72-AX72-AY72) -> 307426
A73: 72 | B73: 46177 | C73: C-CLASS | D73: 69저9004 | E73: WDDWF0EB5FF045742 | F73: 뉴카카/박규민 | G73: 용빈50 | H73: AUTO-ANDI | I73: Andi Cereku | J73: M34710201A | K73: 696688738 | L73: Albania | M73: 10440000 | N73: 0 | O73: =M73+N73 -> 10440000 | Q73: 출고 | R73: 완 | S73: 입금완료 | T73: 6435 | U73: 1513 | V73: 1640 | Z73: =SUM(T73,V73:Y73) -> 8075 | AA73: =SUM(AF73+AH73+AJ73+AK73-AL73) -> 0 | AB73: =SUM(AA73-Z73) -> -8075 | AM73: 35000 | AN73: 30000 | AR73: =SUM(AM73:AQ73) -> 65000 | AS73: =SUM(Z73-V73)*U73-AR73 -> 9671155 | AT73: =SUM(AS73-O73) -> -768845 | AU73: =SUM(M73*0.09) -> 939600 | AV73: =SUM(AT73:AU73)/2 -> 85377.5 | AW73: =AV73-(AV73*10%) -> 76839.75 | AX73: 50000 | AZ73: =SUM(AW73-AX73-AY73) -> 26839.75
A74: 73 | B74: 46177 | C74: A6 45 TDI quattro | D74: 136마5083 | E74: WAUZZZF23MN018606 | F74: 준모터스 / 김현민 | G74: 여자친구 50 | H74: Faturat Net Sh.p.k | I74: Faturat Net Sh.p.k | J74: 811577636 | K74: +38349930085, +38344371274 | L74: Kosovo | M74: 31900000 | N74: 0 | O74: =M74+N74 -> 31900000 | Q74: 출고 | R74: 완 | S74: 입금완료 | T74: 20200 | U74: 1520 | V74: 1640 | Z74: =SUM(T74,V74:Y74) -> 21840 | AA74: =SUM(AF74+AH74+AJ74+AK74-AL74) -> 0 | AB74: =SUM(AA74-Z74) -> -21840 | AM74: 35000 | AN74: 30000 | AR74: =SUM(AM74:AQ74) -> 65000 | AS74: =SUM(Z74-V74)*U74-AR74 -> 30639000 | AT74: =SUM(AS74-O74) -> -1261000 | AU74: =SUM(M74*0.09) -> 2871000 | AV74: =SUM(AT74:AU74)/2 -> 805000 | AW74: =AV74-(AV74*10%) -> 724500 | AX74: 50000 | AZ74: =SUM(AW74-AX74-AY74) -> 674500
A75: 74 | B75: 46178 | C75: GOLF 2.0 | D75: 25더8692 | E75: WVWZZZAUZFW098202 | F75: 홍차/홍석훈 | G75: 여자친구 50 | H75: AUTO-ANDI | I75: Andi Cereku | J75: M34710201A | K75: 696688738 | L75: Albania | M75: 6700000 | N75: 440000 | O75: =M75+N75 -> 7140000 | Q75: 출고 | R75: 완 | S75: 입금완료 | T75: 4760 | U75: 1544 | V75: 1640 | Z75: =SUM(T75,V75:Y75) -> 6400 | AA75: =SUM(AF75+AH75+AJ75+AK75-AL75) -> 0 | AB75: =SUM(AA75-Z75) -> -6400 | AM75: 35000 | AN75: 30000 | AR75: =SUM(AM75:AQ75) -> 65000 | AS75: =SUM(Z75-V75)*U75-AR75 -> 7284440 | AT75: =SUM(AS75-O75) -> 144440 | AU75: =SUM(M75*0.09) -> 603000 | AV75: =SUM(AT75:AU75)/2 -> 373720 | AW75: =AV75-(AV75*10%) -> 336348 | AX75: 50000 | AZ75: =SUM(AW75-AX75-AY75) -> 286348
A76: 75 | B76: 46178 | C76: SANTAFE | D76: 36수7594 | E76: KMHS281BBKU101230 | F76: 원스탑/박일근 | G76: 용빈50 | H76: Faturat Net Sh.p.k | I76: Faturat Net Sh.p.k | J76: 811577636 | K76: +38349930085, +38344371274 | L76: Kosovo | M76: 15400000 | N76: 0 | O76: =M76+N76 -> 15400000 | Q76: 출고 | R76: 완 | S76: 입금완료 | T76: 9760 | U76: 1544 | V76: 1740 | Z76: =SUM(T76,V76:Y76) -> 11500 | AA76: =SUM(AF76+AH76+AJ76+AK76-AL76) -> 0 | AB76: =SUM(AA76-Z76) -> -11500 | AM76: 35000 | AN76: 30000 | AR76: =SUM(AM76:AQ76) -> 65000 | AS76: =SUM(Z76-V76)*U76-AR76 -> 15004440 | AT76: =SUM(AS76-O76) -> -395560 | AU76: =SUM(M76*0.09) -> 1386000 | AV76: =SUM(AT76:AU76)/2 -> 495220 | AW76: =AV76-(AV76*10%) -> 445698 | AX76: 50000 | AZ76: =SUM(AW76-AX76-AY76) -> 395698
A77: 76 | B77: 46178 | C77: A4 | D77: 67구1885 | E77: WAUZZZ8K0EA139602 | F77: 원스타/최환석 | G77: 여자친구 50 | H77: AUTO-ANDI | I77: Vinjolli Rigert | J77: I81124055J | K77: 696688738 | L77: Albania | M77: 5400000 | N77: 0 | O77: =M77+N77 -> 5400000 | Q77: 출고 | R77: 완 | S77: 입금완료 | T77: 3510 | U77: 1544 | V77: 1640 | Z77: =SUM(T77,V77:Y77) -> 5150 | AA77: =SUM(AF77+AH77+AJ77+AK77-AL77) -> 0 | AB77: =SUM(AA77-Z77) -> -5150 | AM77: 35000 | AN77: 30000 | AR77: =SUM(AM77:AQ77) -> 65000 | AS77: =SUM(Z77-V77)*U77-AR77 -> 5354440 | AT77: =SUM(AS77-O77) -> -45560 | AU77: =SUM(M77*0.09) -> 486000 | AV77: =SUM(AT77:AU77)/2 -> 220220 | AW77: =AV77-(AV77*10%) -> 198198 | AX77: 50000 | AZ77: =SUM(AW77-AX77-AY77) -> 148198
A78: 77 | B78: 46178 | C78: TIGUAN | D78: 64저5559 | E78: WVGZZZ5NZCW039752 | F78: 개인/이권호 | G78: 여자친구 100 | H78: AUTO-ANDI | I78: Andi Cereku | J78: M34710201A | K78: 696688738 | L78: Albania | M78: 4500000 | N78: 0 | O78: =M78+N78 -> 4500000 | Q78: 출고 | R78: 완 | S78: 입금완료 | T78: 3310 | U78: 1544 | V78: 1740 | Z78: =SUM(T78,V78:Y78) -> 5050 | AA78: =SUM(AF78+AH78+AJ78+AK78-AL78) -> 0 | AB78: =SUM(AA78-Z78) -> -5050 | AM78: 35000 | AN78: 30000 | AR78: =SUM(AM78:AQ78) -> 65000 | AS78: =SUM(Z78-V78)*U78-AR78 -> 5045640 | AT78: =SUM(AS78-O78) -> 545640 | AU78: =SUM(M78*0.09) -> 405000 | AV78: =SUM(AT78:AU78)/2 -> 475320 | AW78: =AV78-(AV78*10%) -> 427788 | AX78: 50000 | AZ78: =SUM(AW78-AX78-AY78) -> 377788
A79: 78 | B79: 46178 | C79: S-CLASS | D79: 330나4557 | E79: WDDUF3DB2GA221638 | F79: 민모터스/민경훈 | G79: 회사200 | H79: AUTO-ANDI | I79: Leti dritan | J79: H81009062F | K79: 696688738 | L79: Albania | M79: 17800000 | N79: 0 | O79: =M79+N79 -> 17800000 | Q79: 출고 | R79: 완 | S79: 입금완료 | T79: 11660 | U79: 1509 | V79: 1740 | Z79: =SUM(T79,V79:Y79) -> 13400 | AA79: =SUM(AF79+AH79+AJ79+AK79-AL79) -> 0 | AB79: =SUM(AA79-Z79) -> -13400 | AM79: 35000 | AN79: 30000 | AR79: =SUM(AM79:AQ79) -> 65000 | AS79: =SUM(Z79-V79)*U79-AR79 -> 17529940 | AT79: =SUM(AS79-O79) -> -270060 | AU79: =SUM(M79*0.09) -> 1602000 | AV79: =SUM(AT79:AU79)/2 -> 665970 | AW79: =AV79-(AV79*10%) -> 599373 | AX79: 50000 | AZ79: =SUM(AW79-AX79-AY79) -> 549373
A80: 79 | B80: 46184 | C80: JEEP Cherokee | D80: 49두9999 | E80: 1C4RJFM5HC807360 | F80: 세븐모터스/이기설 | G80: 회사100 | H80: Faturat Net Sh.p.k | I80: Faturat Net Sh.p.k | J80: 811577636 | K80: +38349930085, +38344371274 | L80: Kosovo | M80: 12900000 | N80: 0 | O80: =M80+N80 -> 12900000 | Q80: 출고 | R80: 완 | S80: 입금완료 | T80: 8160 | U80: 1509 | V80: 1840 | Z80: =SUM(T80,V80:Y80) -> 10000 | AA80: =SUM(AF80+AH80+AJ80+AK80-AL80) -> 0 | AB80: =SUM(AA80-Z80) -> -10000 | AM80: 35000 | AN80: 30000 | AR80: =SUM(AM80:AQ80) -> 65000 | AS80: =SUM(Z80-V80)*U80-AR80 -> 12248440 | AT80: =SUM(AS80-O80) -> -651560 | AU80: =SUM(M80*0.09) -> 1161000 | AV80: =SUM(AT80:AU80)/2 -> 254720 | AW80: =AV80-(AV80*10%) -> 229248 | AX80: 50000 | AZ80: =SUM(AW80-AX80-AY80) -> 179248
A81: 80 | B81: 46185 | C81: A6 | D81: 40보1247 | E81: WAUZZZ4GEN085412 | F81: 건모터스/김민현 | G81: 회사50 | H81: AUTO-ANDI | I81: Andi Cereku | J81: M34710201A | K81: 696688738 | L81: Albania | M81: 4700000 | N81: 0 | O81: =M81+N81 -> 4700000 | Q81: 출고 | R81: 완 | S81: 입금전 | T81: 3310 | U81: 1505 | V81: 1640 | Z81: =SUM(T81,V81:Y81) -> 4950 | AA81: =SUM(AF81+AH81+AJ81+AK81-AL81) -> 0 | AB81: =SUM(AA81-Z81) -> -4950 | AM81: 35000 | AN81: 30000 | AR81: =SUM(AM81:AQ81) -> 65000 | AS81: =SUM(Z81-V81)*U81-AR81 -> 4916550 | AT81: =SUM(AS81-O81) -> 216550 | AU81: =SUM(M81*0.09) -> 423000 | AV81: =SUM(AT81:AU81)/2 -> 319775 | AW81: =AV81-(AV81*10%) -> 287797.5 | AX81: 50000 | AZ81: =SUM(AW81-AX81-AY81) -> 237797.5
A82: 81 | B82: 46189 | C82: A6 | D82: 39거1721 | E82: WAUZZZ4G2JN115029 | F82: 킹모터스/이홍식 | G82: 용빈100 | H82: Faturat Net Sh.p.k | I82: Faturat Net Sh.p.k | J82: 811577636 | K82: +38349930085, +38344371274 | L82: Kosovo | M82: 17950000 | N82: 0 | O82: =M82+N82 -> 17950000 | R82: 완 | S82: 입금전 | T82: 11760 | U82: 1497 | V82: 1640 | Z82: =SUM(T82,V82:Y82) -> 13400 | AA82: =SUM(AF82+AH82+AJ82+AK82-AL82) -> 0 | AB82: =SUM(AA82-Z82) -> -13400 | AM82: 35000 | AN82: 30000 | AR82: =SUM(AM82:AQ82) -> 65000 | AS82: =SUM(Z82-V82)*U82-AR82 -> 17539720 | AT82: =SUM(AS82-O82) -> -410280 | AU82: =SUM(M82*0.09) -> 1615500 | AV82: =SUM(AT82:AU82)/2 -> 602610 | AW82: =AV82-(AV82*10%) -> 542349 | AX82: 50000 | AZ82: =SUM(AW82-AX82-AY82) -> 492349
A83: 82 | B83: 46189 | C83: ARTEON | D83: 372조1047 | E83: WVWZZZ3HZKE019626 | F83: S1모터스/김세훈 | G83: 용빈100 | H83: Faturat Net Sh.p.k | I83: Faturat Net Sh.p.k | J83: 811577636 | K83: +38349930085, +38344371274 | L83: Kosovo | M83: 19700000 | N83: 0 | O83: =M83+N83 -> 19700000 | R83: 완 | S83: 입금전 | T83: 12910 | U83: 1497 | V83: 1640 | Z83: =SUM(T83,V83:Y83) -> 14550 | AA83: =SUM(AF83+AH83+AJ83+AK83-AL83) -> 0 | AB83: =SUM(AA83-Z83) -> -14550 | AM83: 35000 | AN83: 30000 | AR83: =SUM(AM83:AQ83) -> 65000 | AS83: =SUM(Z83-V83)*U83-AR83 -> 19261270 | AT83: =SUM(AS83-O83) -> -438730 | AU83: =SUM(M83*0.09) -> 1773000 | AV83: =SUM(AT83:AU83)/2 -> 667135 | AW83: =AV83-(AV83*10%) -> 600421.5 | AX83: 50000 | AZ83: =SUM(AW83-AX83-AY83) -> 550421.5
A84: 83 | B84: 46190 | C84: E-CLASS | D84: 190머9766 | E84: WDDZ0EB5HA093089 | F84: 세이프티중고차 / 장순주 | G84: 회사100 | H84: Faturat Net Sh.p.k | I84: Faturat Net Sh.p.k | J84: 811577636 | K84: +38349930085, +38344371274 | L84: Kosovo | M84: 17500000 | N84: 0 | O84: =M84+N84 -> 17500000 | R84: 완 | S84: 입금전 | T84: 11410 | U84: 1505 | V84: 1640 | Z84: =SUM(T84,V84:Y84) -> 13050 | AA84: =SUM(AF84+AH84+AJ84+AK84-AL84) -> 0 | AB84: =SUM(AA84-Z84) -> -13050 | AM84: 35000 | AN84: 30000 | AR84: =SUM(AM84:AQ84) -> 65000 | AS84: =SUM(Z84-V84)*U84-AR84 -> 17107050 | AT84: =SUM(AS84-O84) -> -392950 | AU84: =SUM(M84*0.09) -> 1575000 | AV84: =SUM(AT84:AU84)/2 -> 591025 | AW84: =AV84-(AV84*10%) -> 531922.5 | AX84: 50000 | AZ84: =SUM(AW84-AX84-AY84) -> 481922.5
A85: 84 | B85: 46191 | C85: E-CLASS | D85: 207오9586 | E85: WDDHF0CB1DA684111 | F85: 카울렛 / 김진영 | G85: 회사50 | H85: AUTO-ANDI | I85: Andi Cereku | J85: M34710201A | K85: 696688738 | L85: Albania | M85: 4200000 | O85: =M85+N85 -> 4200000 | T85: 2810 | U85: 1505 | V85: 1640 | Z85: =SUM(T85,V85:Y85) -> 4450 | AA85: =SUM(AF85+AH85+AJ85+AK85-AL85) -> 0 | AB85: =SUM(AA85-Z85) -> -4450 | AM85: 35000 | AN85: 30000 | AR85: =SUM(AM85:AQ85) -> 65000 | AS85: =SUM(Z85-V85)*U85-AR85 -> 4164050 | AT85: =SUM(AS85-O85) -> -35950 | AU85: =SUM(M85*0.09) -> 378000 | AV85: =SUM(AT85:AU85)/2 -> 171025 | AW85: =AV85-(AV85*10%) -> 153922.5 | AX85: 50000 | AZ85: =SUM(AW85-AX85-AY85) -> 103922.5
A86: 85 | G86: ="YB"&RIGHT(#REF!,6) -> #REF! | O86: =M86+N86 -> 0 | Z86: =SUM(T86,V86:Y86) -> 0 | AA86: =SUM(AF86+AH86+AJ86+AK86-AL86) -> 0 | AB86: =SUM(AA86-Z86) -> 0 | AM86: 35000 | AN86: 30000 | AR86: =SUM(AM86:AQ86) -> 65000 | AS86: =SUM(Z86-V86)*U86-AR86 -> -65000 | AT86: =SUM(AS86-O86) -> -65000 | AU86: =SUM(M86*0.09) -> 0 | AV86: =SUM(AT86:AU86)/2 -> -32500 | AW86: =AV86-(AV86*10%) -> -29250 | AX86: 50000 | AZ86: =SUM(AW86-AX86-AY86) -> -79250
A87: 86 | G87: ="YB"&RIGHT(#REF!,6) -> #REF! | O87: =M87+N87 -> 0 | Z87: =SUM(T87,V87:Y87) -> 0 | AA87: =SUM(AF87+AH87+AJ87+AK87-AL87) -> 0 | AB87: =SUM(AA87-Z87) -> 0 | AM87: 35000 | AN87: 30000 | AR87: =SUM(AM87:AQ87) -> 65000 | AS87: =SUM(Z87-V87)*U87-AR87 -> -65000 | AT87: =SUM(AS87-O87) -> -65000 | AU87: =SUM(M87*0.09) -> 0 | AV87: =SUM(AT87:AU87)/2 -> -32500 | AW87: =AV87-(AV87*10%) -> -29250 | AX87: 50000 | AZ87: =SUM(AW87-AX87-AY87) -> -79250
A88: 87 | G88: ="YB"&RIGHT(#REF!,6) -> #REF! | O88: =M88+N88 -> 0 | Z88: =SUM(T88,V88:Y88) -> 0 | AA88: =SUM(AF88+AH88+AJ88+AK88-AL88) -> 0 | AB88: =SUM(AA88-Z88) -> 0 | AM88: 35000 | AN88: 30000 | AR88: =SUM(AM88:AQ88) -> 65000 | AS88: =SUM(Z88-V88)*U88-AR88 -> -65000 | AT88: =SUM(AS88-O88) -> -65000 | AU88: =SUM(M88*0.09) -> 0 | AV88: =SUM(AT88:AU88)/2 -> -32500 | AW88: =AV88-(AV88*10%) -> -29250 | AX88: 50000 | AZ88: =SUM(AW88-AX88-AY88) -> -79250
A89: 88 | G89: ="YB"&RIGHT(#REF!,6) -> #REF! | O89: =M89+N89 -> 0 | Z89: =SUM(T89,V89:Y89) -> 0 | AA89: =SUM(AF89+AH89+AJ89+AK89-AL89) -> 0 | AB89: =SUM(AA89-Z89) -> 0 | AM89: 35000 | AN89: 30000 | AR89: =SUM(AM89:AQ89) -> 65000 | AS89: =SUM(Z89-V89)*U89-AR89 -> -65000 | AT89: =SUM(AS89-O89) -> -65000 | AU89: =SUM(M89*0.09) -> 0 | AV89: =SUM(AT89:AU89)/2 -> -32500 | AW89: =AV89-(AV89*10%) -> -29250 | AX89: 50000 | AZ89: =SUM(AW89-AX89-AY89) -> -79250
A90: 89 | G90: ="YB"&RIGHT(#REF!,6) -> #REF! | O90: =M90+N90 -> 0 | Z90: =SUM(T90,V90:Y90) -> 0 | AA90: =SUM(AF90+AH90+AJ90+AK90-AL90) -> 0 | AB90: =SUM(AA90-Z90) -> 0 | AM90: 35000 | AN90: 30000 | AR90: =SUM(AM90:AQ90) -> 65000 | AS90: =SUM(Z90-V90)*U90-AR90 -> -65000 | AT90: =SUM(AS90-O90) -> -65000 | AU90: =SUM(M90*0.09) -> 0 | AV90: =SUM(AT90:AU90)/2 -> -32500 | AW90: =AV90-(AV90*10%) -> -29250 | AX90: 50000 | AZ90: =SUM(AW90-AX90-AY90) -> -79250
A91: 90 | G91: ="YB"&RIGHT(#REF!,6) -> #REF! | O91: =M91+N91 -> 0 | Z91: =SUM(T91,V91:Y91) -> 0 | AA91: =SUM(AF91+AH91+AJ91+AK91-AL91) -> 0 | AB91: =SUM(AA91-Z91) -> 0 | AM91: 35000 | AN91: 30000 | AR91: =SUM(AM91:AQ91) -> 65000 | AS91: =SUM(Z91-V91)*U91-AR91 -> -65000 | AT91: =SUM(AS91-O91) -> -65000 | AU91: =SUM(M91*0.09) -> 0 | AV91: =SUM(AT91:AU91)/2 -> -32500 | AW91: =AV91-(AV91*10%) -> -29250 | AX91: 50000 | AZ91: =SUM(AW91-AX91-AY91) -> -79250
A92: 91 | G92: ="YB"&RIGHT(#REF!,6) -> #REF! | O92: =M92+N92 -> 0 | Z92: =SUM(T92,V92:Y92) -> 0 | AA92: =SUM(AF92+AH92+AJ92+AK92-AL92) -> 0 | AB92: =SUM(AA92-Z92) -> 0 | AM92: 35000 | AN92: 30000 | AR92: =SUM(AM92:AQ92) -> 65000 | AS92: =SUM(Z92-V92)*U92-AR92 -> -65000 | AT92: =SUM(AS92-O92) -> -65000 | AU92: =SUM(M92*0.09) -> 0 | AV92: =SUM(AT92:AU92)/2 -> -32500 | AW92: =AV92-(AV92*10%) -> -29250 | AX92: 50000 | AZ92: =SUM(AW92-AX92-AY92) -> -79250
A93: 92 | G93: ="YB"&RIGHT(#REF!,6) -> #REF! | O93: =M93+N93 -> 0 | Z93: =SUM(T93,V93:Y93) -> 0 | AA93: =SUM(AF93+AH93+AJ93+AK93-AL93) -> 0 | AB93: =SUM(AA93-Z93) -> 0 | AM93: 35000 | AN93: 30000 | AR93: =SUM(AM93:AQ93) -> 65000 | AS93: =SUM(Z93-V93)*U93-AR93 -> -65000 | AT93: =SUM(AS93-O93) -> -65000 | AU93: =SUM(M93*0.09) -> 0 | AV93: =SUM(AT93:AU93)/2 -> -32500 | AW93: =AV93-(AV93*10%) -> -29250 | AX93: 50000 | AZ93: =SUM(AW93-AX93-AY93) -> -79250
A94: 93 | G94: ="YB"&RIGHT(#REF!,6) -> #REF! | O94: =M94+N94 -> 0 | Z94: =SUM(T94,V94:Y94) -> 0 | AA94: =SUM(AF94+AH94+AJ94+AK94-AL94) -> 0 | AB94: =SUM(AA94-Z94) -> 0 | AM94: 35000 | AN94: 30000 | AR94: =SUM(AM94:AQ94) -> 65000 | AS94: =SUM(Z94-V94)*U94-AR94 -> -65000 | AT94: =SUM(AS94-O94) -> -65000 | AU94: =SUM(M94*0.09) -> 0 | AV94: =SUM(AT94:AU94)/2 -> -32500 | AW94: =AV94-(AV94*10%) -> -29250 | AX94: 50000 | AZ94: =SUM(AW94-AX94-AY94) -> -79250
A95: 94 | G95: ="YB"&RIGHT(#REF!,6) -> #REF! | O95: =M95+N95 -> 0 | Z95: =SUM(T95,V95:Y95) -> 0 | AA95: =SUM(AF95+AH95+AJ95+AK95-AL95) -> 0 | AB95: =SUM(AA95-Z95) -> 0 | AM95: 35000 | AN95: 30000 | AR95: =SUM(AM95:AQ95) -> 65000 | AS95: =SUM(Z95-V95)*U95-AR95 -> -65000 | AT95: =SUM(AS95-O95) -> -65000 | AU95: =SUM(M95*0.09) -> 0 | AV95: =SUM(AT95:AU95)/2 -> -32500 | AW95: =AV95-(AV95*10%) -> -29250 | AX95: 50000 | AZ95: =SUM(AW95-AX95-AY95) -> -79250
A96: 95 | G96: ="YB"&RIGHT(#REF!,6) -> #REF! | O96: =M96+N96 -> 0 | Z96: =SUM(T96,V96:Y96) -> 0 | AA96: =SUM(AF96+AH96+AJ96+AK96-AL96) -> 0 | AB96: =SUM(AA96-Z96) -> 0 | AM96: 35000 | AN96: 30000 | AR96: =SUM(AM96:AQ96) -> 65000 | AS96: =SUM(Z96-V96)*U96-AR96 -> -65000 | AT96: =SUM(AS96-O96) -> -65000 | AU96: =SUM(M96*0.09) -> 0 | AV96: =SUM(AT96:AU96)/2 -> -32500 | AW96: =AV96-(AV96*10%) -> -29250 | AX96: 50000 | AZ96: =SUM(AW96-AX96-AY96) -> -79250
A97: 96 | G97: ="YB"&RIGHT(#REF!,6) -> #REF! | O97: =M97+N97 -> 0 | Z97: =SUM(T97,V97:Y97) -> 0 | AA97: =SUM(AF97+AH97+AJ97+AK97-AL97) -> 0 | AB97: =SUM(AA97-Z97) -> 0 | AM97: 35000 | AN97: 30000 | AR97: =SUM(AM97:AQ97) -> 65000 | AS97: =SUM(Z97-V97)*U97-AR97 -> -65000 | AT97: =SUM(AS97-O97) -> -65000 | AU97: =SUM(M97*0.09) -> 0 | AV97: =SUM(AT97:AU97)/2 -> -32500 | AW97: =AV97-(AV97*10%) -> -29250 | AX97: 50000 | AZ97: =SUM(AW97-AX97-AY97) -> -79250
... A112: 111 | G112: ="YB"&RIGHT(#REF!,6) -> #REF! | O112: =M112+N112 -> 0 | Z112: =SUM(T112,V112:Y112) -> 0 | AA112: =SUM(AF112+AH112+AJ112+AK112-AL112) -> 0 | AB112: =SUM(AA112-Z112) -> 0 | AM112: 35000 | AN112: 30000 | AR112: =SUM(AM112:AQ112) -> 65000 | AS112: =SUM(Z112-V112)*U112-AR112 -> -65000 | AT112: =SUM(AS112-O112) -> -65000 | AU112: =SUM(M112*0.09) -> 0 | AV112: =SUM(AT112:AU112)/2 -> -32500 | AW112: =AV112-(AV112*10%) -> -29250 | AX112: 50000 | AZ112: =SUM(AW112-AX112-AY112) -> -79250
A113: 112 | O113: =M113+N113 -> 0 | Z113: =SUM(T113,V113:Y113) -> 0 | AA113: =SUM(AF113+AH113+AJ113+AK113-AL113) -> 0 | AB113: =SUM(AA113-Z113) -> 0 | AM113: 35000 | AN113: 30000 | AR113: =SUM(AM113:AQ113) -> 65000 | AS113: =SUM(Z113-V113)*U113-AR113 -> -65000 | AT113: =SUM(AS113-O113) -> -65000 | AU113: =SUM(M113*0.09) -> 0 | AV113: =SUM(AT113:AU113)/2 -> -32500 | AW113: =AV113-(AV113*10%) -> -29250 | AX113: 50000 | AZ113: =SUM(AW113-AX113-AY113) -> -79250
A114: 113 | O114: =M114+N114 -> 0 | Z114: =SUM(T114,V114:Y114) -> 0 | AA114: =SUM(AF114+AH114+AJ114+AK114-AL114) -> 0 | AB114: =SUM(AA114-Z114) -> 0 | AM114: 35000 | AN114: 30000 | AR114: =SUM(AM114:AQ114) -> 65000 | AS114: =SUM(Z114-V114)*U114-AR114 -> -65000 | AT114: =SUM(AS114-O114) -> -65000 | AU114: =SUM(M114*0.09) -> 0 | AV114: =SUM(AT114:AU114)/2 -> -32500 | AW114: =AV114-(AV114*10%) -> -29250 | AX114: 50000 | AZ114: =SUM(AW114-AX114-AY114) -> -79250
...

Sheet 달러 인보이스+판매보고AUTO
E1: PROFORM INVOICE | H1: 83 | I1: 판매보고 자동화 (AUTO)
A2: Ssancar LTD 46-1, Gakgol-ro 2an-Gil, Sangnok, Ansan-si, Gyeinggi-do, Incheon, Korea. Phone: +82-505-366-9977 | I2: 매매단지 매입➖➖➖➖➖➖➖➖➖➖➖➖➖
E3: Date | F3: =VLOOKUP($H$1,'달러 판매현황'!A2:BA241,2,FALSE) -> 46190 | I3: ="차량명 : " & VLOOKUP($H$1,'달러 판매현황'!A2:BA241,3,FALSE) -> 차량명 : E-CLASS
E4: Invoice No. | F4: ="YB"&RIGHT(C18,6) -> YB093089 | I4: ="차량번호 : " & TEXT(VLOOKUP($H$1,'달러 판매현황'!A1:BA240,4,FALSE),"#,##0") -> 차량번호 : 190머9766
E5: Name | F5: =VLOOKUP($H$1,'달러 판매현황'!A2:BA241,9,FALSE) -> Faturat Net Sh.p.k | I5: ="차대번호 : " & TEXT(VLOOKUP($H$1,'달러 판매현황'!A2:BA241,5,FALSE),"#,##0") -> 차대번호 : WDDZ0EB5HA093089
E6: ID No. / business No. | F6: =VLOOKUP($H$1,'달러 판매현황'!A2:BA242,10,FALSE) -> 811577636 | I6: ="차량대금 : " & TEXT(VLOOKUP($H$1,'달러 판매현황'!A2:BA241,13,FALSE),"#,##0") & "원" -> 차량대금 : 17,500,000원
E7: Address | F7: =VLOOKUP($H$1,'달러 판매현황'!A2:BA243,12,FALSE) -> Kosovo | I7: ="매도비 : "&VLOOKUP($H$1,'달러 판매현황'!A3:BA242,14,FALSE)&"원" -> 매도비 : 0원
E8: Country | F8: =VLOOKUP($H$1,'달러 판매현황'!A2:BA241,12,FALSE) -> Kosovo | I8: 계산서 : 100%
E9: Phone | F9: =VLOOKUP($H$1,'달러 판매현황'!A2:BA245,11,FALSE) -> +38349930085, +38344371274 | I9: ="판매처 : " & VLOOKUP($H$1,'달러 판매현황'!A5:BA244,6,FALSE) -> 판매처 : 세이프티중고차 / 장순주
E10: Dollar exchange rate | F10: =VLOOKUP($H$1,'달러 판매현황'!A2:BA241,21,FALSE) -> 1505 | I10: ="바이어 : " & VLOOKUP($H$1,'달러 판매현황'!A5:BA244,8,FALSE) -> 바이어 : Faturat Net Sh.p.k
I11: ="판매금액 : $" & TEXT(VLOOKUP($H$1,'달러 판매현황'!A2:BA245,20,FALSE),"#,##0") -> 판매금액 : $11,410
A12: BANK ACCOUNT INFORMATION | I12: 배송조건 : CFR
A13: Beneficiary | C13: SSANCAR CO LTD | E13: Bank Name | F13: SHINHAN BANK | I13: ="환율 : $" & VLOOKUP($H$1,'달러 판매현황'!A2:BA245,21,FALSE) -> 환율 : $1505
A14: Swift Cose | C14: SHBKKRSE | E14: Bank Adress | F14: 20,Sejong-Daero9-Gil,Jung-Gu Seoul South Korea | I14: ="운임비 : $" & TEXT(VLOOKUP($H$1,'달러 판매현황'!A2:BA245,22,FALSE),"#,##0") -> 운임비 : $1,640
A15: Bank Account Number | C15: 180-008-400167 | E15: Beneficiary Adress | F15: 65 SEONGHYEON-RO,ILSANDONG-GU,GOYANG-SI, GYEONGGI-DO, SOUTH KOREA | I15: ="토탈 입금 받을금액 : $" & TEXT(VLOOKUP($H$1,'달러 판매현황'!A2:BA245,26,FALSE),"#,##0") -> 토탈 입금 받을금액 : $13,050
I16: ="계약금" & TEXT(VLOOKUP($H$1,'달러 판매현황'!A2:BA245,7,FALSE),"#,##0") -> 계약금회사100
A17: Code | B17: Model | C17: Chassis Number | D17: CAR PRICE | E17: Shipping Cost | F17: Total
A18: =VLOOKUP($H$1,'달러 판매현황'!A2:BA242,4,FALSE) -> 190머9766 | B18: =VLOOKUP($H$1,'달러 판매현황'!A2:BA242,3,FALSE) -> E-CLASS | C18: =VLOOKUP($H$1,'달러 판매현황'!A2:BA242,5,FALSE) -> WDDZ0EB5HA093089 | D18: =VLOOKUP($H$1,'달러 판매현황'!A2:BA241,20,FALSE) -> 11410 | E18: =VLOOKUP($H$1,'달러 판매현황'!A2:BA241,22,FALSE) -> 1640 | F18: =SUM(D18:E18) -> 13050
E31: Subtotal | F31: =SUM(F18:G30) -> 13050
E32: replacement cost | F32: -
E33: Commission | F33: -
E35: Total | F35: =SUM(F31:G34) -> 13050

Sheet 유로 판매현황
A1: NO | B1: 구입일자 | C1: CAR NAME | D1: 차량번호 | E1: WBAJC310 | F1: 판매자 정보 | G1: 계약금 | H1: 구입금액 | I1: 매도비 | J1: 총 구입금액 | K1: 상태 | L1: 판매보고 여부 | M1: 바이어 회사명 | N1: 고객컨사이니 | O1: 고객 ID / 비즈니스 넘버 | P1: 전화번호 | Q1: 주소 | R1: 나라 | S1: 입금여부 | T1: 판매금액 | U1: 환율 EURO | V1: 환율 USD | W1: 운임 | X1: 배송 | Y1: 디스카운트 | Z1: 인보이스 금액 | AA1: 판매 총 합계 | AB1: 입금합계 | AC1: 선수금 | AD1: 메모 | AE1: 메모 | AF1: 입금날짜01 | AG1: 정산01 | AH1: 입금날짜02 | AI1: 정산02 | AJ1: 입금날짜03 | AK1: 정산03 | AL1: 적립금 사용 | AM1: 선수금 | AN1: 말소/면허 | AO1: 탁송 | AP1: 캐리어 | AQ1: 쇼링 | AR1: 기타 | AS1: 합계 | AT1: 정산판매금 원화 | AU1: 판매마진 | AV1: 부가세 마진 | AW1: 총 마진 | AX1: 지급액 | AY1: 서류공제 | AZ1: 비용공제 | BA1: 실지급액 | BB1: 돈받은거
A2: 2 | B2: 46113 | C2: E-CLASS | D2: 18모1709 | E2: WDDHF0CBXEA918795 | F2: AJ | G2: ="YB"&RIGHT(#REF!,6) -> #REF! | H2: 6000000 | I2: 165000 | J2: =H2+I2 -> 6165000 | K2: 인천항 | L2: 완 | M2: Ramadan Xhaferi | N2: Balla Eni | O2: J00630041G | P2: +355 692079087 | Q2: Lagja 13 , plazh Albania | R2: Albania | S2: 50%적용/ 쉬핑제외 | T2: 3580 | U2: 1738 | V2: 1499 | W2: 0 | AA2: =SUM(T2,W2:Z2) -> 3580 | AB2: =SUM(AG2+AI2+AK2+AL2-AM2) -> 0 | AC2: =SUM(AB2-AA2) -> -3580 | AN2: 35000 | AO2: 30000 | AS2: =SUM(AN2:AR2) -> 65000 | AT2: =SUM(AA2-W2)*U2-AS2 -> 6157040 | AU2: =SUM(AT2-J2) -> -7960 | AV2: =SUM(0.09*H2) -> 540000 | AW2: =SUM(AU2:AV2)/2 -> 266020 | AX2: =AW2-(AW2*10%) -> 239418 | AY2: 50000 | BA2: =SUM(AX2-AY2-AZ2) -> 189418
A3: 3 | B3: 46113 | C3: A6 | D3: 64서3065 | E3: WAUZZZ4G0FN011534 | F3: AJ | G3: ="YB"&RIGHT(#REF!,6) -> #REF! | H3: 6450000 | I3: 166730 | J3: =H3+I3 -> 6616730 | K3: 인천항 | L3: 완 | M3: Ramadan Xhaferi | N3: MECANAJ ALBION | O3: K20217071W | P3: +355 692079087 | Q3: VLORE | R3: Albania | S3: 50%적용/ 쉬핑제외 | T3: 3830 | U3: 1738 | V3: 1499 | W3: 0 | AA3: =SUM(T3,W3:Z3) -> 3830 | AB3: =SUM(AG3+AI3+AK3+AL3-AM3) -> 0 | AC3: =SUM(AB3-AA3) -> -3830 | AN3: 35000 | AO3: 30000 | AS3: =SUM(AN3:AR3) -> 65000 | AT3: =SUM(AA3-W3)*U3-AS3 -> 6591540 | AU3: =SUM(AT3-J3) -> -25190 | AV3: =SUM(0.09*H3) -> 580500 | AW3: =SUM(AU3:AV3)/2 -> 277655 | AX3: =AW3-(AW3*10%) -> 249889.5 | AY3: 50000 | BA3: =SUM(AX3-AY3-AZ3) -> 199889.5
A4: 4 | B4: 46113 | C4: E-CLASS | D4: 16고6141 | E4: WDDHF8CB4EA910769 | F4: AJ | G4: ="YB"&RIGHT(#REF!,6) -> #REF! | H4: 6600000 | I4: 17610 | J4: =H4+I4 -> 6617610 | K4: 인천항 | L4: 완 | M4: Ramadan Xhaferi | N4: Erand derjaj | O4: J60818087L | P4: +355 692079087 | Q4: Lagja 13 , plazh Albania | R4: Albania | S4: 50%적용/ 쉬핑제외 | T4: 3930 | U4: 1738 | V4: 1499 | W4: 0 | AA4: =SUM(T4,W4:Z4) -> 3930 | AB4: =SUM(AG4+AI4+AK4+AL4-AM4) -> 0 | AC4: =SUM(AB4-AA4) -> -3930 | AN4: 35000 | AO4: 30000 | AS4: =SUM(AN4:AR4) -> 65000 | AT4: =SUM(AA4-W4)*U4-AS4 -> 6765340 | AU4: =SUM(AT4-J4) -> 147730 | AV4: =SUM(0.09*H4) -> 594000 | AW4: =SUM(AU4:AV4)/2 -> 370865 | AX4: =AW4-(AW4*10%) -> 333778.5 | AY4: 50000 | BA4: =SUM(AX4-AY4-AZ4) -> 283778.5
A5: 5 | B5: 46114 | C5: S-CLASS | D5: 175모8928 | E5: WDDUF3DB5FA158307 | F5: 차카/허재 | G5: ="YB"&RIGHT(#REF!,6) -> #REF! | H5: 24500000 | I5: 0 | J5: =H5+I5 -> 24500000 | K5: 인천항 | L5: 완 | M5: AUTO SHQIPONZA | N5: Allko esirald | O5: M43428202S | P5: +0696591358 | Q5: DURRES POST | R5: Albania | S5: 미수 | T5: 13370 | U5: 1738 | V5: 1499 | W5: 1380 | AA5: =SUM(T5,W5:Z5) -> 14750 | AB5: =SUM(AG5+AI5+AK5+AL5-AM5) -> 0 | AC5: =SUM(AB5-AA5) -> -14750 | AN5: 35000 | AO5: 30000 | AS5: =SUM(AN5:AR5) -> 65000 | AT5: =SUM(AA5-W5)*U5-AS5 -> 23172060 | AU5: =SUM(AT5-J5) -> -1327940 | AV5: =SUM(0.09*H5) -> 2205000 | AW5: =SUM(AU5:AV5)/2 -> 438530 | AX5: =AW5-(AW5*10%) -> 394677 | AY5: 50000 | BA5: =SUM(AX5-AY5-AZ5) -> 344677
A6: 6 | B6: 46114 | C6: GOLF | D6: 21로5718 | E6: WVWZZZAUZEW226952 | F6: 솔카/천승호 | G6: ="YB"&RIGHT(#REF!,6) -> #REF! | H6: 4500000 | I6: 0 | J6: =H6+I6 -> 4500000 | K6: 인천항 | L6: 완 | M6: AUTO SHQIPONZA | N6: Allko esirald | O6: M43428202S | P6: +0696591358 | Q6: DURRES POST | R6: Albania | S6: 미수 | T6: 2600 | U6: 1738 | V6: 1499 | W6: 1300 | AA6: =SUM(T6,W6:Z6) -> 3900 | AB6: =SUM(AG6+AI6+AK6+AL6-AM6) -> 0 | AC6: =SUM(AB6-AA6) -> -3900 | AN6: 35000 | AO6: 30000 | AS6: =SUM(AN6:AR6) -> 65000 | AT6: =SUM(AA6-W6)*U6-AS6 -> 4453800 | AU6: =SUM(AT6-J6) -> -46200 | AV6: =SUM(0.09*H6) -> 405000 | AW6: =SUM(AU6:AV6)/2 -> 179400 | AX6: =AW6-(AW6*10%) -> 161460 | AY6: 50000 | BA6: =SUM(AX6-AY6-AZ6) -> 111460
A7: 7 | B7: 46114 | C7: A6 40 TDI | D7: 380누8232 | E7: WAUZZZ4G3GN167195 | F7: 오토웨이/박병학 | G7: ="YB"&RIGHT(#REF!,6) -> #REF! | H7: 13340000 | I7: 0 | J7: =H7+I7 -> 13340000 | K7: 인천항 | L7: 완 | M7: FER-GROUP SH.P.K | N7: FERGROUP SHPK | O7: 811054999 | P7: ‪+383 48 238888‪ | Q7: DURRES POST | R7: Kosovo | S7: 입금완료 | T7: 7550 | U7: 1738 | V7: 1499 | W7: 1300 | AA7: =SUM(T7,W7:Z7) -> 8850 | AB7: =SUM(AG7+AI7+AK7+AL7-AM7) -> 0 | AC7: =SUM(AB7-AA7) -> -8850 | AN7: 35000 | AO7: 30000 | AS7: =SUM(AN7:AR7) -> 65000 | AT7: =SUM(AA7-W7)*U7-AS7 -> 13056900 | AU7: =SUM(AT7-J7) -> -283100 | AV7: =SUM(0.09*H7) -> 1200600 | AW7: =SUM(AU7:AV7)/2 -> 458750 | AX7: =AW7-(AW7*10%) -> 412875 | AY7: 50000 | BA7: =SUM(AX7-AY7-AZ7) -> 362875
A8: 8 | B8: 46114 | C8: A7 3.0 TDI | D8: 287저2966 | E8: WAUZZZ4G1DN081010 | F8: 신원자동차/정환석 | G8: ="YB"&RIGHT(#REF!,6) -> #REF! | H8: 8640000 | I8: 0 | J8: =H8+I8 -> 8640000 | K8: 인천항 | L8: 완 | M8: AUTO SHQIPONZA | N8: Allko esirald | O8: M43428202S | P8: +0696591358 | Q8: DURRES POST | R8: Albania | S8: 미수 | T8: 4800 | U8: 1738 | V8: 1499 | W8: 1300 | AA8: =SUM(T8,W8:Z8) -> 6100 | AB8: =SUM(AG8+AI8+AK8+AL8-AM8) -> 0 | AC8: =SUM(AB8-AA8) -> -6100 | AN8: 35000 | AO8: 30000 | AS8: =SUM(AN8:AR8) -> 65000 | AT8: =SUM(AA8-W8)*U8-AS8 -> 8277400 | AU8: =SUM(AT8-J8) -> -362600 | AV8: =SUM(0.09*H8) -> 777600 | AW8: =SUM(AU8:AV8)/2 -> 207500 | AX8: =AW8-(AW8*10%) -> 186750 | AY8: 50000 | BA8: =SUM(AX8-AY8-AZ8) -> 136750
A9: 9 | B9: 46114 | C9: TIGUAN | D9: 32소9154 | E9: WVGZZZ5NZAW095741 | F9: AJ | G9: ="YB"&RIGHT(#REF!,6) -> #REF! | H9: 2800000 | I9: 165000 | J9: =H9+I9 -> 2965000 | K9: 인천항 | L9: 완 | M9: AUTO SHQIPONZA | N9: Allko esirald | O9: M43428202S | P9: +0696591358 | Q9: DURRES POST | R9: Albania | S9: 미수 | T9: 2170 | U9: 1738 | V9: 1499 | W9: 1380 | AA9: =SUM(T9,W9:Z9) -> 3550 | AB9: =SUM(AG9+AI9+AK9+AL9-AM9) -> 0 | AC9: =SUM(AB9-AA9) -> -3550 | AN9: 35000 | AO9: 30000 | AS9: =SUM(AN9:AR9) -> 65000 | AT9: =SUM(AA9-W9)*U9-AS9 -> 3706460 | AU9: =SUM(AT9-J9) -> 741460 | AV9: =SUM(0.09*H9) -> 252000 | AW9: =SUM(AU9:AV9)/2 -> 496730 | AX9: =AW9-(AW9*10%) -> 447057 | AY9: 50000 | BA9: =SUM(AX9-AY9-AZ9) -> 397057
A10: 10 | B10: 46114 | C10: E-CLASS | D10: 340고3006 | E10: WDDHF9EB5FB098588 | F10: KCAR | G10: ="YB"&RIGHT(#REF!,6) -> #REF! | H10: 7300000 | I10: 165000 | J10: =H10+I10 -> 7465000 | K10: 인천항 | L10: 완 | M10: AUTO SHQIPONZA | N10: Allko esirald | O10: M43428202S | P10: +0696591358 | Q10: DURRES POST | R10: Albania | T10: =6500-1285 -> 5215 | U10: 1738 | V10: 1499 | W10: 1285 | AA10: =SUM(T10,W10:Z10) -> 6500 | AB10: =SUM(AG10+AI10+AK10+AL10-AM10) -> 0 | AC10: =SUM(AB10-AA10) -> -6500 | AN10: 35000 | AO10: 30000 | AS10: =SUM(AN10:AR10) -> 65000 | AT10: =SUM(AA10-W10)*U10-AS10 -> 8998670 | AU10: =SUM(AT10-J10) -> 1533670 | AV10: =SUM(0.09*H10) -> 657000 | AW10: =SUM(AU10:AV10)/2 -> 1095335 | AX10: =AW10-(AW10*10%) -> 985801.5 | AY10: 50000 | BA10: =SUM(AX10-AY10-AZ10) -> 935801.5
A11: 11 | B11: 46118 | C11: 640D | D11: 45거3724 | E11: WBA6E4101GD929387 | F11: 스카이모터스 / 송민서 | G11: ="YB"&RIGHT(#REF!,6) -> #REF! | H11: 15000000 | I11: 0 | J11: =H11+I11 -> 15000000 | K11: 인천항 | L11: 완 | M11: AUTO SHQIPONZA | N11: Allko esirald | O11: M43428202S | P11: +0696591358 | Q11: DURRES POST | R11: Albania | S11: 미수 | T11: 8200 | U11: 1722 | V11: 1495 | W11: 1300 | AA11: =SUM(T11,W11:Z11) -> 9500 | AB11: =SUM(AG11+AI11+AK11+AL11-AM11) -> 0 | AC11: =SUM(AB11-AA11) -> -9500 | AN11: 35000 | AO11: 30000 | AS11: =SUM(AN11:AR11) -> 65000 | AT11: =SUM(AA11-W11)*U11-AS11 -> 14055400 | AU11: =SUM(AT11-J11) -> -944600 | AV11: =SUM(0.09*H11) -> 1350000 | AW11: =SUM(AU11:AV11)/2 -> 202700 | AX11: =AW11-(AW11*10%) -> 182430 | AY11: 50000 | BA11: =SUM(AX11-AY11-AZ11) -> 132430
A12: 12 | B12: 46118 | C12: EVOQUE | D12: 06누0302 | E12: SALVA2BN6GH136032 | F12: 현진모터스/유현진 | G12: ="YB"&RIGHT(#REF!,6) -> #REF! | H12: 12800000 | I12: 0 | J12: =H12+I12 -> 12800000 | K12: 인천항 | L12: 완 | M12: AUTO SHQIPONZA | N12: Bicaku Elda | O12: K35923063B | P12: +0696591358 | Q12: DURRES POST | R12: Albania | S12: 미수 | T12: 7020 | U12: 1722 | V12: 1495 | W12: 1380 | AA12: =SUM(T12,W12:Z12) -> 8400 | AB12: 8400 | AC12: =SUM(AB12-AA12) -> 0 | AN12: 35000 | AO12: 30000 | AS12: =SUM(AN12:AR12) -> 65000 | AT12: =SUM(AA12-W12)*U12-AS12 -> 12023440 | AU12: =SUM(AT12-J12) -> -776560 | AV12: =SUM(0.09*H12) -> 1152000 | AW12: =SUM(AU12:AV12)/2 -> 187720 | AX12: =AW12-(AW12*10%) -> 168948 | AY12: 50000 | BA12: =SUM(AX12-AY12-AZ12) -> 118948
A13: 13 | B13: 46118 | C13: TIGUAN | D13: 387무3733 | E13: WVGZZZ5NZLW319878 | F13: 블루오토/장기훈 | G13: . | H13: 17700000 | I13: 440000 | J13: =H13+I13 -> 18140000 | K13: 인천항 | L13: 완 | M13: AUTO SALLON TIKU-DITI SH.P.K | N13: Ibush Arifi | O13: 1011135761 | P13: +383 45 588 543 | Q13: ISMET KRASNIQI, 208, 10 Prishtine, Kosovo | R13: Kosovo | S13: 미수 4800. 6800입금 | T13: 10220 | U13: 1722 | V13: 1495 | W13: 1380 | AA13: =SUM(T13,W13:Z13) -> 11600 | AB13: =SUM(AG13+AI13+AK13+AL13-AM13) -> 0 | AC13: =SUM(AB13-AA13) -> -11600 | AN13: 35000 | AO13: 30000 | AS13: =SUM(AN13:AR13) -> 65000 | AT13: =SUM(AA13-W13)*U13-AS13 -> 17533840 | AU13: =SUM(AT13-J13) -> -606160 | AV13: =SUM(0.09*H13) -> 1593000 | AW13: =SUM(AU13:AV13)/2 -> 493420 | AX13: =AW13-(AW13*10%) -> 444078 | AY13: 50000 | BA13: =SUM(AX13-AY13-AZ13) -> 394078 | BB13: 0
A14: 14 | B14: 46118 | C14: Porsche Macan | D14: 287조5161 | E14: WP1AD2954FLB88336 | F14: 건모터스/김태혁 | G14: ="YB"&RIGHT(#REF!,6) -> #REF! | H14: 18900000 | I14: 0 | J14: =H14+I14 -> 18900000 | K14: 인천항 | L14: 완 | M14: AUTO SHQIPONZA | N14: Allko esirald | O14: M43428202S | P14: +0696591358 | Q14: DURRES POST | R14: Albania | S14: 미수 | T14: 10520 | U14: 1722 | V14: 1495 | W14: 1380 | AA14: =SUM(T14,W14:Z14) -> 11900 | AB14: =SUM(AG14+AI14+AK14+AL14-AM14) -> 0 | AC14: =SUM(AB14-AA14) -> -11900 | AN14: 35000 | AO14: 30000 | AS14: =SUM(AN14:AR14) -> 65000 | AT14: =SUM(AA14-W14)*U14-AS14 -> 18050440 | AU14: =SUM(AT14-J14) -> -849560 | AV14: =SUM(0.09*H14) -> 1701000 | AW14: =SUM(AU14:AV14)/2 -> 425720 | AX14: =AW14-(AW14*10%) -> 383148 | AY14: 50000 | BA14: =SUM(AX14-AY14-AZ14) -> 333148
A15: 15 | B15: 46118 | C15: A4 | D15: 193조6929 | E15: WAUZZZ8K0GA010729 | F15: 스마일자동차/김정훈 | G15: ="YB"&RIGHT(#REF!,6) -> #REF! | H15: 6600000 | I15: 0 | J15: =H15+I15 -> 6600000 | K15: 인천항 | L15: 완 | M15: Ramadan Xhaferi | N15: Hasan Sokoli | O15: J502020460 | P15: +355 692079087 | Q15: Lagja 13 , plazh Albania | R15: Albania | S15: 50%적용/ 쉬핑제외 | T15: 3800 | U15: 1722 | V15: 1495 | W15: 1380 | AA15: =SUM(T15,W15:Z15) -> 5180 | AB15: =SUM(AG15+AI15+AK15+AL15-AM15) -> 0 | AC15: =SUM(AB15-AA15) -> -5180 | AN15: 35000 | AO15: 30000 | AS15: =SUM(AN15:AR15) -> 65000 | AT15: =SUM(AA15-W15)*U15-AS15 -> 6478600 | AU15: =SUM(AT15-J15) -> -121400 | AV15: =SUM(0.09*H15) -> 594000 | AW15: =SUM(AU15:AV15)/2 -> 236300 | AX15: =AW15-(AW15*10%) -> 212670 | AY15: 50000 | BA15: =SUM(AX15-AY15-AZ15) -> 162670
A16: 16 | B16: 46118 | C16: GOLF | D16: 11도5235 | E16: WVWZZZAUZFW280737 | F16: 현대글로비스 | G16: ="YB"&RIGHT(#REF!,6) -> #REF! | H16: 6300000 | I16: 165000 | J16: =H16+I16 -> 6465000 | K16: 인천항 | L16: 완 | M16: Ramadan Xhaferi | N16: Hasan Sokoli | O16: J502020460 | P16: +355 692079087 | Q16: Lagja 13 , plazh Albania | R16: Albania | S16: 50%적용/ 쉬핑제외 | T16: 3800 | U16: 1722 | V16: 1495 | AA16: =SUM(T16,W16:Z16) -> 3800 | AB16: =SUM(AG16+AI16+AK16+AL16-AM16) -> 0 | AC16: =SUM(AB16-AA16) -> -3800 | AN16: 35000 | AO16: 30000 | AS16: =SUM(AN16:AR16) -> 65000 | AT16: =SUM(AA16-W16)*U16-AS16 -> 6478600 | AU16: =SUM(AT16-J16) -> 13600 | AV16: =SUM(0.09*H16) -> 567000 | AW16: =SUM(AU16:AV16)/2 -> 290300 | AX16: =AW16-(AW16*10%) -> 261270 | AY16: 50000 | BA16: =SUM(AX16-AY16-AZ16) -> 211270 | BB16: 0
A17: 17 | B17: 46120 | C17: CLS250D | D17: 298오9431 | E17: WDDLJ9HB3FA144977 | F17: AJ | G17: con10 | H17: 9750000 | I17: 252030 | J17: =H17+I17 -> 10002030 | K17: 인천항 | L17: 완 | M17: Ramadan Xhaferi | N17: Erand derjaj | O17: J60818087L | P17: +355 692079087 | Q17: Lagja 13 , plazh Albania | R17: Albania | S17: 50%적용/ 쉬핑제외 | T17: 5650 | U17: 1713 | V17: 1465 | AA17: =SUM(T17,W17:Z17) -> 5650 | AB17: =SUM(AG17+AI17+AK17+AL17-AM17) -> 0 | AC17: =SUM(AB17-AA17) -> -5650 | AN17: 35000 | AO17: 30000 | AS17: =SUM(AN17:AR17) -> 65000 | AT17: =SUM(AA17-W17)*U17-AS17 -> 9613450 | AU17: =SUM(AT17-J17) -> -388580 | AV17: =SUM(0.09*H17) -> 877500 | AW17: =SUM(AU17:AV17)/2 -> 244460 | AX17: =AW17-(AW17*10%) -> 220014 | AY17: 50000 | BA17: =SUM(AX17-AY17-AZ17) -> 170014
A18: 18 | B18: 46120 | C18: GOLF | D18: 11노1747 | E18: WVWZZZAUZFW271981 | F18: AJ | G18: con10 | H18: 5800000 | I18: 165000 | J18: =H18+I18 -> 5965000 | K18: 인천항 | L18: 완 | M18: Ramadan Xhaferi | N18: ELIDJON SULO | O18: J00116105A | P18: +355 692079087 | Q18: Lagja 13 , plazh Albania | R18: Albania | S18: 50%적용/ 쉬핑제외 | T18: 3480 | U18: 1713 | V18: 1465 | AA18: =SUM(T18,W18:Z18) -> 3480 | AB18: =SUM(AG18+AI18+AK18+AL18-AM18) -> 0 | AC18: =SUM(AB18-AA18) -> -3480 | AN18: 35000 | AO18: 30000 | AS18: =SUM(AN18:AR18) -> 65000 | AT18: =SUM(AA18-W18)*U18-AS18 -> 5896240 | AU18: =SUM(AT18-J18) -> -68760 | AV18: =SUM(0.09*H18) -> 522000 | AW18: =SUM(AU18:AV18)/2 -> 226620 | AX18: =AW18-(AW18*10%) -> 203958 | AY18: 50000 | BA18: =SUM(AX18-AY18-AZ18) -> 153958
A19: 19 | B19: 46120 | C19: GOLF | D19: 17소5786 | E19: WVWZZZAUZEW401738 | F19: AJ | G19: con10 | H19: 6550000 | I19: 169310 | J19: =H19+I19 -> 6719310 | K19: 인천항 | L19: 완 | M19: Ramadan Xhaferi | N19: COLLAKI KLESJO | O19: J90219059T | P19: +355 692079087 | Q19: ALBANIA | R19: Albania | S19: 50%적용/ 쉬핑제외 | T19: 3900 | U19: 1713 | V19: 1465 | AA19: =SUM(T19,W19:Z19) -> 3900 | AB19: =SUM(AG19+AI19+AK19+AL19-AM19) -> 0 | AC19: =SUM(AB19-AA19) -> -3900 | AN19: 35000 | AO19: 30000 | AS19: =SUM(AN19:AR19) -> 65000 | AT19: =SUM(AA19-W19)*U19-AS19 -> 6615700 | AU19: =SUM(AT19-J19) -> -103610 | AV19: =SUM(0.09*H19) -> 589500 | AW19: =SUM(AU19:AV19)/2 -> 242945 | AX19: =AW19-(AW19*10%) -> 218650.5 | AY19: 50000 | BA19: =SUM(AX19-AY19-AZ19) -> 168650.5
A20: 20 | B20: 46120 | C20: GLA | D20: 56가4320 | E20: WDCTG0JB5FJ033212 | F20: AJ | G20: con11 | H20: 8000000 | I20: 200000 | J20: =H20+I20 -> 8200000 | K20: 인천항 | L20: 완 | M20: Ramadan Xhaferi | N20: Erand derjaj | O20: J60818087L | P20: +355 692079087 | Q20: Lagja 13 , plazh Albania | R20: Albania | S20: 50%적용/ 쉬핑제외 | T20: 4750 | U20: 1713 | V20: 1465 | AA20: =SUM(T20,W20:Z20) -> 4750 | AB20: =SUM(AG20+AI20+AK20+AL20-AM20) -> 0 | AC20: =SUM(AB20-AA20) -> -4750 | AN20: 35000 | AO20: 30000 | AS20: =SUM(AN20:AR20) -> 65000 | AT20: =SUM(AA20-W20)*U20-AS20 -> 8071750 | AU20: =SUM(AT20-J20) -> -128250 | AV20: =SUM(0.09*H20) -> 720000 | AW20: =SUM(AU20:AV20)/2 -> 295875 | AX20: =AW20-(AW20*10%) -> 266287.5 | AY20: 50000 | BA20: =SUM(AX20-AY20-AZ20) -> 216287.5
A21: 21 | B21: 46121 | C21: JETTA | D21: 68주1042 | E21: WVWZZZ16ZDM078771 | F21: KCAR | G21: X | H21: 3600000 | I21: 165000 | J21: =H21+I21 -> 3765000 | K21: 인천항 | L21: 완 | M21: Ramadan Xhaferi | N21: Erand derjaj | O21: J60818087L | P21: +355 692079087 | Q21: Lagja 13 , plazh Albania | R21: Albania | S21: 50%적용/ 쉬핑제외 | T21: 2200 | U21: 1725 | V21: 1472 | AA21: =SUM(T21,W21:Z21) -> 2200 | AB21: =SUM(AG21+AI21+AK21+AL21-AM21) -> 0 | AC21: =SUM(AB21-AA21) -> -2200 | AN21: 35000 | AO21: 30000 | AS21: =SUM(AN21:AR21) -> 65000 | AT21: =SUM(AA21-W21)*U21-AS21 -> 3730000 | AU21: =SUM(AT21-J21) -> -35000 | AV21: =SUM(0.09*H21) -> 324000 | AW21: =SUM(AU21:AV21)/2 -> 144500 | AX21: =AW21-(AW21*10%) -> 130050 | AY21: 50000 | BA21: =SUM(AX21-AY21-AZ21) -> 80050
A22: 22 | B22: 46121 | C22: PASSAT | D22: 30모1529 | E22: 1VWZZZA3ZFC061301 | F22: KCAR | G22: con11 | H22: 3900000 | I22: 165000 | J22: =H22+I22 -> 4065000 | K22: 인천항 | L22: 완 | M22: Ramadan Xhaferi | N22: MYRTA NAIM | O22: G70920085G | P22: +355 692079087 | Q22: SHOERDHET | R22: Albania | S22: 50%적용/ 쉬핑제외 | T22: 2400 | U22: 1725 | V22: 1472 | AA22: =SUM(T22,W22:Z22) -> 2400 | AB22: =SUM(AG22+AI22+AK22+AL22-AM22) -> 0 | AC22: =SUM(AB22-AA22) -> -2400 | AN22: 35000 | AO22: 30000 | AS22: =SUM(AN22:AR22) -> 65000 | AT22: =SUM(AA22-W22)*U22-AS22 -> 4075000 | AU22: =SUM(AT22-J22) -> 10000 | AV22: =SUM(0.09*H22) -> 351000 | AW22: =SUM(AU22:AV22)/2 -> 180500 | AX22: =AW22-(AW22*10%) -> 162450 | AY22: 50000 | BA22: =SUM(AX22-AY22-AZ22) -> 112450
A23: 23 | B23: 46121 | C23: PASSAT | D23: 32서7449 | E23: 1VWZZZA3ZFC006849 | F23: KCAR | G23: con11 | H23: 4300000 | I23: 165000 | J23: =H23+I23 -> 4465000 | K23: 인천항 | L23: 완 | M23: Ramadan Xhaferi | N23: MYRTA NAIM | O23: G70920085G | P23: +355 692079087 | Q23: SHOERDHET | R23: Albania | S23: 50%적용/ 쉬핑제외 | T23: 2610 | U23: 1725 | V23: 1472 | AA23: =SUM(T23,W23:Z23) -> 2610 | AB23: =SUM(AG23+AI23+AK23+AL23-AM23) -> 0 | AC23: =SUM(AB23-AA23) -> -2610 | AN23: 35000 | AO23: 30000 | AS23: =SUM(AN23:AR23) -> 65000 | AT23: =SUM(AA23-W23)*U23-AS23 -> 4437250 | AU23: =SUM(AT23-J23) -> -27750 | AV23: =SUM(0.09*H23) -> 387000 | AW23: =SUM(AU23:AV23)/2 -> 179625 | AX23: =AW23-(AW23*10%) -> 161662.5 | AY23: 50000 | BA23: =SUM(AX23-AY23-AZ23) -> 111662.5
A24: 24 | B24: 46121 | C24: PEUGEOT 308 | D24: 41우0205 | E24: VF3LBBHZWGS056943 | F24: KCAR | G24: X | H24: 5000000 | I24: 165000 | J24: =H24+I24 -> 5165000 | K24: 인천항 | L24: 완 | M24: Ardian Bajram | N24: Nova auto ardi korea | O24: 1174897090 | P24: +38345883676 | Q24: Lagja Dardania , rruga Idriz Gjilani lokali Nova Bar | R24: Kosovo | S24: 완 | T24: =AA24-W24 -> 3488 | U24: 1725 | V24: 1472 | W24: 1272 | AA24: 4760 | AB24: =SUM(AG24+AI24+AK24+AL24-AM24) -> 0 | AC24: =SUM(AB24-AA24) -> -4760 | AN24: 35000 | AO24: 30000 | AS24: =SUM(AN24:AR24) -> 65000 | AT24: =SUM(AA24-W24)*U24-AS24 -> 5951800 | AU24: =SUM(AT24-J24) -> 786800 | AV24: =SUM(0.09*H24) -> 450000 | AW24: =SUM(AU24:AV24)/2 -> 618400 | AX24: =AW24-(AW24*10%) -> 556560 | AY24: 50000 | BA24: =SUM(AX24-AY24-AZ24) -> 506560
A25: 25 | B25: 46121 | C25: BMW X5 | D25: 184가6767 | E25: WBACV6100L9B07128 | G25: ="YB"&RIGHT(#REF!,6) -> #REF! | H25: 51300000 | J25: =H25+I25 -> 51300000 | K25: 인천항 | L25: 완 | M25: 888 AUTO KOSOVA | N25: BERVENIKU CORPORATION SHPK | O25: 812063709 | P25: +383 44878548 | Q25: Rruga Mon Balaj, Prishtinë, Kosovë | R25: Kosovo | S25: 입금완료 | T25: 28385 | U25: 1712 | V25: 1470 | W25: 1365 | AA25: =SUM(T25,W25:Z25) -> 29750 | AB25: =SUM(AG25+AI25+AK25+AL25-AM25) -> 0 | AC25: =SUM(AB25-AA25) -> -29750 | AD25: not paid | AN25: 35000 | AO25: 30000 | AS25: =SUM(AN25:AR25) -> 65000 | AT25: =SUM(AA25-W25)*U25-AS25 -> 48530120 | AU25: =SUM(AT25-J25) -> -2769880 | AV25: =SUM(0.09*H25) -> 4617000 | AW25: =SUM(AU25:AV25)/2 -> 923560 | AX25: =AW25-(AW25*10%) -> 831204 | AY25: 50000 | BA25: =SUM(AX25-AY25-AZ25) -> 781204
A26: 26 | B26: 46121 | C26: Q5 | D26: 53도7978 | E26: WAUZZZ8R7DA008209 | G26: 이용빈/회사 통장 50만원식 | H26: 10700000 | I26: 440000 | J26: =H26+I26 -> 11140000 | K26: 인천항 | L26: 완 | M26: Kv auto group | N26: Kolev Krasimir Hristov | O26: 6501030966 | P26: +359 89 982 0982 | Q26: Bulgaria, Varna, str. Vladislav Varnenchik 303 number 6, fl. 6 ap. 24 | R26: Bulgaria | S26: 입금완료 | T26: 6650 | U26: 1712 | V26: 1470 | X26: CON1 운항중 | AA26: =SUM(T26,W26:Z26) -> 6650 | AB26: =SUM(AG26+AI26+AK26+AL26-AM26) -> 0 | AC26: =SUM(AB26-AA26) -> -6650 | AN26: 35000 | AO26: 30000 | AS26: =SUM(AN26:AR26) -> 65000 | AT26: =SUM(AA26-W26)*U26-AS26 -> 11319800 | AU26: =SUM(AT26-J26) -> 179800 | AV26: =SUM(0.09*H26) -> 963000 | AW26: =SUM(AU26:AV26)/2 -> 571400 | AX26: =AW26-(AW26*10%) -> 514260 | AY26: 50000 | BA26: =SUM(AX26-AY26-AZ26) -> 464260
A27: 27 | B27: 46121 | C27: Benz GLE 300 D 4 MATIC | D27: 298저1919 | E27: WDCFB1KB8KA076789 | F27: 정모터스/ 정상근 | G27: 이용빈 계약 50만 | H27: 44000000 | J27: =H27+I27 -> 44000000 | K27: 인천항 | L27: 완 | M27: Idealshped | N27: Sasa Vulovic B.l. | O27: 810209868 | P27: +383 49 822 255 | Q27: Donje Varage zubin Potok | R27: Kosovo | S27: 입금완료 | T27: 23833 | U27: 1722 | V27: 1495 | W27: 1467 | AA27: =SUM(T27,W27:Z27) -> 25300 | AB27: =SUM(AG27+AI27+AK27+AL27-AM27) -> 0 | AC27: =SUM(AB27-AA27) -> -25300 | AN27: 35000 | AO27: 30000 | AS27: =SUM(AN27:AR27) -> 65000 | AT27: =SUM(AA27-W27)*U27-AS27 -> 40975426 | AU27: =SUM(AT27-J27) -> -3024574 | AV27: =SUM(0.09*H27) -> 3960000 | AW27: =SUM(AU27:AV27)/2 -> 467713 | AX27: =AW27-(AW27*10%) -> 420941.7 | AY27: 50000 | BA27: =SUM(AX27-AY27-AZ27) -> 370941.7
A28: 28 | B28: 46121 | C28: Arteon | D28: 253머1590 | E28: WVWZZZ3HZKE012994 | F28: 레인보우 | G28: 이용빈/회사 통장 50만원식 | H28: 18100000 | I28: 440000 | J28: =H28+I28 -> 18540000 | K28: 인천항 | L28: 완 | M28: Kv auto group | N28: Svetoslav Ivanov Ivanov | O28: 9702098726 | P28: +359 89 982 0982 | Q28: Plovdiv , Str. Asen Hristoforov №25 | R28: Bulgaria | S28: 입금완료 | T28: 11000 | U28: 1712 | V28: 1470 | X28: CON1 운항중 | AA28: =SUM(T28,W28:Z28) -> 11000 | AB28: =SUM(AG28+AI28+AK28+AL28-AM28) -> 0 | AC28: =SUM(AB28-AA28) -> -11000 | AN28: 35000 | AO28: 30000 | AS28: =SUM(AN28:AR28) -> 65000 | AT28: =SUM(AA28-W28)*U28-AS28 -> 18767000 | AU28: =SUM(AT28-J28) -> 227000 | AV28: =SUM(0.09*H28) -> 1629000 | AW28: =SUM(AU28:AV28)/2 -> 928000 | AX28: =AW28-(AW28*10%) -> 835200 | AY28: 50000 | BA28: =SUM(AX28-AY28-AZ28) -> 785200
A29: 29 | B29: 46121 | C29: Niro | D29: 06마5650 | E29: KNACB81CGJA175189 | F29: 뉴코리아코터스 | G29: 이용빈 통장 100만원 | H29: 10700000 | I29: 440000 | J29: =H29+I29 -> 11140000 | K29: 인천항 | L29: 완 | M29: AUTO SHQIPONZA | N29: BUZANI REXHEP | O29: K10703071M | P29: +0696591358 | Q29: DURRES POST | R29: Albania | S29: 26.04.11 | T29: 6220 | U29: 1712 | V29: 1470 | W29: 1280 | AA29: =SUM(T29,W29:Z29) -> 7500 | AB29: 8100 | AC29: =SUM(AB29-AA29) -> 600 | AD29: 8100입금 | AE29: 600 선수금 | AN29: 35000 | AO29: 30000 | AS29: =SUM(AN29:AR29) -> 65000 | AT29: =SUM(AA29-W29)*U29-AS29 -> 10583640 | AU29: =SUM(AT29-J29) -> -556360 | AV29: =SUM(0.09*H29) -> 963000 | AW29: =SUM(AU29:AV29)/2 -> 203320 | AX29: =AW29-(AW29*10%) -> 182988 | AY29: 50000 | BA29: =SUM(AX29-AY29-AZ29) -> 132988
A30: 30 | B30: 46127 | C30: A6 | D30: 103러8412 | E30: WAUZZZ4G0GN159300 | F30: 위즈모토모티브 | G30: 이용빈 계약 50만 | H30: =13500000-I29 -> 13060000 | I30: 440000 | J30: =H30+I30 -> 13500000 | K30: 인천항 | L30: 완 | M30: FER-GROUP SH.P.K | N30: FERGROUP SHPK | O30: 811054999 | P30: ‪+383 48 238888‪ | Q30: DURRES POST | R30: Kosovo | S30: 2026.04.30 | T30: =9000-W30 -> 7733 | U30: 1723 | V30: 1465 | W30: 1267 | AA30: =SUM(T30,W30:Z30) -> 9000 | AB30: =SUM(AG30+AI30+AK30+AL30-AM30) -> 0 | AC30: =SUM(AB30-AA30) -> -9000 | AN30: 35000 | AO30: 30000 | AS30: =SUM(AN30:AR30) -> 65000 | AT30: =SUM(AA30-W30)*U30-AS30 -> 13258959 | AU30: =SUM(AT30-J30) -> -241041 | AV30: =SUM(0.09*H30) -> 1175400 | AW30: =SUM(AU30:AV30)/2 -> 467179.5 | AX30: =AW30-(AW30*10%) -> 420461.55 | AY30: 50000 | BA30: =SUM(AX30-AY30-AZ30) -> 370461.55
A31: 31 | B31: 46127 | C31: C220 d | D31: 383더9665 | E31: WDDWF0EBXFF087307 | F31: 강남모터스 | G31: 이용빈 통장 100만원 | H31: =12700000-I31 -> 12260000 | I31: 440000 | J31: =H31+I31 -> 12700000 | K31: 인천항 | L31: 완 | M31: AUTO SHQIPONZA | N31: Zheleku Aleks | O31: J80222017M | P31: +0696591358 | Q31: DURRES POST | R31: Albania | S31: 미수 | T31: 7733 | U31: 1723 | V31: 1465 | W31: 1267 | AA31: =SUM(T31,W31:Z31) -> 9000 | AB31: =SUM(AG31+AI31+AK31+AL31-AM31) -> 0 | AN31: 35000 | AO31: 30000 | AS31: =SUM(AN31:AR31) -> 65000 | AT31: =SUM(AA31-W31)*U31-AS31 -> 13258959 | AU31: =SUM(AT31-J31) -> 558959 | AV31: =SUM(0.09*H31) -> 1103400 | AW31: =SUM(AU31:AV31)/2 -> 831179.5 | AX31: =AW31-(AW31*10%) -> 748061.55 | AY31: 50000 | BA31: =SUM(AX31-AY31-AZ31) -> 698061.55
A32: 32 | B32: 46127 | C32: VolvoXC40T4 | D32: 366머7245 | E32: YV1XZACACL2259209 | F32: 에키원모터스 | G32: 이용빈 계약 50만 | H32: =18000000-I31 -> 17560000 | I32: 440000 | J32: =H32+I32 -> 18000000 | K32: 인천항 | L32: 완 | M32: 888 AUTO KOSOVA | N32: Marjan Spasic | O32: 1232286519 | P32: +383 44878548 | Q32: Selo Gotovusa, Strpce | R32: Kosovo | S32: 입금예정. | T32: =11450-W32 -> 10098 | U32: 1723 | V32: 1465 | W32: 1352 | AA32: =SUM(T32,W32:Z32) -> 11450 | AB32: =SUM(AG32+AI32+AK32+AL32-AM32) -> 0 | AD32: not paid | AN32: 35000 | AO32: 30000 | AS32: =SUM(AN32:AR32) -> 65000 | AT32: =SUM(AA32-W32)*U32-AS32 -> 17333854 | AU32: =SUM(AT32-J32) -> -666146 | AV32: =SUM(0.09*H32) -> 1580400 | AW32: =SUM(AU32:AV32)/2 -> 457127 | AX32: =AW32-(AW32*10%) -> 411414.3 | AY32: 50000 | BA32: =SUM(AX32-AY32-AZ32) -> 361414.3
A33: 33 | B33: 46127 | C33: GOLF | D33: 28고8915 | E33: WVWZZZAUZFW123794 | F33: AJ | G33: con11 | H33: 6100000 | I33: 165000 | J33: =H33+I33 -> 6265000 | K33: 인천항 | L33: 완 | M33: Ramadan Xhaferi | N33: Erand derjaj | O33: J60818087L | P33: +355 692079087 | Q33: Lagja 13 , plazh Albania | R33: Albania | S33: 50%적용/ 쉬핑제외 | T33: 3600 | U33: 1723 | V33: 1465 | AA33: =SUM(T33,W33:Z33) -> 3600 | AB33: =SUM(AG33+AI33+AK33+AL33-AM33) -> 0 | AN33: 35000 | AO33: 30000 | AS33: =SUM(AN33:AR33) -> 65000 | AT33: =SUM(AA33-W33)*U33-AS33 -> 6137800 | AU33: =SUM(AT33-J33) -> -127200 | AV33: =SUM(0.09*H33) -> 549000 | AW33: =SUM(AU33:AV33)/2 -> 210900 | AX33: =AW33-(AW33*10%) -> 189810 | AY33: 50000 | BA33: =SUM(AX33-AY33-AZ33) -> 139810
A34: 34 | B34: 46131 | C34: A6 | D34: 124모8906 | E34: WAUZZZF29LN064990 | F34: ㈜에스원모터스 | G34: 이용빈 계약 100만 | H34: 26000000 | I34: 440000 | J34: =H34+I34 -> 26440000 | K34: 인천항 | L34: 완 | M34: 888 AUTO KOSOVA | N34: Shkurte Rrahmani Duriqi | O34: 12311427734 | P34: +38344851128 | Q34: Rr. Jakup Ferri - Prishtine | R34: Kosovo | S34: 입금완료/300유로손상보상 | T34: =16100-W34 -> 14833 | U34: 1711 | V34: 1455 | W34: 1267 | AA34: 16100 | AB34: =SUM(AG34+AI34+AK34+AL34-AM34) -> 0 | AD34: not paid | AN34: 35000 | AO34: 30000 | AS34: =SUM(AN34:AR34) -> 65000 | AT34: =SUM(AA34-W34)*U34-AS34 -> 25314263 | AU34: =SUM(AT34-J34) -> -1125737 | AV34: =SUM(0.09*H34) -> 2340000 | AW34: =SUM(AU34:AV34)/2 -> 607131.5 | AX34: =AW34-(AW34*10%) -> 546418.35 | AY34: 50000 | BA34: =SUM(AX34-AY34-AZ34) -> 496418.35
A35: 35 | B35: 46129 | C35: TIGUAN | D35: 27서7560 | E35: WVGZZZ5NZFW500635 | F35: ㈜제이씨오토 | G35: 이용빈 계약 50만 | H35: =8300000-I35 -> 7860000 | I35: 440000 | J35: =H35+I35 -> 8300000 | K35: 인천항 | L35: 완 | M35: AUTO SHQIPONZA | N35: Bicaku Elda | O35: K35923063B | P35: +0696591358 | Q35: DURRES POST | R35: Albania | S35: 6550. 26.04.21 | T35: 2850 | U35: 1711 | V35: 1455 | W35: 1350 | AA35: =SUM(T35,W35:Z35) -> 4200 | AB35: =SUM(AG35+AI35+AK35+AL35-AM35) -> 0 | AC35: =6550-6050 -> 500 | AD35: 6550 | AE35: 500 선수금 | AN35: 35000 | AO35: 30000 | AS35: =SUM(AN35:AR35) -> 65000 | AT35: =SUM(AA35-W35)*U35-AS35 -> 4811350 | AU35: =SUM(AT35-J35) -> -3488650 | AV35: =SUM(0.09*H35) -> 707400 | AW35: =SUM(AU35:AV35)/2 -> -1390625 | AX35: =AW35-(AW35*10%) -> -1251562.5 | AY35: 50000 | BA35: =SUM(AX35-AY35-AZ35) -> -1301562.5
A36: 36 | B36: 46121 | C36: I30 | D36: 11오9354 | E36: KMHD251UBCU011162 | F36: KCAR | G36: con10 | H36: 3050000 | I36: 165000 | J36: =H36+I36 -> 3215000 | K36: 인천항 | L36: 완 | M36: Ramadan Xhaferi | N36: Fetishi Evisa | O36: I85526073O | P36: +355 692079087 | Q36: Tirane, Albania | R36: Albania | S36: 50%적용/ 쉬핑제외 | T36: 2000 | U36: 1725 | V36: 1472 | AA36: =SUM(T36,W36:Z36) -> 2000 | AB36: =SUM(AG36+AI36+AK36+AL36-AM36) -> 0 | AN36: 35000 | AO36: 30000 | AS36: =SUM(AN36:AR36) -> 65000 | AT36: =SUM(AA36-W36)*U36-AS36 -> 3385000 | AU36: =SUM(AT36-J36) -> 170000 | AV36: =SUM(0.09*H36) -> 274500 | AW36: =SUM(AU36:AV36)/2 -> 222250 | AX36: =AW36-(AW36*10%) -> 200025 | AY36: 50000 | BA36: =SUM(AX36-AY36-AZ36) -> 150025
A37: 37 | B37: 46129 | C37: S350d | D37: 168무3069 | E37: W1K6F3AB7NA117186 | F37: ㈜수성자동차 | G37: 이용빈 계약 100만 | H37: 69000000 | I37: 440000 | J37: =H37+I37 -> 69440000 | K37: 인천항 | L37: 완 | M37: Kv auto group | N37: Peltekov Damyan | O37: 8805166045 | P37: +359 89 982 0982 | Q37: Sofia , zh.k Malinova Dolina 25 | R37: Bulgaria | S37: 입금완료 | T37: 39900 | U37: 1711 | V37: 1455 | X37: CON1 운항중 | AA37: =SUM(T37,W37:Z37) -> 39900 | AB37: =SUM(AG37+AI37+AK37+AL37-AM37) -> 0 | AN37: 35000 | AO37: 30000 | AS37: =SUM(AN37:AR37) -> 65000 | AT37: =SUM(AA37-W37)*U37-AS37 -> 68203900 | AU37: =SUM(AT37-J37) -> -1236100 | AV37: =SUM(0.09*H37) -> 6210000 | AW37: =SUM(AU37:AV37)/2 -> 2486950 | AX37: =AW37-(AW37*10%) -> 2238255 | AY37: 50000 | BA37: =SUM(AX37-AY37-AZ37) -> 2188255
A38: 38 | B38: 46131 | C38: TIGUAN | D38: 156우9509 | E38: WVGZZZ5NZLW891588 | F38: ㈜동카 | H38: 23000000 | I38: 440000 | J38: =H38+I38 -> 23440000 | K38: 인천항 | L38: 완 | M38: Idealshped | N38: IDEAL SHPED | O38: 810356271 | P38: +383 49 822 255 | Q38: Kosovo | R38: Kosovo | S38: 입금완료/522EURO | T38: 12548 | U38: 1711 | V38: 1455 | W38: 1352 | AA38: =SUM(T38,W38:Z38) -> 13900 | AB38: =SUM(AG38+AI38+AK38+AL38-AM38) -> 0 | AN38: 35000 | AO38: 30000 | AS38: =SUM(AN38:AR38) -> 65000 | AT38: =SUM(AA38-W38)*U38-AS38 -> 21404628 | AU38: =SUM(AT38-J38) -> -2035372 | AV38: =SUM(0.09*H38) -> 2070000 | AW38: =SUM(AU38:AV38)/2 -> 17314 | AX38: =AW38-(AW38*10%) -> 15582.6 | AY38: 50000 | BA38: =SUM(AX38-AY38-AZ38) -> -34417.4
A39: 39 | B39: 46131 | C39: GOLF | D39: 54두9525 | E39: WVWZZZAUZFW256138 | F39: ㈜비케이 모터스 | G39: 이용빈 계약 50만 | H39: =6600000-I38 -> 6160000 | I39: 440000 | J39: =H39+I39 -> 6600000 | K39: 인천항 | L39: 완 | M39: AUTO SHQIPONZA | N39: Ymeraj Rei | O39: K30207067O | P39: +0696591358 | Q39: DURRES POST | R39: Albania | S39: 5450 인보이스 | T39: =5050-W39 -> 3783 | U39: 1711 | V39: 1455 | W39: 1267 | AA39: =SUM(T39,W39:Z39) -> 5050 | AB39: =SUM(AG39+AI39+AK39+AL39-AM39) -> 0 | AN39: 35000 | AO39: 30000 | AS39: =SUM(AN39:AR39) -> 65000 | AT39: =SUM(AA39-W39)*U39-AS39 -> 6407713 | AU39: =SUM(AT39-J39) -> -192287 | AV39: =SUM(0.09*H39) -> 554400 | AW39: =SUM(AU39:AV39)/2 -> 181056.5 | AX39: =AW39-(AW39*10%) -> 162950.85 | AY39: 50000 | BA39: =SUM(AX39-AY39-AZ39) -> 112950.85
A40: 40 | B40: 46131 | C40: MINI COOPER | D40: 17고0986 | E40: WMWXD5104GWT62240 | F40: ㈜나이스카 | G40: 이용빈 계약 100만 | H40: =7240000-440000 -> 6800000 | I40: 440000 | J40: =H40+I40 -> 7240000 | K40: 인천항 | L40: 완 | M40: 888 AUTO KOSOVA | N40: Alberina Grajçevci | O40: 1240722395 | P40: +383 44 319 394 | Q40: Prishtinë, Kosovë | R40: Kosovo | S40: 입금완료 | T40: =5500-W40 -> 4233 | U40: 1711 | V40: 1455 | W40: 1267 | AA40: =SUM(T40,W40:Z40) -> 5500 | AB40: =SUM(AG40+AI40+AK40+AL40-AM40) -> 0 | AN40: 35000 | AO40: 30000 | AS40: =SUM(AN40:AR40) -> 65000 | AT40: =SUM(AA40-W40)*U40-AS40 -> 7177663 | AU40: =SUM(AT40-J40) -> -62337 | AV40: =SUM(0.09*H40) -> 612000 | AW40: =SUM(AU40:AV40)/2 -> 274831.5 | AX40: =AW40-(AW40*10%) -> 247348.35 | AY40: 50000 | BA40: =SUM(AX40-AY40-AZ40) -> 197348.35
A41: 41 | B41: 46132 | C41: 520D | D41: 24너0743 | E41: WBA5E7104GG159441 | F41: 엘리트모터스 | G41: 이용빈 50만원 | H41: =12700000-I41 -> 12260000 | I41: 440000 | J41: =H41+I41 -> 12700000 | K41: 인천항 | L41: 완 | M41: AUTO SALLON TIKU-DITI SH.P.K | N41: AUTO SALLON TIKU-DITI SH.P.K. | O41: 810056003 | P41: +38344340828 | Q41: Llazareve, nn - 15000 Obiliq, Kosovo | R41: Kosovo | S41: 입금완료 | T41: =8400-W41 -> 7131 | U41: 1718 | V41: 1463 | W41: 1269 | AA41: =SUM(T41,W41:Z41) -> 8400 | AB41: =SUM(AG41+AI41+AK41+AL41-AM41) -> 0 | AN41: 35000 | AO41: 30000 | AS41: =SUM(AN41:AR41) -> 65000 | AT41: =SUM(AA41-W41)*U41-AS41 -> 12186058 | AU41: =SUM(AT41-J41) -> -513942 | AV41: =SUM(0.09*H41) -> 1103400 | AW41: =SUM(AU41:AV41)/2 -> 294729 | AX41: =AW41-(AW41*10%) -> 265256.1 | AY41: 50000 | BA41: =SUM(AX41-AY41-AZ41) -> 215256.1
A42: 42 | B42: 46132 | C42: 520D | D42: 134노3654 | E42: WBAJC3102HG855083 | F42: 엘리트모터스 | G42: 이용빈 계약 50만 | H42: =21000000-I42 -> 20560000 | I42: 440000 | J42: =H42+I42 -> 21000000 | K42: 인천항 | L42: 완 | M42: FER-GROUP SH.P.K | N42: FERGROUP SHPK | O42: 811054999 | P42: ‪+383 48 238888‪ | Q42: DURRES POST | R42: Kosovo | S42: 미수 | T42: =13400-W42 -> 12132 | U42: 1718 | V42: 1463 | W42: 1268 | AA42: =SUM(T42,W42:Z42) -> 13400 | AB42: =SUM(AG42+AI42+AK42+AL42-AM42) -> 0 | AN42: 35000 | AO42: 30000 | AS42: =SUM(AN42:AR42) -> 65000 | AT42: =SUM(AA42-W42)*U42-AS42 -> 20777776 | AU42: =SUM(AT42-J42) -> -222224 | AV42: =SUM(0.09*H42) -> 1850400 | AW42: =SUM(AU42:AV42)/2 -> 814088 | AX42: =AW42-(AW42*10%) -> 732679.2 | AY42: 50000 | BA42: =SUM(AX42-AY42-AZ42) -> 682679.2
A43: 43 | B43: 46134 | C43: 520d | D43: 217부4572 | E43: WBAJC3101JWE63596 | F43: 행운모터스 | G43: 회사 계약 100만 | H43: =18700000-I43 -> 18260000 | I43: 440000 | J43: =H43+I43 -> 18700000 | K43: 인천항 | L43: 완 | M43: 888 AUTO KOSOVA | N43: Ymer Berisha | O43: 1014801851 | P43: +383 044 72 92 41 | Q43: Rr 27 Nëntori, pn, Prishtinë | R43: Kosovo | S43: 입금완료 | T43: =11900-W43 -> 10635 | U43: 1718 | V43: 1458 | W43: 1265 | AA43: =SUM(T43,W43:Z43) -> 11900 | AB43: =SUM(AG43+AI43+AK43+AL43-AM43) -> 0 | AN43: 35000 | AO43: 30000 | AS43: =SUM(AN43:AR43) -> 65000 | AT43: =SUM(AA43-W43)*U43-AS43 -> 18205930 | AU43: =SUM(AT43-J43) -> -494070 | AV43: =SUM(0.09*H43) -> 1643400 | AW43: =SUM(AU43:AV43)/2 -> 574665 | AX43: =AW43-(AW43*10%) -> 517198.5 | AY43: 50000 | BA43: =SUM(AX43-AY43-AZ43) -> 467198.5
A44: 44 | B44: 46132 | C44: QM3 | D44: 58도6850 | E44: VF12RGJ1DHW756979 | F44: 현대글로비스 | H44: 4320000 | J44: =H44+I44 -> 4320000 | K44: 인천항 | L44: 완 | M44: Ardian Bajram | N44: Bajrami Lumturije | O44: 1001063509 | P44: +38345883676 | Q44: Lagja Dardania , rruga Idriz Gjilani lokali Nova Bar | R44: Kosovo | S44: 완 | T44: =AA44-W44 -> 2774 | U44: 1735 | V44: 1463 | W44: 1256 | AA44: 4030 | AB44: =SUM(AG44+AI44+AK44+AL44-AM44) -> 0 | AN44: 35000 | AO44: 30000 | AS44: =SUM(AN44:AR44) -> 65000 | AT44: =SUM(AA44-W44)*U44-AS44 -> 4747890 | AU44: =SUM(AT44-J44) -> 427890 | AV44: =SUM(0.09*H44) -> 388800 | AW44: =SUM(AU44:AV44)/2 -> 408345 | AX44: =AW44-(AW44*10%) -> 367510.5 | AY44: 50000 | BA44: =SUM(AX44-AY44-AZ44) -> 317510.5
A45: 45 | B45: 46134 | C45: QM3 | D45: 45어0847 | E45: VF12RGJ1DGW242103 | F45: 오토플러스 | G45: 이용빈 계약 50만 | H45: =6000000-I45 -> 5560000 | I45: 440000 | J45: =H45+I45 -> 6000000 | K45: 인천항 | L45: 완 | M45: AUTO SALLON TIKU-DITI SH.P.K | N45: ANUAR SH.P.K. | O45: 810854085 | P45: +383 45 588 543 | Q45: 38344179964 | R45: Kosovo | S45: 입금완료/1850선수금처리 | T45: =5000-W45 -> 3744 | U45: 1735 | V45: 1463 | W45: 1256 | AA45: =SUM(T45,W45:Z45) -> 5000 | AB45: =SUM(AG45+AI45+AK45+AL45-AM45) -> 0 | AN45: 35000 | AO45: 30000 | AS45: =SUM(AN45:AR45) -> 65000 | AT45: =SUM(AA45-W45)*U45-AS45 -> 6430840 | AU45: =SUM(AT45-J45) -> 430840 | AV45: =SUM(0.09*H45) -> 500400 | AW45: =SUM(AU45:AV45)/2 -> 465620 | AX45: =AW45-(AW45*10%) -> 419058 | AY45: 50000 | BA45: =SUM(AX45-AY45-AZ45) -> 369058
A46: 46 | B46: 46134 | C46: SANTAFE | D46: 167누4264 | E46: KMHP581LHRU015779 | F46: ㈜윤일용 | G46: 회사 계약 200만 | H46: =40400000-I45 -> 39960000 | I46: 440000 | J46: =I46+H46 -> 40400000 | K46: 인천항 | L46: 완 | M46: Kv auto group | N46: Plamen Petkov Petkov | O46: 7812295785 | P46: +359 89 982 0982 | Q46: Sofia 1000 , str Hristo Kovachev 26 | R46: Bulgaria | S46: 입금완료 | T46: 23220 | U46: 1718 | V46: 1458 | X46: CON2 운항중 | AA46: =SUM(T46,W46:Z46) -> 23220 | AB46: =SUM(AG46+AI46+AK46+AL46-AM46) -> 0 | AN46: 35000 | AO46: 30000 | AS46: =SUM(AN46:AR46) -> 65000 | AT46: =SUM(AA46-W46)*U46-AS46 -> 39826960 | AU46: =SUM(AT46-J46) -> -573040 | AV46: =SUM(0.09*H46) -> 3596400 | AW46: =SUM(AU46:AV46)/2 -> 1511680 | AX46: =AW46-(AW46*10%) -> 1360512 | AY46: 50000 | BA46: =SUM(AX46-AY46-AZ46) -> 1310512
A47: 47 | B47: 46140 | C47: e220d | D47: 22도0680 | E47: WDDHF0AB0GB319825 | F47: ㈜카베이 | G47: 이용빈 계약 50만 | H47: =10000000 -> 10000000 | I47: 440000 | J47: =H47+I47 -> 10440000 | K47: 인천항 | L47: 완 | M47: AUTO SALLON TIKU-DITI SH.P.K | N47: AUTO SALLON TIKU-DITI SH.P.K. | O47: 810056003 | P47: +38344340828 | Q47: Llazareve, nn - 15000 Obiliq, Kosovo | R47: Kosovo | S47: 입금완료/128인상미수 | T47: =7000-W47 -> 5728 | U47: 1708 | V47: 1458 | W47: 1272 | AA47: =SUM(T47,W47:Z47) -> 7000 | AB47: =SUM(AG47+AI47+AK47+AL47-AM47) -> 0 | AC47: =SUM(AB47-AA47) -> -7000 | AN47: 35000 | AO47: 30000 | AS47: =SUM(AN47:AR47) -> 65000 | AT47: =SUM(AA47-W47)*U47-AS47 -> 9718424 | AU47: =SUM(AT47-J47) -> -721576 | AV47: =SUM(0.09*H47) -> 900000 | AW47: =SUM(AU47:AV47)/2 -> 89212 | AX47: =AW47-(AW47*10%) -> 80290.8 | AY47: 50000 | BA47: =SUM(AX47-AY47-AZ47) -> 30290.8
A48: 48 | B48: 46140 | C48: A6 | D48: 319부9936 | E48: WAUZZZF21MN016885 | F48: ㈜ 차란차 | G48: 이용빈 계약 100만 | H48: 32760000 | I48: 440000 | J48: 33200000 | K48: 인천항 | L48: 완 | M48: FER-GROUP SH.P.K | N48: FERGROUP SHPK | O48: 811054999 | P48: ‪+383 48 238888‪ | Q48: DURRES POST | R48: Kosovo | S48: 2026.04.30 | T48: =20050-W48 -> 18778 | U48: 1708 | V48: 1458 | W48: 1272 | AA48: =SUM(T48,W48:Z48) -> 20050 | AB48: =SUM(AG48+AI48+AK48+AL48-AM48) -> 0 | AC48: =SUM(AB48-AA48) -> -20050 | AN48: 35000 | AO48: 30000 | AS48: =SUM(AN48:AR48) -> 65000 | AT48: =SUM(AA48-W48)*U48-AS48 -> 32007824 | AU48: =SUM(AT48-J48) -> -1192176 | AV48: =SUM(0.09*H48) -> 2948400 | AW48: =SUM(AU48:AV48)/2 -> 878112 | AX48: =AW48-(AW48*10%) -> 790300.8 | AY48: 50000 | BA48: =SUM(AX48-AY48-AZ48) -> 740300.8
A49: 49 | B49: 46140 | C49: C220 d | D49: 61로4677 | E49: WDDWF0EB1JR316125 | F49: ㈜와이엠모터스 | G49: 이용빈 계약 50만 | H49: =15540000-I49 -> 15100000 | I49: 440000 | J49: =H49+I49 -> 15540000 | K49: 인천항 | L49: 완 | M49: Idealshped | N49: HAJRA ANDI | O49: ID2143268 | P49: 383 049 822 255 | Q49: Kosovo | R49: Kosovo | S49: 입금완료/128인상미수 | T49: =10100-W49 -> 8828.0913 | U49: 1708 | V49: 1458 | W49: =1490*V49/U49 -> 1271.9087 | AA49: =SUM(T49,W49:Z49) -> 10100 | AB49: =SUM(AG49+AI49+AK49+AL49-AM49) -> 0 | AC49: =SUM(AB49-AA49) -> -10100 | AN49: 35000 | AO49: 30000 | AS49: =SUM(AN49:AR49) -> 65000 | AT49: =SUM(AA49-W49)*U49-AS49 -> 15013380 | AU49: =SUM(AT49-J49) -> -526620 | AV49: =SUM(0.09*H49) -> 1359000 | AW49: =SUM(AU49:AV49)/2 -> 416190 | AX49: =AW49-(AW49*10%) -> 374571 | AY49: 50000 | BA49: =SUM(AX49-AY49-AZ49) -> 324571
A50: 50 | B50: 46140 | C50: E220 | D50: 387나4880 | E50: WDDZF0FB4HA210255 | F50: ㈜솔카 | G50: 회사 계약 50만 | H50: =14240000-I50 -> 13800000 | I50: 440000 | J50: =H50+I50 -> 14240000 | K50: 인천항 | L50: 완 | M50: Idealshped | N50: Auto Sallon Ardiani A&Q SHPK | O50: 812398693 | P50: 383 049 822 255 | Q50: Kosovo | R50: Kosovo | S50: 입금완료/128인상미수 | T50: =9600-W50 -> 8328 | U50: 1708 | V50: 1458 | W50: 1272 | AA50: =SUM(T50,W50:Z50) -> 9600 | AB50: =SUM(AG50+AI50+AK50+AL50-AM50) -> 0 | AC50: =SUM(AB50-AA50) -> -9600 | AN50: 35000 | AO50: 30000 | AS50: =SUM(AN50:AR50) -> 65000 | AT50: =SUM(AA50-W50)*U50-AS50 -> 14159224 | AU50: =SUM(AT50-J50) -> -80776 | AV50: =SUM(0.09*H50) -> 1242000 | AW50: =SUM(AU50:AV50)/2 -> 580612 | AX50: =AW50-(AW50*10%) -> 522550.8 | AY50: 50000 | BA50: =SUM(AX50-AY50-AZ50) -> 472550.8
A51: 51 | B51: 46140 | C51: bmw 320d | D51: 45두8408 | E51: WBA8C5103HA068995 | F51: 개인매입 이영표 | G51: 이용빈 계약 100만 | H51: =8640000-I50 -> 8200000 | I51: 440000 | J51: =H51+I51 -> 8640000 | K51: 인천항 | L51: 완 | M51: AUTO SALLON TIKU-DITI SH.P.K | N51: AUTO SALLON TIKU-DITI SH.P.K. | O51: 810056003 | P51: +38344340828 | Q51: Llazareve, nn - 15000 Obiliq, Kosovo | R51: Kosovo | S51: 입금완료/128인상미수 | T51: =6400-1272 -> 5128 | U51: 1708 | V51: 1458 | W51: 1272 | AA51: =SUM(T51,W51:Z51) -> 6400 | AB51: =SUM(AG51+AI51+AK51+AL51-AM51) -> 0 | AC51: =SUM(AB51-AA51) -> -6400 | AN51: 35000 | AO51: 30000 | AS51: =SUM(AN51:AR51) -> 65000 | AT51: =SUM(AA51-W51)*U51-AS51 -> 8693624 | AU51: =SUM(AT51-J51) -> 53624 | AV51: =SUM(0.09*H51) -> 738000 | AW51: =SUM(AU51:AV51)/2 -> 395812 | AX51: =AW51-(AW51*10%) -> 356230.8 | AY51: 50000 | BA51: =SUM(AX51-AY51-AZ51) -> 306230.8
A52: 52 | B52: 46141 | C52: 3008 | D52: 257루9080 | E52: VF3MJEHZRKS035655 | F52: ㈜코오롱모빌리티 | G52: 회사 계약 100만 | H52: =14000000-I52 -> 13560000 | I52: 440000 | J52: =H52+I52 -> 14000000 | K52: 인천항 | L52: 완 | M52: AUTO SALLON TIKU-DITI SH.P.K | N52: Blerim Syla | O52: 1173573185 | P52: +38344179964 | Q52: DALIP ALSHIQI, 27, 10000 Prishtine, Kosovo | R52: Kosovo | S52: 입금완료/128인상미수 | T52: =9550-W52 -> 8192.7283 | U52: 1708 | V52: 1458 | W52: =1590*V51/U51 -> 1357.2717 | AA52: =SUM(T52,W52:Z52) -> 9550 | AB52: =SUM(AG52+AI52+AK52+AL52-AM52) -> 0 | AC52: =SUM(AB52-AA52) -> -9550 | AN52: 35000 | AO52: 30000 | AS52: =SUM(AN52:AR52) -> 65000 | AT52: =SUM(AA52-W52)*U52-AS52 -> 13928180 | AU52: =SUM(AT52-J52) -> -71820 | AV52: =SUM(0.09*H52) -> 1220400 | AW52: =SUM(AU52:AV52)/2 -> 574290 | AX52: =AW52-(AW52*10%) -> 516861 | AY52: 50000 | BA52: =SUM(AX52-AY52-AZ52) -> 466861
A53: 53 | B53: 46142 | C53: ARTEON | D53: 334소2450 | E53: WVWZZZ3HZKE020603 | F53: ㈜조아조아자동차 | G53: 이용빈 계약 100만 | H53: =18400000-I53 -> 17960000 | I53: 440000 | J53: =H53+I53 -> 18400000 | K53: 인천항 | L53: 완 | M53: AUTO SALLON TIKU-DITI SH.P.K | N53: Jeton Krasniqi | O53: 1244028965 | P53: +38344179964 | Q53: XHEVDET DODA, 5, 5-15, 10000 Prishtine, Kosovo | R53: Kosovo | S53: 입금완료/128인상미수 | T53: =11850-W53 -> 10578 | U53: 1708 | V53: 1458 | W53: 1272 | AA53: =SUM(T53,W53:Z53) -> 11850 | AB53: =SUM(AG53+AI53+AK53+AL53-AM53) -> 0 | AC53: =SUM(AB53-AA53) -> -11850 | AN53: 35000 | AO53: 30000 | AS53: =SUM(AN53:AR53) -> 65000 | AT53: =SUM(AA53-W53)*U53-AS53 -> 18002224 | AU53: =SUM(AT53-J53) -> -397776 | AV53: =SUM(0.09*H53) -> 1616400 | AW53: =SUM(AU53:AV53)/2 -> 609312 | AX53: =AW53-(AW53*10%) -> 548380.8 | AY53: 50000 | BA53: =SUM(AX53-AY53-AZ53) -> 498380.8
A54: 54 | B54: 46142 | C54: BMW 118D | D54: 272주8289 | E54: WBA1S5101G5D28017 | F54: ㈜카베이 | G54: heyman | H54: =7900000-I54 -> 7460000 | I54: 440000 | J54: =H54+I54 -> 7900000 | K54: 인천항 | L54: 완 | M54: AUTO SALLON TIKU-DITI SH.P.K | N54: AUTO SALLON TIKU-DITI SH.P.K. | O54: 810056003 | P54: +38344340828 | Q54: Llazareve, nn - 15000 Obiliq, Kosovo | R54: Kosovo | S54: 입금완료 | T54: =5900-W53 -> 4628 | U54: 1708 | V54: 1458 | W54: 1392 | AA54: =SUM(T54,W54:Z54) -> 6020 | AB54: =SUM(AG54+AI54+AK54+AL54-AM54) -> 0 | AC54: =SUM(AB54-AA54) -> -6020 | AN54: 35000 | AO54: 30000 | AS54: =SUM(AN54:AR54) -> 65000 | AT54: =SUM(AA54-W54)*U54-AS54 -> 7839624 | AU54: =SUM(AT54-J54) -> -60376 | AV54: =SUM(0.09*H54) -> 671400 | AW54: =SUM(AU54:AV54)/2 -> 305512 | AX54: =AW54-(AW54*10%) -> 274960.8 | AY54: 50000 | BA54: =SUM(AX54-AY54-AZ54) -> 224960.8
A55: 55 | B55: 46142 | C55: E250 | D55: 03고0650 | E55: WDDHF9HB1GB284173 | F55: ㈜뉴코리아모터스 | G55: 이용빈 계약 100만 | H55: =11400000-I55 -> 10960000 | I55: 440000 | J55: =H55+I55 -> 11400000 | K55: 인천항 | L55: 완 | M55: Idealshped | N55: IDEAL SHPED | O55: 810356271 | P55: +383 49 822 255 | Q55: Kosovo | R55: Kosovo | S55: 입금완료/128인상미수 | T55: =7650-W55 -> 6373.477 | U55: 1717 | V55: 1471 | W55: =1490*V55/U55 -> 1276.523 | AA55: =SUM(T55,W55:Z55) -> 7650 | AB55: =SUM(AG55+AI55+AK55+AL55-AM55) -> 0 | AC55: =SUM(AB55-AA55) -> -7650 | AN55: 35000 | AO55: 30000 | AS55: =SUM(AN55:AR55) -> 65000 | AT55: =SUM(AA55-W55)*U55-AS55 -> 10878260 | AU55: =SUM(AT55-J55) -> -521740 | AV55: =SUM(0.09*H55) -> 986400 | AW55: =SUM(AU55:AV55)/2 -> 232330 | AX55: =AW55-(AW55*10%) -> 209097 | AY55: 50000 | BA55: =SUM(AX55-AY55-AZ55) -> 159097
A56: 56 | B56: 46145 | C56: BMW X6 | D56: 01누0194 | E56: WBAKV2103G0R27733 | F56: ㈜무결점카모터스 | G56: 이용빈 계약 100만 | H56: =17900000-I56 -> 17460000 | I56: 440000 | J56: =H56+I56 -> 17900000 | K56: 인천항 | L56: 완 | M56: Idealshped | N56: Asllani Rrezart | O56: 1908678 | P56: 383 049 822 255 | Q56: Kosovo | R56: Kosovo | S56: 입금완료/128인상미수 | T56: =11500-W56 -> 10059.167 | U56: 1716 | V56: 1463 | W56: =1690*V56/U56 -> 1440.8333 | AA56: =SUM(T56,W56:Z56) -> 11500 | AB56: =SUM(AG56+AI56+AK56+AL56-AM56) -> 0 | AC56: =SUM(AB56-AA56) -> -11500 | AN56: 35000 | AO56: 30000 | AS56: =SUM(AN56:AR56) -> 65000 | AT56: =SUM(AA56-W56)*U56-AS56 -> 17196530 | AU56: =SUM(AT56-J56) -> -703470 | AV56: =SUM(0.09*H56) -> 1571400 | AW56: =SUM(AU56:AV56)/2 -> 433965 | AX56: =AW56-(AW56*10%) -> 390568.5 | AY56: 50000 | BA56: =SUM(AX56-AY56-AZ56) -> 340568.5
A57: 57 | B57: 46145 | C57: t-roc | D57: 168버2224 | E57: WVGZZZA1ZMV027697 | F57: ㈜에이투지네트워스 | G57: 이용빈 계약 50만 | H57: =17700000-I57 -> 17260000 | I57: 440000 | J57: =H57+I57 -> 17700000 | K57: 인천항 | L57: 완 | M57: Idealshped | N57: IDEAL SHPED | O57: 810356271 | P57: +383 49 822 255 | Q57: Kosovo | R57: Kosovo | S57: 미수/128인상미수 | T57: =11150-W57 -> 9794.4231 | U57: 1716 | V57: 1463 | W57: =1590*V57/U57 -> 1355.5769 | AA57: =SUM(T57,W57:Z57) -> 11150 | AB57: =SUM(AG57+AI57+AK57+AL57-AM57) -> 0 | AC57: =SUM(AB57-AA57) -> -11150 | AN57: 35000 | AO57: 30000 | AS57: =SUM(AN57:AR57) -> 65000 | AT57: =SUM(AA57-W57)*U57-AS57 -> 16742230 | AU57: =SUM(AT57-J57) -> -957770 | AV57: =SUM(0.09*H57) -> 1553400 | AW57: =SUM(AU57:AV57)/2 -> 297815 | AX57: =AW57-(AW57*10%) -> 268033.5 | AY57: 50000 | BA57: =SUM(AX57-AY57-AZ57) -> 218033.5
A58: 58 | B58: 46146 | C58: S350d | D58: 11로2790 | E58: WDDUF3DBXFA179282 | H58: =16000000-I58 -> 15560000 | I58: 440000 | J58: =H58+I58 -> 16000000 | K58: 인천항 | L58: 완 | M58: Ramadan Xhaferi | N58: JULIAN GURI | O58: H80704057J | P58: +355 692079087 | Q58: Albania | R58: Albania | S58: 50%적용/ 쉬핑제외 | T58: 9148 | U58: 1709 | V58: 1470 | W58: 1497 | AA58: =SUM(T58,W58:Z58) -> 10645 | AB58: =SUM(AG58+AI58+AK58+AL58-AM58) -> 0 | AC58: =SUM(AB58-AA58) -> -10645 | AN58: 35000 | AO58: 30000 | AS58: =SUM(AN58:AR58) -> 65000 | AT58: =SUM(AA58-W58)*U58-AS58 -> 15568932 | AU58: =SUM(AT58-J58) -> -431068 | AV58: =SUM(0.09*H58) -> 1400400 | AW58: =SUM(AU58:AV58)/2 -> 484666 | AX58: =AW58-(AW58*10%) -> 436199.4 | AY58: 50000 | BA58: =SUM(AX58-AY58-AZ58) -> 386199.4
A59: 59 | B59: 46148 | C59: AUDI A7 | D59: 34도2837 | E59: WAUZZZ4G0EN117884 | F59: 경매장- AJ | H59: 6500000 | I59: 168020 | J59: =H59+I59 -> 6668020 | K59: 인천항 | L59: 완 | M59: Ramadan Xhaferi | N59: JULIAN GURI | O59: H80704057J | P59: +355 692079087 | Q59: Albania | R59: Albania | S59: 50%적용/ 쉬핑제외 | T59: 3970 | U59: 1684 | V59: 1433 | W59: 1400 | AA59: =SUM(T59,W59:Z59) -> 5370 | AB59: =SUM(AG59+AI59+AK59+AL59-AM59) -> 0 | AC59: =SUM(AB59-AA59) -> -5370 | AN59: 35000 | AO59: 30000 | AS59: =SUM(AN59:AR59) -> 65000 | AT59: =SUM(AA59-W59)*U59-AS59 -> 6620480 | AU59: =SUM(AT59-J59) -> -47540 | AV59: =SUM(0.09*H59) -> 585000 | AW59: =SUM(AU59:AV59)/2 -> 268730 | AX59: =AW59-(AW59*10%) -> 241857 | AY59: 50000 | BA59: =SUM(AX59-AY59-AZ59) -> 191857
A60: 60 | B60: 46148 | C60: SANTAFE | D60: 18저1953 | E60: KMHSU81UBEU188516 | F60: 경매장- AJ | H60: 5100000 | I60: 165000 | J60: =H60+I60 -> 5265000 | K60: 인천항 | L60: 완 | M60: Ramadan Xhaferi | N60: JULIAN GURI | O60: H80704057J | P60: +355 692079087 | Q60: Albania | R60: Albania | S60: 50%적용/ 쉬핑제외 | T60: 3130 | U60: 1684 | V60: 1433 | AA60: =SUM(T60,W60:Z60) -> 3130 | AB60: =SUM(AG60+AI60+AK60+AL60-AM60) -> 0 | AC60: =SUM(AB60-AA60) -> -3130 | AN60: 35000 | AO60: 30000 | AS60: =SUM(AN60:AR60) -> 65000 | AT60: =SUM(AA60-W60)*U60-AS60 -> 5205920 | AU60: =SUM(AT60-J60) -> -59080 | AV60: =SUM(0.09*H60) -> 459000 | AW60: =SUM(AU60:AV60)/2 -> 199960 | AX60: =AW60-(AW60*10%) -> 179964 | AY60: 50000 | BA60: =SUM(AX60-AY60-AZ60) -> 129964
A61: 61 | B61: 46148 | C61: TUCSON | D61: 50더0709 | E61: KMHJ2815GGU139247 | F61: 경매장- AJ | H61: 6000000 | I61: 165000 | J61: =H61+I61 -> 6165000 | K61: 인천항 | L61: 완 | M61: Ramadan Xhaferi | N61: JULIAN GURI | O61: H80704057J | P61: +355 692079087 | Q61: Albania | R61: Albania | S61: 50%적용/ 쉬핑제외 | T61: 3670 | U61: 1684 | V61: 1433 | W61: 1500 | AA61: =SUM(T61,W61:Z61) -> 5170 | AB61: =SUM(AG61+AI61+AK61+AL61-AM61) -> 0 | AC61: =SUM(AB61-AA61) -> -5170 | AN61: 35000 | AO61: 30000 | AS61: =SUM(AN61:AR61) -> 65000 | AT61: =SUM(AA61-W61)*U61-AS61 -> 6115280 | AU61: =SUM(AT61-J61) -> -49720 | AV61: =SUM(0.09*H61) -> 540000 | AW61: =SUM(AU61:AV61)/2 -> 245140 | AX61: =AW61-(AW61*10%) -> 220626 | AY61: 50000 | BA61: =SUM(AX61-AY61-AZ61) -> 170626
A62: 62 | B62: 46148 | C62: GOLF 7 | D62: 66우6287 | E62: WVWZZZAUZEW110839 | F62: 경매장- AJ | H62: 4800000 | I62: 165000 | J62: =H62+I62 -> 4965000 | K62: 인천항 | L62: 완 | M62: Ramadan Xhaferi | N62: Joca Edmond | O62: K30407051L | P62: +355 692079087 | Q62: Albania | R62: Albania | S62: 50%적용/ 쉬핑제외 | T62: 4200 | U62: 1684 | V62: 1433 | W62: 1400 | AA62: =SUM(T62,W62:Z62) -> 5600 | AB62: =SUM(AG62+AI62+AK62+AL62-AM62) -> 0 | AC62: =SUM(AB62-AA62) -> -5600 | AN62: 35000 | AO62: 30000 | AS62: =SUM(AN62:AR62) -> 65000 | AT62: =SUM(AA62-W62)*U62-AS62 -> 7007800 | AU62: =SUM(AT62-J62) -> 2042800 | AV62: =SUM(0.09*H62) -> 432000 | AW62: =SUM(AU62:AV62)/2 -> 1237400 | AX62: =AW62-(AW62*10%) -> 1113660 | AY62: 50000 | BA62: =SUM(AX62-AY62-AZ62) -> 1063660
A63: 63 | B63: 46148 | C63: HYUNDAI I30 | D63: 22도6254 | E63: KMHD251UBCU038410 | F63: 경매장- AJ | H63: 3900000 | I63: 165000 | J63: =H63+I63 -> 4065000 | K63: 야드 | L63: 완 | M63: Ramadan Xhaferi | N63: JULIAN GURI | O63: H80704057J | P63: +355 692079087 | Q63: Albania | R63: Albania | S63: 50%적용/ 쉬핑제외 | T63: 2450 | U63: 1684 | V63: 1433 | AA63: =SUM(T63,W63:Z63) -> 2450 | AB63: =SUM(AG63+AI63+AK63+AL63-AM63) -> 0 | AC63: =SUM(AB63-AA63) -> -2450 | AN63: 35000 | AO63: 30000 | AS63: =SUM(AN63:AR63) -> 65000 | AT63: =SUM(AA63-W63)*U63-AS63 -> 4060800 | AU63: =SUM(AT63-J63) -> -4200 | AV63: =SUM(0.09*H63) -> 351000 | AW63: =SUM(AU63:AV63)/2 -> 173400 | AX63: =AW63-(AW63*10%) -> 156060 | AY63: 50000 | BA63: =SUM(AX63-AY63-AZ63) -> 106060
A64: 64 | B64: 46148 | C64: QM3 | D64: 09고0664 | E64: VF12RGJ1DGW104022 | F64: 경매장- AJ | H64: 4050000 | I64: 165000 | J64: =H64+I64 -> 4215000 | K64: 인천항 | L64: 완 | M64: Ardian Bajram | N64: AUTO SHEVDA | O64: 1174897090 | P64: +38345883676 | Q64: Lagja Dardania , rruga Idriz Gjilani lokali Nova Bar | R64: Kosovo | S64: 미수 | T64: =4150-W64 -> 2756 | U64: 1686 | V64: 1433 | W64: 1394 | AA64: =SUM(T64,W64:Z64) -> 4150 | AB64: =SUM(AG64+AI64+AK64+AL64-AM64) -> 0 | AC64: =SUM(AB64-AA64) -> -4150 | AN64: 35000 | AO64: 30000 | AS64: =SUM(AN64:AR64) -> 65000 | AT64: =SUM(AA64-W64)*U64-AS64 -> 4581616 | AU64: =SUM(AT64-J64) -> 366616 | AV64: =SUM(0.09*H64) -> 364500 | AW64: =SUM(AU64:AV64)/2 -> 365558 | AX64: =AW64-(AW64*10%) -> 329002.2 | AY64: 50000 | BA64: =SUM(AX64-AY64-AZ64) -> 279002.2
A65: 65 | B65: 46150 | C65: A3 | D65: 11오4585 | E65: WAUZZZ8V3FA132493 | H65: 5750000 | I65: 165000 | J65: =H65+I65 -> 5915000 | K65: 인천항 | L65: 완 | M65: Ramadan Xhaferi | N65: JULIAN GURI | O65: H80704057J | P65: +355 692079087 | Q65: Albania | R65: Albania | S65: 50%적용/ 쉬핑제외 | T65: 3525 | U65: 1706 | V65: 1450 | W65: 1400 | AA65: =SUM(T65,W65:Z65) -> 4925 | AB65: =SUM(AG65+AI65+AK65+AL65-AM65) -> 0 | AC65: =SUM(AB65-AA65) -> -4925 | AN65: 35000 | AO65: 30000 | AS65: =SUM(AN65:AR65) -> 65000 | AT65: =SUM(AA65-W65)*U65-AS65 -> 5948650 | AU65: =SUM(AT65-J65) -> 33650 | AV65: =SUM(0.09*H65) -> 517500 | AW65: =SUM(AU65:AV65)/2 -> 275575 | AX65: =AW65-(AW65*10%) -> 248017.5 | AY65: 50000 | BA65: =SUM(AX65-AY65-AZ65) -> 198017.5
A66: 66 | B66: 46150 | C66: GOLF | D66: 38소5029 | E66: WVWZZZAUZDW148842 | H66: 4100000 | I66: 165000 | J66: =H66+I66 -> 4265000 | K66: 인천항 | L66: 완 | M66: Ramadan Xhaferi | N66: JULIAN GURI | O66: H80704057J | P66: +355 692079087 | Q66: Albania | R66: Albania | S66: 50%적용/ 쉬핑제외 | T66: 2540 | U66: 1706 | V66: 1450 | W66: 1400 | AA66: =SUM(T66,W66:Z66) -> 3940 | AB66: =SUM(AG66+AI66+AK66+AL66-AM66) -> 0 | AC66: =SUM(AB66-AA66) -> -3940 | AN66: 35000 | AO66: 30000 | AS66: =SUM(AN66:AR66) -> 65000 | AT66: =SUM(AA66-W66)*U66-AS66 -> 4268240 | AU66: =SUM(AT66-J66) -> 3240 | AV66: =SUM(0.09*H66) -> 369000 | AW66: =SUM(AU66:AV66)/2 -> 186120 | AX66: =AW66-(AW66*10%) -> 167508 | AY66: 50000 | BA66: =SUM(AX66-AY66-AZ66) -> 117508
A67: 67 | B67: 46152 | C67: QM6 | D67: 180노6876 | E67: KNME5C2M2KP046254 | F67: ㈜핀카 | G67: 이용빈 계약 100만 | H67: =12600000-I67 -> 12160000 | I67: 440000 | J67: =H67+I67 -> 12600000 | K67: 인천항 | L67: 완 | M67: Ardian Bajram | N67: Azemi Igballe | O67: 1000740353 | P67: +38345883676 | Q67: Lagja Dardania , rruga Idriz Gjilani lokali Nova Bar | R67: Kosovo | S67: 미수 | T67: =8950-W67 -> 7471 | U67: 1706 | V67: 1450 | W67: 1479 | AA67: =SUM(T67,W67:Z67) -> 8950 | AB67: =SUM(AG67+AI67+AK67+AL67-AM67) -> 0 | AC67: =SUM(AB67-AA67) -> -8950 | AN67: 35000 | AO67: 130000 | AS67: =SUM(AN67:AR67) -> 165000 | AT67: =SUM(AA67-W67)*U67-AS67 -> 12580526 | AU67: =SUM(AT67-J67) -> -19474 | AV67: =SUM(0.09*H67) -> 1094400 | AW67: =SUM(AU67:AV67)/2 -> 537463 | AX67: =AW67-(AW67*10%) -> 483716.7 | AY67: 50000 | BA67: =SUM(AX67-AY67-AZ67) -> 433716.7
A68: 68 | B68: 46152 | C68: A6 | D68: 156거8201 | E68: WAUZZZ4G5GN181616 | F68: ㈜훈카 | G68: 이용빈 계약 50만 | H68: =11300000-I68 -> 10860000 | I68: 440000 | J68: =H68+I68 -> 11300000 | K68: 인천항 | L68: 완 | M68: Idealshped | N68: Autosallon Elhami SH.PK | O68: 810169575 | P68: +383 49 822 255 | Q68: Kosovo | R68: Kosovo | S68: 입금완료 | T68: =7800-W68 -> 6406 | U68: 1706 | V68: 1450 | W68: 1394 | AA68: =SUM(T68,W68:Z68) -> 7800 | AB68: =SUM(AG68+AI68+AK68+AL68-AM68) -> 0 | AC68: =SUM(AB68-AA68) -> -7800 | AN68: 35000 | AO68: 130000 | AS68: =SUM(AN68:AR68) -> 165000 | AT68: =SUM(AA68-W68)*U68-AS68 -> 10763636 | AU68: =SUM(AT68-J68) -> -536364 | AV68: =SUM(0.09*H68) -> 977400 | AW68: =SUM(AU68:AV68)/2 -> 220518 | AX68: =AW68-(AW68*10%) -> 198466.2 | AY68: 50000 | BA68: =SUM(AX68-AY68-AZ68) -> 148466.2
A69: 69 | B69: 46152 | C69: BMW 520D | D69: 356구3706 | E69: WBAJC5100HG850105 | F69: ㈜ 골드상사 | G69: 이용빈 계약 50만 | H69: =16990000-I69 -> 16550000 | I69: 440000 | J69: =H69+I69 -> 16990000 | K69: 인천항 | L69: 완 | M69: Idealshped | N69: IDEAL SHPED | O69: 810356271 | P69: +383 49 822 255 | Q69: Kosovo | R69: Kosovo | S69: 미수 | T69: =11200-W69 -> 9806 | U69: 1706 | V69: 1450 | W69: 1394 | AA69: =SUM(T69,W69:Z69) -> 11200 | AB69: =SUM(AG69+AI69+AK69+AL69-AM69) -> 0 | AC69: =SUM(AB69-AA69) -> -11200 | AN69: 35000 | AO69: 130000 | AS69: =SUM(AN69:AR69) -> 165000 | AT69: =SUM(AA69-W69)*U69-AS69 -> 16564036 | AU69: =SUM(AT69-J69) -> -425964 | AV69: =SUM(0.09*H69) -> 1489500 | AW69: =SUM(AU69:AV69)/2 -> 531768 | AX69: =AW69-(AW69*10%) -> 478591.2 | AY69: 50000 | BA69: =SUM(AX69-AY69-AZ69) -> 428591.2
A70: 70 | B70: 45787 | C70: BMW 740D | D70: 103러3648 | E70: WBA7S610XLCD70885 | F70: ㈜예인자동치 | G70: 회사 200만원 | H70: =40500000-I70 -> 40060000 | I70: 440000 | J70: =H70+I70 -> 40500000 | K70: 인천항 | L70: 완 | M70: FER-GROUP SH.P.K | N70: FERGROUP SHPK | O70: 811054999 | P70: ‪+383 48 238888‪ | Q70: DURRES POST | R70: Kosovo | S70: 미수 | T70: =24600-W70 -> 23122 | U70: 1709 | V70: 1457 | W70: =1478 -> 1478 | AA70: =SUM(T70,W70:Z70) -> 24600 | AB70: =SUM(AG70+AI70+AK70+AL70-AM70) -> 0 | AC70: =SUM(AB70-AA70) -> -24600 | AN70: 35000 | AO70: 30000 | AS70: =SUM(AN70:AR70) -> 65000 | AT70: =SUM(AA70-W70)*U70-AS70 -> 39450498 | AU70: =SUM(AT70-J70) -> -1049502 | AV70: =SUM(0.09*H70) -> 3605400 | AW70: =SUM(AU70:AV70)/2 -> 1277949 | AX70: =AW70-(AW70*10%) -> 1150154.1 | AY70: 50000 | BA70: =SUM(AX70-AY70-AZ70) -> 1100154.1
A71: 71 | B71: 45787 | C71: TIGUAN | D71: 174더4123 | E71: WVGZZZ5NZLW854080 | F71: ㈜ 오썸아우토 | G71: 회사 100만원 | H71: =22200000-I71 -> 21760000 | I71: 440000 | J71: =H71+I71 -> 22200000 | K71: 인천항 | L71: 완 | M71: 888 AUTO KOSOVA | N71: Fatime Ibrahimi | O71: 1277626 | P71: +38344 410430 | Q71: Dobraje e madhe, Lipjan | R71: Kosovo | S71: 입금완료 | T71: =14050-W71 -> 12571 | U71: 1706 | V71: 1450 | W71: 1479 | AA71: =SUM(T71,W71:Z71) -> 14050 | AB71: =SUM(AG71+AI71+AK71+AL71-AM71) -> 0 | AC71: =SUM(AB71-AA71) -> -14050 | AN71: 35000 | AO71: 30000 | AS71: =SUM(AN71:AR71) -> 65000 | AT71: =SUM(AA71-W71)*U71-AS71 -> 21381126 | AU71: =SUM(AT71-J71) -> -818874 | AV71: =SUM(0.09*H71) -> 1958400 | AW71: =SUM(AU71:AV71)/2 -> 569763 | AX71: =AW71-(AW71*10%) -> 512786.7 | AY71: 50000 | BA71: =SUM(AX71-AY71-AZ71) -> 462786.7
A72: 72 | B72: 45788 | C72: A6 | D72: 09조0400 | E72: WAUZZZ4G0GN123686 | F72: ㈜ 차모터스 | G72: 이용빈 계약 50만 | H72: =10400000-I72 -> 9960000 | I72: 440000 | J72: =H72+I72 -> 10400000 | K72: 인천항 | L72: 완 | M72: Idealshped | N72: IDEAL SHPED | O72: 810356271 | P72: +383 49 822 255 | Q72: Kosovo | R72: Kosovo | S72: 입금완료 | T72: =7400-W72 -> 6006 | U72: 1705 | V72: 1450 | W72: 1394 | AA72: =SUM(T72,W72:Z72) -> 7400 | AB72: =SUM(AG72+AI72+AK72+AL72-AM72) -> 0 | AC72: =SUM(AB72-AA72) -> -7400 | AN72: 35000 | AO72: 30000 | AS72: =SUM(AN72:AR72) -> 65000 | AT72: =SUM(AA72-W72)*U72-AS72 -> 10175230 | AU72: =SUM(AT72-J72) -> -224770 | AV72: =SUM(0.09*H72) -> 896400 | AW72: =SUM(AU72:AV72)/2 -> 335815 | AX72: =AW72-(AW72*10%) -> 302233.5 | AY72: 50000 | BA72: =SUM(AX72-AY72-AZ72) -> 252233.5
A73: 73 | B73: 45789 | C73: MONDEO | D73: 46머1174 | E73: WF0DXXWPCHGS28977 | F73: 경매장-현대글로비스 | H73: 4860000 | I73: 165000 | J73: =H73+I73 -> 5025000 | K73: 인천항 | L73: 완 | M73: Ardian Bajram | N73: Nova auto ardi Korea | O73: 1174897090 | P73: +38345883676 | Q73: Lagja Dardania , rruga Idriz Gjilani lokali Nova Bar | R73: Kosovo | S73: 미수 | T73: =5450-W73 -> 4055 | U73: 1705 | V73: 1450 | W73: 1395 | AA73: =SUM(T73,W73:Z73) -> 5450 | AB73: =SUM(AG73+AI73+AK73+AL73-AM73) -> 0 | AC73: =SUM(AB73-AA73) -> -5450 | AN73: 35000 | AO73: 30000 | AS73: =SUM(AN73:AR73) -> 65000 | AT73: =SUM(AA73-W73)*U73-AS73 -> 6848775 | AU73: =SUM(AT73-J73) -> 1823775 | AV73: =SUM(0.09*H73) -> 437400 | AW73: =SUM(AU73:AV73)/2 -> 1130587.5 | AX73: =AW73-(AW73*10%) -> 1017528.8 | AY73: 50000 | BA73: =SUM(AX73-AY73-AZ73) -> 967528.75
A74: 74 | B74: 46155 | C74: A4 | D74: 33오3771 | E74: WAUZZZ8K9FA004992 | F74: 경매장-AJ | H74: 5300000 | I74: 165000 | J74: =H74+I74 -> 5465000 | K74: 인천항 | L74: 완 | M74: Ramadan Xhaferi | N74: JULIAN GURI | O74: H80704057J | P74: +355 692079087 | Q74: Albania | R74: Albania | S74: 50%적용/ 쉬핑제외 | T74: 3370 | U74: 1728 | V74: 1485 | AA74: =SUM(T74,W74:Z74) -> 3370 | AB74: =SUM(AG74+AI74+AK74+AL74-AM74) -> 0 | AC74: =SUM(AB74-AA74) -> -3370 | AN74: 35000 | AO74: 30000 | AS74: =SUM(AN74:AR74) -> 65000 | AT74: =SUM(AA74-W74)*U74-AS74 -> 5758360 | AU74: =SUM(AT74-J74) -> 293360 | AV74: =SUM(0.09*H74) -> 477000 | AW74: =SUM(AU74:AV74)/2 -> 385180 | AX74: =AW74-(AW74*10%) -> 346662 | AY74: 50000 | BA74: =SUM(AX74-AY74-AZ74) -> 296662
A75: 75 | B75: 46157 | C75: CC | D75: 41구3526 | E75: WVWZZZ3CZEE535830 | F75: 경매장-현대글로비스 | H75: 4020000 | I75: 165000 | J75: =H75+I75 -> 4185000 | K75: 인천항 | L75: 완 | M75: Ramadan Xhaferi | N75: JULIAN GURI | O75: H80704057J | P75: +355 692079087 | Q75: Albania | R75: Albania | S75: 50%적용/ 쉬핑제외 | T75: 2500 | U75: 1728 | V75: 1485 | AA75: =SUM(T75,W75:Z75) -> 2500 | AB75: =SUM(AG75+AI75+AK75+AL75-AM75) -> 0 | AC75: =SUM(AB75-AA75) -> -2500 | AN75: 35000 | AO75: 30000 | AS75: =SUM(AN75:AR75) -> 65000 | AT75: =SUM(AA75-W75)*U75-AS75 -> 4255000 | AU75: =SUM(AT75-J75) -> 70000 | AV75: =SUM(0.09*H75) -> 361800 | AW75: =SUM(AU75:AV75)/2 -> 215900 | AX75: =AW75-(AW75*10%) -> 194310 | AY75: 50000 | BA75: =SUM(AX75-AY75-AZ75) -> 144310
A76: 76 | B76: 46157 | C76: PASSAT | D76: 68거9662 | E76: 1VWZZZA3ZDC026851 | F76: 경매장-현대글로비스 | H76: 3680000 | I76: 165000 | J76: =H76+I76 -> 3845000 | K76: 야드 | L76: 완 | M76: Ramadan Xhaferi | N76: JULIAN GURI | O76: H80704057J | P76: +355 692079087 | Q76: Albania | R76: Albania | S76: 50%적용/ 쉬핑제외 | T76: 2300 | U76: 1728 | V76: 1485 | AA76: =SUM(T76,W76:Z76) -> 2300 | AB76: =SUM(AG76+AI76+AK76+AL76-AM76) -> 0 | AC76: =SUM(AB76-AA76) -> -2300 | AN76: 35000 | AO76: 30000 | AS76: =SUM(AN76:AR76) -> 65000 | AT76: =SUM(AA76-W76)*U76-AS76 -> 3909400 | AU76: =SUM(AT76-J76) -> 64400 | AV76: =SUM(0.09*H76) -> 331200 | AW76: =SUM(AU76:AV76)/2 -> 197800 | AX76: =AW76-(AW76*10%) -> 178020 | AY76: 50000 | BA76: =SUM(AX76-AY76-AZ76) -> 128020
A77: 77 | B77: 46157 | C77: A4 | D77: 22더3870 | E77: WAUZZZ8K1EA048435 | F77: 경매장-현대글로비스 | H77: 4630000 | I77: 165000 | J77: =H77+I77 -> 4795000 | K77: 인천항 | L77: 완 | M77: Ramadan Xhaferi | N77: Fariese Domenico | O77: I63628006T | P77: +355 692079087 | Q77: Albania | R77: Albania | S77: 50%적용/ 쉬핑제외 | T77: 2860 | U77: 1728 | V77: 1485 | AA77: =SUM(T77,W77:Z77) -> 2860 | AB77: =SUM(AG77+AI77+AK77+AL77-AM77) -> 0 | AC77: =SUM(AB77-AA77) -> -2860 | AN77: 35000 | AO77: 30000 | AS77: =SUM(AN77:AR77) -> 65000 | AT77: =SUM(AA77-W77)*U77-AS77 -> 4877080 | AU77: =SUM(AT77-J77) -> 82080 | AV77: =SUM(0.09*H77) -> 416700 | AW77: =SUM(AU77:AV77)/2 -> 249390 | AX77: =AW77-(AW77*10%) -> 224451 | AY77: 50000 | BA77: =SUM(AX77-AY77-AZ77) -> 174451
A78: 78 | B78: 46157 | C78: SPORTAGE | D78: 267어5480 | E78: KNAPT81BGNK077349 | G78: 용빈 100 | H78: 17730000 | I78: 0 | J78: 17730000 | K78: 야드 | L78: 완 | M78: Kv auto group | N78: Bul. Severen 4 ent.A fl.6 ap. 26 | O78: 9202114449 | P78: +359 89 982 0982 | Q78: Sofia 1000 , str Hristo Kovachev 26 | R78: Bulgaria | S78: 입금완료 | T78: 10300 | U78: 1728 | V78: 1485 | X78: CON3 | AA78: =SUM(T78,W78:Z78) -> 10300 | AB78: =SUM(AG78+AI78+AK78+AL78-AM78) -> 0 | AC78: =SUM(AB78-AA78) -> -10300 | AN78: 35000 | AO78: 30000 | AS78: =SUM(AN78:AR78) -> 65000 | AT78: =SUM(AA78-W78)*U78-AS78 -> 17733400 | AU78: =SUM(AT78-J78) -> 3400 | AV78: =SUM(0.09*H78) -> 1595700 | AW78: =SUM(AU78:AV78)/2 -> 799550 | AX78: =AW78-(AW78*10%) -> 719595 | AY78: 50000 | BA78: =SUM(AX78-AY78-AZ78) -> 669595
A79: 79 | B79: 46157 | C79: CLS250D | D79: 154무6439 | E79: WDDL9HB0HA204541 | F79: 유진모터스/유진우 | G79: 회사100 | H79: 19040000 | I79: 0 | J79: =H79+I79 -> 19040000 | K79: 인천항 | L79: 완 | M79: Megadolon shpk | N79: Megadolon shpk | O79: 812073807 | P79: 38349110291 | Q79: Shaqir inhrishta prishtine 10000 | R79: Kosovo | S79: 50% 입금완료/0601 | T79: 10640 | U79: 1728 | V79: 1485 | W79: 1410 | AA79: =SUM(T79,W79:Z79) -> 12050 | AB79: =SUM(AG79+AI79+AK79+AL79-AM79) -> 0 | AC79: =SUM(AB79-AA79) -> -12050 | AN79: 35000 | AO79: 30000 | AS79: =SUM(AN79:AR79) -> 65000 | AT79: =SUM(AA79-W79)*U79-AS79 -> 18320920 | AU79: =SUM(AT79-J79) -> -719080 | AV79: =SUM(0.09*H79) -> 1713600 | AW79: =SUM(AU79:AV79)/2 -> 497260 | AX79: =AW79-(AW79*10%) -> 447534 | AY79: 50000 | BA79: =SUM(AX79-AY79-AZ79) -> 397534
A80: 80 | B80: 46162 | C80: CLIO | D80: 34누5985 | E80: VF15RBJ0DJR024698 | F80: BK모터스/ 경현수 | G80: 회사50 | H80: 8140000 | I80: 0 | J80: =H80+I80 -> 8140000 | K80: 인천항 | L80: 완 | M80: Megadolon shpk | N80: Megadolon shpk | O80: 812073807 | P80: 38349110291 | Q80: Shaqir inhrishta prishtine 10000 | R80: Kosovo | S80: 50% 입금완료/0601 | T80: 4735 | U80: 1730 | V80: 1490 | W80: 1410 | AA80: =SUM(T80,W80:Z80) -> 6145 | AB80: =SUM(AG80+AI80+AK80+AL80-AM80) -> 0 | AC80: =SUM(AB80-AA80) -> -6145 | AN80: 35000 | AO80: 30000 | AS80: =SUM(AN80:AR80) -> 65000 | AT80: =SUM(AA80-W80)*U80-AS80 -> 8126550 | AU80: =SUM(AT80-J80) -> -13450 | AV80: =SUM(0.09*H80) -> 732600 | AW80: =SUM(AU80:AV80)/2 -> 359575 | AX80: =AW80-(AW80*10%) -> 323617.5 | AY80: 50000 | BA80: =SUM(AX80-AY80-AZ80) -> 273617.5
A81: 81 | B81: 46162 | C81: S-CLASS | D81: 348주7431 | E81: W1KUF2BB6LA579946 | F81: 쏠카/신동민 | G81: 용빈50 | H81: 36900000 | I81: 0 | J81: =H81+I81 -> 36900000 | K81: 인천항 | L81: 완 | M81: Megadolon shpk | N81: Megadolon shpk | O81: 812073807 | P81: 38349110291 | Q81: Shaqir inhrishta prishtine 10000 | R81: Kosovo | S81: 50% 입금완료/0601 | T81: 20345 | U81: 1730 | V81: 1490 | W81: 1500 | AA81: =SUM(T81,W81:Z81) -> 21845 | AB81: =SUM(AG81+AI81+AK81+AL81-AM81) -> 0 | AC81: =SUM(AB81-AA81) -> -21845 | AN81: 35000 | AO81: 30000 | AS81: =SUM(AN81:AR81) -> 65000 | AT81: =SUM(AA81-W81)*U81-AS81 -> 35131850 | AU81: =SUM(AT81-J81) -> -1768150 | AV81: =SUM(0.09*H81) -> 3321000 | AW81: =SUM(AU81:AV81)/2 -> 776425 | AX81: =AW81-(AW81*10%) -> 698782.5 | AY81: 50000 | BA81: =SUM(AX81-AY81-AZ81) -> 648782.5
A82: 82 | B82: 46162 | C82: Peugeot 508 | D82: 29조9274 | E82: VF38DBHZTGL002564 | F82: 우민모터스 / 배광일 | G82: 회사50 | H82: 5200000 | I82: 0 | J82: =H82+I82 -> 5200000 | K82: 인천항 | L82: 완 | M82: Megadolon shpk | N82: Megadolon shpk | O82: 812073807 | P82: 38349110291 | Q82: Shaqir inhrishta prishtine 10000 | R82: Kosovo | S82: 50% 입금완료/0601 | T82: 2630 | U82: 1730 | V82: 1490 | W82: 1410 | AA82: =SUM(T82,W82:Z82) -> 4040 | AB82: =SUM(AG82+AI82+AK82+AL82-AM82) -> 0 | AC82: =SUM(AB82-AA82) -> -4040 | AN82: 35000 | AO82: 30000 | AS82: =SUM(AN82:AR82) -> 65000 | AT82: =SUM(AA82-W82)*U82-AS82 -> 4484900 | AU82: =SUM(AT82-J82) -> -715100 | AV82: =SUM(0.09*H82) -> 468000 | AW82: =SUM(AU82:AV82)/2 -> -123550 | AX82: =AW82-(AW82*10%) -> -111195 | AY82: 50000 | BA82: =SUM(AX82-AY82-AZ82) -> -161195
A83: 83 | B83: 46162 | C83: CLS300D | D83: 187로3654 | E83: WDD2J1JB7KA041921 | F83: H오토모티브/장준운 | G83: 회사50 | H83: 27040000 | I83: 0 | J83: =H83+I83 -> 27040000 | K83: 인천항 | L83: 완 | M83: Megadolon shpk | N83: Megadolon shpk | O83: 812073807 | P83: 38349110291 | Q83: Shaqir inhrishta prishtine 10000 | R83: Kosovo | S83: 50% 입금완료/0601 | U83: 1730 | V83: 1490 | W83: 1410 | AA83: =SUM(T83,W83:Z83) -> 1410 | AB83: =SUM(AG83+AI83+AK83+AL83-AM83) -> 0 | AC83: =SUM(AB83-AA83) -> -1410 | AN83: 35000 | AO83: 30000 | AS83: =SUM(AN83:AR83) -> 65000 | AT83: =SUM(AA83-W83)*U83-AS83 -> -65000 | AU83: =SUM(AT83-J83) -> -27105000 | AV83: =SUM(0.09*H83) -> 2433600 | AW83: =SUM(AU83:AV83)/2 -> -12335700 | AX83: =AW83-(AW83*10%) -> -11102130 | AY83: 50000 | BA83: =SUM(AX83-AY83-AZ83) -> -11152130
A84: 84 | B84: 46162 | C84: QM3 | D84: 27너1811 | E84: VF12RS01AJW021650 | F84: 원스타/이승규 | G84: 회사50 | H84: 6630000 | I84: 0 | J84: =H84+I84 -> 6630000 | K84: 인천항 | L84: 완 | M84: Ardian Bajram | N84: NOVA AUTO ARDI KOREA SHPK | O84: 812408145 | P84: +38345883676 | Q84: Lagja Dardania , rruga Idriz Gjilani lokali Nova Bar | R84: Kosovo | T84: 3930 | U84: 1730 | V84: 1490 | W84: 1410 | AA84: =SUM(T84,W84:Z84) -> 5340 | AB84: =SUM(AG84+AI84+AK84+AL84-AM84) -> 0 | AC84: =SUM(AB84-AA84) -> -5340 | AN84: 35000 | AO84: 30000 | AS84: =SUM(AN84:AR84) -> 65000 | AT84: =SUM(AA84-W84)*U84-AS84 -> 6733900 | AU84: =SUM(AT84-J84) -> 103900 | AV84: =SUM(0.09*H84) -> 596700 | AW84: =SUM(AU84:AV84)/2 -> 350300 | AX84: =AW84-(AW84*10%) -> 315270 | AY84: 50000 | BA84: =SUM(AX84-AY84-AZ84) -> 265270
A85: 85 | B85: 46163 | C85: A5 | D85: 316노8043 | E85: WAUZZZF56LA015294 | F85: 골드상사/박찬홍 | G85: 용빈50 | H85: 25700000 | I85: 0 | J85: =H85+I85 -> 25700000 | K85: 인천항 | L85: 완 | M85: Kv auto group | N85: VESELIN PANOV | O85: 8009244506 | P85: +359 89 982 0982 | Q85: City:Plovdiv Zh.K Trakia 127 | R85: Bulgaria | S85: 입금완료 | T85: 14800 | U85: 1730 | V85: 1492 | X85: CON2 운항중 | AA85: =SUM(T85,W85:Z85) -> 14800 | AB85: =SUM(AG85+AI85+AK85+AL85-AM85) -> 0 | AC85: =SUM(AB85-AA85) -> -14800 | AN85: 35000 | AO85: 30000 | AS85: =SUM(AN85:AR85) -> 65000 | AT85: =SUM(AA85-W85)*U85-AS85 -> 25539000 | AU85: =SUM(AT85-J85) -> -161000 | AV85: =SUM(0.09*H85) -> 2313000 | AW85: =SUM(AU85:AV85)/2 -> 1076000 | AX85: =AW85-(AW85*10%) -> 968400 | AY85: 50000 | BA85: =SUM(AX85-AY85-AZ85) -> 918400
A86: 86 | B86: 46162 | C86: TIGUAN | D86: 149소3319 | E86: WVGZZZ5NZGW568057 | F86: 경매장-AJ | H86: 6600000 | I86: 170610 | J86: =H86+I86 -> 6770610 | K86: 인천항 | L86: 완 | M86: Idealshped | N86: Auto Sallon Ardiani A&Q SHPK | O86: 812398693 | P86: 383 049 822 255 | Q86: Kosovo | R86: Kosovo | S86: 입금완료 | T86: 4140 | U86: 1730 | V86: 1492 | W86: 1500 | AA86: =SUM(T86,W86:Z86) -> 5640 | AB86: =SUM(AG86+AI86+AK86+AL86-AM86) -> 0 | AC86: =SUM(AB86-AA86) -> -5640 | AN86: 35000 | AO86: 30000 | AS86: =SUM(AN86:AR86) -> 65000 | AT86: =SUM(AA86-W86)*U86-AS86 -> 7097200 | AU86: =SUM(AT86-J86) -> 326590 | AV86: =SUM(0.09*H86) -> 594000 | AW86: =SUM(AU86:AV86)/2 -> 460295 | AX86: =AW86-(AW86*10%) -> 414265.5 | AY86: 50000 | BA86: =SUM(AX86-AY86-AZ86) -> 364265.5
A87: 87 | B87: 46168 | C87: SPORTAGE | D87: 347무9122 | E87: KNAPV81CDPK147135 | F87: 오토인사이드 / 이재성 | G87: 용빈 100 | H87: 18800000 | I87: 440000 | J87: =H87+I87 -> 19240000 | K87: 인천항 | L87: 완 | M87: Kv auto group | N87: Cvetelina Stoyanova Stefanova | O87: 0245054372 | P87: +359 89 982 0982 | Q87: City Plovdiv , str. Boris Petrov 28 | R87: Bulgaria | S87: 입금완료 | T87: 10850 | U87: 1730 | V87: 1487 | X87: CON2 운항중 | AA87: 10850 | AB87: =SUM(AG87+AI87+AK87+AL87-AM87) -> 0 | AC87: =SUM(AB87-AA87) -> -10850 | AN87: 35000 | AO87: 30000 | AS87: =SUM(AN87:AR87) -> 65000 | AT87: =SUM(AA87-W87)*U87-AS87 -> 18705500 | AU87: =SUM(AT87-J87) -> -534500 | AV87: =SUM(0.09*H87) -> 1692000 | AW87: =SUM(AU87:AV87)/2 -> 578750 | AX87: =AW87-(AW87*10%) -> 520875 | AY87: 50000 | BA87: =SUM(AX87-AY87-AZ87) -> 470875
A88: 88 | B88: 46168 | C88: A5 | D88: 214라8788 | E88: WAUZZZF52LA015437 | F88: UK모터스 / 고경민 | G88: 용빈 100 | H88: 26340000 | I88: 0 | J88: =H88+I88 -> 26340000 | K88: 인천항 | L88: 완 | M88: Kv auto group | N88: Bozhidar Yonkov Choplishki | O88: 0042287748 | P88: +359 89 982 0982 | Q88: City Plovdiv , Bul. Bulgaria 2 | R88: Bulgaria | S88: 입금완료 | T88: 14900 | U88: 1730 | V88: 1487 | X88: CON2 운항중 | AA88: 14900 | AB88: =SUM(AG88+AI88+AK88+AL88-AM88) -> 0 | AC88: =SUM(AB88-AA88) -> -14900 | AN88: 35000 | AO88: 30000 | AS88: =SUM(AN88:AR88) -> 65000 | AT88: =SUM(AA88-W88)*U88-AS88 -> 25712000 | AU88: =SUM(AT88-J88) -> -628000 | AV88: =SUM(0.09*H88) -> 2370600 | AW88: =SUM(AU88:AV88)/2 -> 871300 | AX88: =AW88-(AW88*10%) -> 784170 | AY88: 50000 | BA88: =SUM(AX88-AY88-AZ88) -> 734170
A89: 89 | B89: 46168 | C89: A6 | D89: 247더7292 | E89: WAUZZZF26LN069936 | F89: 카멘토 / 양기택 | G89: 용빈50 | H89: 31600000 | I89: 0 | J89: =H89+I89 -> 31600000 | K89: 인천항 | L89: 완 | M89: Megadolon shpk | N89: Megadolon shpk | O89: 812073807 | P89: 38349110291 | Q89: Shaqir inhrishta prishtine 10000 | R89: Kosovo | S89: 50% 입금완료/0604 | T89: 17600 | U89: 1730 | V89: 1487 | W89: 1410 | AA89: 19010 | AB89: =SUM(AG89+AI89+AK89+AL89-AM89) -> 0 | AC89: =SUM(AB89-AA89) -> -19010 | AN89: 35000 | AO89: 30000 | AS89: =SUM(AN89:AR89) -> 65000 | AT89: =SUM(AA89-W89)*U89-AS89 -> 30383000 | AU89: =SUM(AT89-J89) -> -1217000 | AV89: =SUM(0.09*H89) -> 2844000 | AW89: =SUM(AU89:AV89)/2 -> 813500 | AX89: =AW89-(AW89*10%) -> 732150 | AY89: 50000 | BA89: =SUM(AX89-AY89-AZ89) -> 682150
A90: 90 | B90: 46168 | C90: A7 55 TDI | D90: 48조0810 | E90: WAUZZZ4G6GN139553 | F90: 우리트레이딩 / 채보경 | G90: 용빈 50 | H90: 19800000 | I90: 0 | J90: =H90+I90 -> 19800000 | K90: 인천항 | L90: 완 | M90: Megadolon shpk | N90: Megadolon shpk | O90: 812073807 | P90: 38349110291 | Q90: Shaqir inhrishta prishtine 10000 | R90: Kosovo | S90: 50% 입금완료/0604 | T90: 10950 | U90: 1730 | V90: 1487 | W90: 1410 | X90: ONE CON1 | AA90: 12360 | AB90: =SUM(AG90+AI90+AK90+AL90-AM90) -> 0 | AC90: =SUM(AB90-AA90) -> -12360 | AN90: 35000 | AO90: 30000 | AS90: =SUM(AN90:AR90) -> 65000 | AT90: =SUM(AA90-W90)*U90-AS90 -> 18878500 | AU90: =SUM(AT90-J90) -> -921500 | AV90: =SUM(0.09*H90) -> 1782000 | AW90: =SUM(AU90:AV90)/2 -> 430250 | AX90: =AW90-(AW90*10%) -> 387225 | AY90: 50000 | BA90: =SUM(AX90-AY90-AZ90) -> 337225
A91: 91 | B91: 46168 | C91: GLA | D91: 17조0166 | E91: WDCTG0JBXBH287856 | F91: 설레임 / 조성훈 | G91: 회사 50 | H91: 13000000 | I91: 0 | J91: =H91+I91 -> 13000000 | K91: 인천항 | L91: 완 | M91: Megadolon shpk | N91: Megadolon shpk | O91: 812073807 | P91: 38349110291 | Q91: Shaqir inhrishta prishtine 10000 | R91: Kosovo | S91: 50% 입금완료/0604 | T91: 7620 | U91: 1730 | V91: 1487 | W91: 1500 | AA91: 9120 | AB91: =SUM(AG91+AI91+AK91+AL91-AM91) -> 0 | AC91: =SUM(AB91-AA91) -> -9120 | AN91: 35000 | AO91: 30000 | AS91: =SUM(AN91:AR91) -> 65000 | AT91: =SUM(AA91-W91)*U91-AS91 -> 13117600 | AU91: =SUM(AT91-J91) -> 117600 | AV91: =SUM(0.09*H91) -> 1170000 | AW91: =SUM(AU91:AV91)/2 -> 643800 | AX91: =AW91-(AW91*10%) -> 579420 | AY91: 50000 | BA91: =SUM(AX91-AY91-AZ91) -> 529420
A92: 92 | B92: 46169 | C92: TIGUAN | D92: 64부3877 | E92: WVGZZZ5NZJW943799 | F92: 제이디모터스/윤용범 | G92: 회사 50 | H92: 18700000 | I92: 0 | J92: =H92+I92 -> 18700000 | K92: 인천항 | L92: 완 | M92: Megadolon shpk | N92: Megadolon shpk | O92: 812073807 | P92: 38349110291 | Q92: Shaqir inhrishta prishtine 10000 | R92: Kosovo | S92: 50% 입금완료/0604 | T92: 10350 | U92: 1730 | V92: 1487 | W92: 1500 | AA92: 11850 | AB92: =SUM(AG92+AI92+AK92+AL92-AM92) -> 0 | AC92: =SUM(AB92-AA92) -> -11850 | AN92: 35000 | AO92: 30000 | AS92: =SUM(AN92:AR92) -> 65000 | AT92: =SUM(AA92-W92)*U92-AS92 -> 17840500 | AU92: =SUM(AT92-J92) -> -859500 | AV92: =SUM(0.09*H92) -> 1683000 | AW92: =SUM(AU92:AV92)/2 -> 411750 | AX92: =AW92-(AW92*10%) -> 370575 | AY92: 50000 | BA92: =SUM(AX92-AY92-AZ92) -> 320575
A93: 93 | B93: 46169 | C93: SANTAFE | D93: 14라9855 | E93: KMHS281BBKU018161 | F93: 하이오토코리아 / 김종성 | G93: 회사 50 | H93: 14500000 | I93: 0 | J93: =H93+I93 -> 14500000 | K93: 인천항 | L93: 완 | M93: Ramadan Xhaferi | N93: Hysenbelli Shaqir | O93: I80319069E | P93: +355 692079087 | Q93: DURRES POST | R93: Albania | S93: 50%적용/ 쉬핑제외 | T93: 8200 | U93: 1730 | V93: 1487 | W93: 1500 | AA93: =SUM(T93,W93:Z93) -> 9700 | AB93: =SUM(AG93+AI93+AK93+AL93-AM93) -> 0 | AC93: =SUM(AB93-AA93) -> -9700 | AN93: 35000 | AO93: 30000 | AS93: =SUM(AN93:AR93) -> 65000 | AT93: =SUM(AA93-W93)*U93-AS93 -> 14121000 | AU93: =SUM(AT93-J93) -> -379000 | AV93: =SUM(0.09*H93) -> 1305000 | AW93: =SUM(AU93:AV93)/2 -> 463000 | AX93: =AW93-(AW93*10%) -> 416700 | AY93: 50000 | BA93: =SUM(AX93-AY93-AZ93) -> 366700
A94: 94 | B94: 46171 | C94: TIGUAN | D94: 282로8301 | E94: WVGZZZ5NZLM178288 | F94: 카베이 / 이석호 | G94: 용빈50 | H94: 20500000 | I94: 440000 | J94: =H94+I94 -> 20940000 | K94: 인천항 | L94: 완 | M94: 888 AUTO KOSOVA | N94: Dokleat Veseli | O94: 1175140057 | P94: +383 044 72 92 41 | Q94: Kosova, Prishtina | R94: Kosovo | S94: 입금예정 | T94: 11500 | U94: 1737 | V94: 1491 | W94: 1500 | AA94: =SUM(T94,W94:Z94) -> 13000 | AB94: =SUM(AG94+AI94+AK94+AL94-AM94) -> 0 | AC94: =SUM(AB94-AA94) -> -13000 | AN94: 35000 | AO94: 30000 | AS94: =SUM(AN94:AR94) -> 65000 | AT94: =SUM(AA94-W94)*U94-AS94 -> 19910500 | AU94: =SUM(AT94-J94) -> -1029500 | AV94: =SUM(0.09*H94) -> 1845000 | AW94: =SUM(AU94:AV94)/2 -> 407750 | AX94: =AW94-(AW94*10%) -> 366975 | AY94: 50000 | BA94: =SUM(AX94-AY94-AZ94) -> 316975
A95: 95 | B95: 46151 | C95: BENTAYGA | D95: 138누3453 | E95: SJAAM14V6MC036673 | F95: 솔카 / 이종진 | G95: 회사 500 | H95: 155000000 | I95: 440000 | J95: =H95+I95 -> 155440000 | K95: 인천항 | L95: 완 | M95: Megadolon shpk | N95: Megadolon shpk | O95: 812073807 | P95: 38349110291 | Q95: Shaqir inhrishta prishtine 10000 | R95: Kosovo | S95: 50% 입금완료/0604 | T95: 87700 | U95: 1737 | V95: 1491 | W95: 2980 | X95: CMA CON2 | AA95: =SUM(T95,W95:Z95) -> 90680 | AB95: =SUM(AG95+AI95+AK95+AL95-AM95) -> 0 | AC95: =SUM(AB95-AA95) -> -90680 | AN95: 35000 | AO95: 30000 | AS95: =SUM(AN95:AR95) -> 65000 | AT95: =SUM(AA95-W95)*U95-AS95 -> 152269900 | AU95: =SUM(AT95-J95) -> -3170100 | AV95: =SUM(0.09*H95) -> 13950000 | AW95: =SUM(AU95:AV95)/2 -> 5389950 | AX95: =AW95-(AW95*10%) -> 4850955 | AY95: 50000 | BA95: =SUM(AX95-AY95-AZ95) -> 4800955
A96: 96 | B96: 46171 | C96: BENZ SL | D96: 244도9761 | E96: W1KVK8BB7PF013449 | F96: 더하이앤드 / 박태인 | G96: 회사 300 | H96: 137400000 | I96: 0 | J96: =H96+I96 -> 137400000 | K96: 인천항 | L96: 완 | M96: Megadolon shpk | N96: Megadolon shpk | O96: 812073807 | P96: 38349110291 | Q96: Shaqir inhrishta prishtine 10000 | R96: Kosovo | S96: 50% 입금완료 배송비 제외 /0604 | T96: 74080 | U96: 1737 | V96: 1491 | W96: 2525 | X96: CMA CON2 | AA96: =SUM(T96,W96:Z96) -> 76605 | AB96: =SUM(AG96+AI96+AK96+AL96-AM96) -> 0 | AC96: =SUM(AB96-AA96) -> -76605 | AN96: 35000 | AO96: 30000 | AS96: =SUM(AN96:AR96) -> 65000 | AT96: =SUM(AA96-W96)*U96-AS96 -> 128611960 | AU96: =SUM(AT96-J96) -> -8788040 | AV96: =SUM(0.09*H96) -> 12366000 | AW96: =SUM(AU96:AV96)/2 -> 1788980 | AX96: =AW96-(AW96*10%) -> 1610082 | AY96: 50000 | BA96: =SUM(AX96-AY96-AZ96) -> 1560082
A97: 97 | B97: 46171 | C97: 750L I x Drive | D97: 36너2000 | E97: WBA7F2108GG523983 | F97: 무결점/박예춘 | G97: 회사50 | H97: 23200000 | I97: 0 | J97: =H97+I97 -> 23200000 | K97: 인천항 | L97: 완 | M97: Megadolon shpk | N97: Megadolon shpk | O97: 812073807 | P97: 38349110291 | Q97: Shaqir inhrishta prishtine 10000 | R97: Kosovo | T97: 13100 | U97: 1737 | V97: 1491 | W97: 1500 | AA97: =SUM(T97,W97:Z97) -> 14600 | AB97: =SUM(AG97+AI97+AK97+AL97-AM97) -> 0 | AC97: =SUM(AB97-AA97) -> -14600 | AN97: 35000 | AO97: 30000 | AS97: =SUM(AN97:AR97) -> 65000 | AT97: =SUM(AA97-W97)*U97-AS97 -> 22689700 | AU97: =SUM(AT97-J97) -> -510300 | AV97: =SUM(0.09*H97) -> 2088000 | AW97: =SUM(AU97:AV97)/2 -> 788850 | AX97: =AW97-(AW97*10%) -> 709965 | AY97: 50000 | BA97: =SUM(AX97-AY97-AZ97) -> 659965
A98: 98 | B98: 46171 | C98: E-CLASS | D98: 181너7046 | E98: WDDZF0EB8JA462307 | F98: 차모터스 / 김중호 | G98: 회사50 | H98: 16540000 | I98: 0 | J98: =H98+I98 -> 16540000 | K98: 인천항 | L98: 완 | M98: Megadolon shpk | N98: Megadolon shpk | O98: 812073807 | P98: 38349110291 | Q98: Shaqir inhrishta prishtine 10000 | R98: Kosovo | S98: 50% 입금완료/0604 | T98: 9266 | U98: 1737 | V98: 1491 | W98: 1410 | AA98: =SUM(T98,W98:Z98) -> 10676 | AB98: =SUM(AG98+AI98+AK98+AL98-AM98) -> 0 | AC98: =SUM(AB98-AA98) -> -10676 | AN98: 35000 | AO98: 30000 | AS98: =SUM(AN98:AR98) -> 65000 | AT98: =SUM(AA98-W98)*U98-AS98 -> 16030042 | AU98: =SUM(AT98-J98) -> -509958 | AV98: =SUM(0.09*H98) -> 1488600 | AW98: =SUM(AU98:AV98)/2 -> 489321 | AX98: =AW98-(AW98*10%) -> 440388.9 | AY98: 50000 | BA98: =SUM(AX98-AY98-AZ98) -> 390388.9
A99: 99 | B99: 46171 | C99: 118D | D99: 19구0684 | E99: WBA1S5101GV679247 | F99: V모터스 / 민상진 | G99: 회사50 | H99: 12000000 | J99: =H99+I99 -> 12000000 | K99: 인천항 | L99: 완 | M99: Megadolon shpk | N99: Megadolon shpk | O99: 812073807 | P99: 38349110291 | Q99: Shaqir inhrishta prishtine 10000 | R99: Kosovo | S99: 50% 입금완료/0604 | T99: 6865 | U99: 1737 | V99: 1491 | W99: 1410 | AA99: =SUM(T99,W99:Z99) -> 8275 | AB99: =SUM(AG99+AI99+AK99+AL99-AM99) -> 0 | AC99: =SUM(AB99-AA99) -> -8275 | AN99: 35000 | AO99: 30000 | AS99: =SUM(AN99:AR99) -> 65000 | AT99: =SUM(AA99-W99)*U99-AS99 -> 11859505 | AU99: =SUM(AT99-J99) -> -140495 | AV99: =SUM(0.09*H99) -> 1080000 | AW99: =SUM(AU99:AV99)/2 -> 469752.5 | AX99: =AW99-(AW99*10%) -> 422777.25 | AY99: 50000 | BA99: =SUM(AX99-AY99-AZ99) -> 372777.25
A100: 100 | B100: 46171 | C100: 320I | D100: 314우2051 | E100: WBA8A9105JAE91874 | F100: 카울렛 / 구태형 | G100: 용빈50 | H100: 11400000 | I100: 0 | J100: =H100+I100 -> 11400000 | K100: 인천항 | L100: 완 | M100: Megadolon shpk | N100: Megadolon shpk | O100: 812073807 | P100: 38349110291 | Q100: Shaqir inhrishta prishtine 10000 | R100: Kosovo | S100: 50% 입금완료/0604 | T100: 6525 | U100: 1737 | V100: 1491 | W100: 1410 | AA100: =SUM(T100,W100:Z100) -> 7935 | AB100: =SUM(AG100+AI100+AK100+AL100-AM100) -> 0 | AC100: =SUM(AB100-AA100) -> -7935 | AN100: 35000 | AO100: 30000 | AS100: =SUM(AN100:AR100) -> 65000 | AT100: =SUM(AA100-W100)*U100-AS100 -> 11268925 | AU100: =SUM(AT100-J100) -> -131075 | AV100: =SUM(0.09*H100) -> 1026000 | AW100: =SUM(AU100:AV100)/2 -> 447462.5 | AX100: =AW100-(AW100*10%) -> 402716.25 | AY100: 50000 | BA100: =SUM(AX100-AY100-AZ100) -> 352716.25
...

Sheet 유로 인보이스+판매보고AUTO
E1: PROFORM INVOICE | H1: 128 | J1: 판매보고 자동화 (AUTO)
A2: Ssancar LTD 46-1, Gakgol-ro 2an-Gil, Sangnok, Ansan-si, Gyeinggi-do, Incheon, Korea. Phone: +82-505-366-9977 | J2: 매매단지 매입➖➖➖➖➖➖➖➖➖➖➖➖➖
E3: Date | F3: =VLOOKUP($H$1,'유로 판매현황'!A2:BB238,2,FALSE) -> 46189 | J3: ="차량명 : " & VLOOKUP($H$1,'유로 판매현황'!A2:BB239,3,FALSE) -> 차량명 : SPORTAGE
E4: Invoice No. | F4: ="YB"&RIGHT(C18,6) -> YB061080 | J4: ="차량번호 : " & TEXT(VLOOKUP($H$1,'유로 판매현황'!A1:BB237,4,FALSE),"#,##0") -> 차량번호 : 396수1494
E5: Name | F5: =VLOOKUP($H$1,'유로 판매현황'!A2:BB238,14,FALSE) -> Sasa Spasic | J5: ="차대번호 : " & TEXT(VLOOKUP($H$1,'유로 판매현황'!A2:BB238,5,FALSE),"#,##0") -> 차대번호 : KNAPU81CBKNK061080
E6: ID No. / business No. | F6: =VLOOKUP($H$1,'유로 판매현황'!A2:BB239,15,FALSE) -> 1502153826 | J6: ="차량대금 : " & TEXT(VLOOKUP($H$1,'유로 판매현황'!A2:BB238,8,FALSE),"#,##0") & "원" -> 차량대금 : 14,900,000원
E7: Adress | F7: =VLOOKUP($H$1,'유로 판매현황'!A2:BB240,17,FALSE) -> Štrpce, Kosovo | J7: ="매도비 : "&VLOOKUP($H$1,'유로 판매현황'!A3:BB239,9,FALSE)&"원" -> 매도비 : 0원
E8: Country | F8: =VLOOKUP($H$1,'유로 판매현황'!A2:BB241,18,FALSE) -> Kosovo | J8: 계산서 : 100%
E9: Phone | F9: =VLOOKUP($H$1,'유로 판매현황'!A2:BB242,16,FALSE) -> 383 44 116 519 | J9: ="판매자정보 : " & TEXT(VLOOKUP($H$1,'유로 판매현황'!A2:BB238,6,FALSE),"#,##0") -> 판매자정보 : 오토핸즈/이재성
E10: EURO exchange rate | F10: =VLOOKUP($H$1,'유로 판매현황'!A2:BB238,21,FALSE) -> 1734 | G10: =VLOOKUP($H$1,'유로 판매현황'!A2:BB238,22,FALSE) -> 1497 | J10: ="바이어 : " & VLOOKUP($H$1,'유로 판매현황'!A5:BB241,13,FALSE) -> 바이어 : 888 AUTO KOSOVA
J11: ="판매금액 : €" & TEXT(VLOOKUP($H$1,'유로 판매현황'!A2:BB242,20,FALSE),"#,##0") -> 판매금액 : €8,400
A12: BANK ACCOUNT INFORMATION | J12: 배송조건 : CFR
A13: Beneficiary | C13: SSANCAR CO LTD | E13: Bank Name | F13: SHINHAN BANK | J13: ="환율 : €" & VLOOKUP($H$1,'유로 판매현황'!A2:BB242,21,FALSE) -> 환율 : €1734 | K13: ="/ $" & VLOOKUP($H$1,'유로 판매현황'!A2:BB242,22,FALSE) -> / $1497
A14: Swift Cose | C14: SHBKKRSE | E14: Bank Adress | F14: 20,Sejong-Daero9-Gil,Jung-Gu Seoul South Korea | J14: ="운임비 : €" & TEXT(VLOOKUP($H$1,'유로 판매현황'!A2:BB242,23,FALSE),"#,##0") -> 운임비 : €1,500
A15: Bank Account Number | C15: 180-008-400167 | E15: Beneficiary Adress | F15: 65 SEONGHYEON-RO,ILSANDONG-GU,GOYANG-SI, GYEONGGI-DO, SOUTH KOREA | J15: ="토탈 입금 받을금액 : €" & TEXT(VLOOKUP($H$1,'유로 판매현황'!A2:BB242,27,FALSE),"#,##0") -> 토탈 입금 받을금액 : €9,900
J16: ="계약금 : " & TEXT(VLOOKUP($H$1,'유로 판매현황'!A3:BB243,7,FALSE),"#,##0") -> 계약금 : 용빈50
A17: Code | B17: Model | C17: Chassis Number | D17: CAR PRICE | E17: Shipping Cost | F17: Total
A18: =VLOOKUP($H$1,'유로 판매현황'!A2:BB238,4,FALSE) -> 396수1494 | B18: =VLOOKUP($H$1,'유로 판매현황'!A2:BB238,3,FALSE) -> SPORTAGE | C18: =VLOOKUP($H$1,'유로 판매현황'!A2:BB238,5,FALSE) -> KNAPU81CBKNK061080 | D18: =VLOOKUP($H$1,'유로 판매현황'!A2:BB240,20,FALSE) -> 8400 | E18: =VLOOKUP($H$1,'유로 판매현황'!A2:BB240,23,FALSE) -> 1500 | F18: =SUM(D18:E18) -> 9900
J21: 5월 현재 스코어 | N21: 6월 현재 스코어
J22: 달러현황 | K22: 유로현황 | L22: 독일 노르웨이 현황 | N22: 달러현황 | O22: 유로현황 | P22: 독일 노르웨이 현황
J23: =SUMIFS('달러 판매현황'!AZ:AZ,'달러 판매현황'!B:B,">="&DATE(2026,5,1),'달러 판매현황'!B:B,"<"&DATE(2026,6,1)) -> 787443.5 | K23: =SUMIFS('유로 판매현황'!BA:BA,'유로 판매현황'!B:B,">="&DATE(2026,5,1),'유로 판매현황'!B:B,"<"&DATE(2026,6,1)) -> 11674445 | L23: =SUMIFS('독일 노르웨이 판매현황'!BF:BF, '독일 노르웨이 판매현황'!B:B, ">="&DATE(2026,5,1), '독일 노르웨이 판매현황'!B:B, "<"&DATE(2026,6,1)) -> 0 | N23: =SUMIFS('달러 판매현황'!AZ:AZ,'달러 판매현황'!B:B,">="&DATE(2026,6,1),'달러 판매현황'!B:B,"<"&DATE(2026,7,1)) -> 4956942.8 | O23: =SUMIFS('유로 판매현황'!BA:BA,'유로 판매현황'!B:B,">="&DATE(2026,6,1),'유로 판매현황'!B:B,"<"&DATE(2026,7,1)) -> 19169391 | P23: =SUMIFS('독일 노르웨이 판매현황'!BF:BF, '독일 노르웨이 판매현황'!B:B, ">="&DATE(2026,5,1), '독일 노르웨이 판매현황'!B:B, "<"&DATE(2026,6,1)) -> 0
J24: ="합계 : "&TEXT(SUM(J23, K23, L23),"#,##0")&"원" -> 합계 : 12,461,889원 | N24: ="합계 : "&TEXT(SUM(N23, O23, P23),"#,##0")&"원" -> 합계 : 24,126,334원
E31: Subtotal | F31: =SUM(F18:G30) -> 9900
E32: replacement cost | F32: -
E33: Commission | F33: -
E35: Total | F35: =SUM(F31:G34) -> 9900

Sheet 독일 노르웨이 판매현황
A1: NO | B1: 구입일자2 | C1: 차량모델명15 | D1: 30무0996 14 | E1: CHASSIS NUMBER | F1: 판매자정보3 | G1: 엔진 배기량4 | H1: 엔진타입5 | I1: 에어컨 정보6 | J1: 등록일자7 | K1: 계약금 | L1: 바이어 회사명12 | M1: 고객컨사이니11 | N1: 고객 ID / 비즈니스 넘버10 | O1: 전화번호9 | P1: 주소8 | Q1: 이메일 | R1: 구입금액 | S1: 매도비 | T1: 총 구입금액 | U1: 유로 | V1: 위치 | W1: 판매보고 여부 | X1: 입금여부 | Y1: 판매금액 | Z1: 유로환율 | AA1: 달러환율 | AB1: 운임 | AC1: 커미션 | AD1: 디스카운트 | AE1: 부가세 | AF1: 판매 총 합계 | AG1: 입금합계 | AH1: 미수금 | AI1: 메모 | AJ1: 메모 | AK1: 입금날짜01 | AL1: 정산01 | AM1: 입금날짜02 | AN1: 정산02 | AO1: 입금날짜03 | AP1: 정산03 | AQ1: 적립금 사용 | AR1: 선수금 | AS1: 말소/면허 | AT1: 탁송 | AU1: 캐리어 | AV1: 쇼링 | AW1: 기타 | AX1: 합계 | AY1: 정산판매금 원화 | AZ1: 판매마진 | BA1: 부가세 마진 | BB1: 총 마진 | BC1: 지급액 | BD1: 서류공제 | BE1: 비용공제 | BF1: 실지급액 | BG1: 돈받은거
A2: 1 | B2: 45978 | C2: GLE63 AMG | D2: 202모6400 | E2: WDCDA7EB7GA741312 | F2: 우리들모터스 / 이재형 | L2: CERTUS GmbH | M2: CERTUS Industriedienstleistungen GmbH | N2: M34710201A | O2: +491755624915 | P2: James-Watt-Straße 10 / 33334 Gütersloh - Germany | Q2: tm@certus.gmbh | R2: 31000000 | S2: 0 | T2: =R2+S2 -> 31000000 | V2: 출고 | W2: 삼실 판매보고 완 | X2: 입금완료 | Y2: 20837 | Z2: 1448 | AA2: 1448 | AF2: =SUM(Y2,AB2:AE2) -> 20837 | AG2: =SUM(AL2+AN2+AP2+AQ2-AR2) -> 0 | AH2: =SUM(AG2-AF2) -> -20837 | AS2: 35000 | AT2: 30000 | AX2: =SUM(AS2:AW2) -> 65000 | AY2: =SUM(AF2-AB2)*Z2-AX2 -> 30106976 | AZ2: =SUM(AY2-T2) -> -893024 | BA2: =SUM(R2*0.09) -> 2790000 | BB2: =SUM(AZ2:BA2)/2 -> 948488 | BC2: =BB2-(BB2*10%) -> 853639.2 | BD2: 50000 | BF2: =SUM(BC2-BD2-BE2) -> 803639.2
A3: 2 | B3: 45989 | C3: CLS250 d 4Matic | D3: 28누0813 | E3: WDDL9HB3GA183389 | F3: 디에이모터스 / 김대신 | L3: CERTUS GmbH | M3: CERTUS Industriedienstleistungen GmbH | N3: M34710201A | O3: +491755624915 | P3: James-Watt-Straße 10 / 33334 Gütersloh - Germany | Q3: tm@certus.gmbh | R3: 13700000 | S3: 0 | T3: =R3+S3 -> 13700000 | V3: 출고 | W3: 삼실 판매보고 완 | X3: 입금완료 | Y3: 9192 | Z3: 1698 | AA3: 1452 | AF3: =SUM(Y3,AB3:AE3) -> 9192 | AG3: =SUM(AL3+AN3+AP3+AQ3-AR3) -> 0 | AH3: =SUM(AG3-AF3) -> -9192 | AS3: 35000 | AT3: 30000 | AX3: =SUM(AS3:AW3) -> 65000 | AY3: =SUM(AF3-AB3)*Z3-AX3 -> 15543016 | AZ3: =SUM(AY3-T3) -> 1843016 | BA3: =SUM(R3*0.09) -> 1233000 | BB3: =SUM(AZ3:BA3)/2 -> 1538008 | BC3: =BB3-(BB3*10%) -> 1384207.2 | BD3: 50000 | BF3: =SUM(BC3-BD3-BE3) -> 1334207.2
A4: 3 | B4: 45999 | C4: GLE350d 4Matic | D4: 43너1760 | E4: WDCDA2EB5HA992057 | F4: 무결점카모터스 / 정혜원 | L4: CERTUS GmbH | M4: CERTUS Industriedienstleistungen GmbH | N4: M34710201A | O4: +491755624915 | P4: James-Watt-Straße 10 / 33334 Gütersloh - Germany | Q4: tm@certus.gmbh | R4: 20500000 | S4: 0 | T4: =R4+S4 -> 20500000 | V4: 출고 | W4: 삼실 판매보고 완 | X4: 입금완료 | Y4: 13865 | Z4: 1698 | AA4: 1460 | AF4: =SUM(Y4,AB4:AE4) -> 13865 | AG4: =SUM(AL4+AN4+AP4+AQ4-AR4) -> 0 | AH4: =SUM(AG4-AF4) -> -13865 | AS4: 35000 | AT4: 30000 | AX4: =SUM(AS4:AW4) -> 65000 | AY4: =SUM(AF4-AB4)*Z4-AX4 -> 23477770 | AZ4: =SUM(AY4-T4) -> 2977770 | BA4: =SUM(R4*0.09) -> 1845000 | BB4: =SUM(AZ4:BA4)/2 -> 2411385 | BC4: =BB4-(BB4*10%) -> 2170246.5 | BD4: 50000 | BF4: =SUM(BC4-BD4-BE4) -> 2120246.5
A5: 4 | B5: 45999 | C5: C63 S AMG | D5: 36조0919 | E5: WDDWF8HB0GF317643 | F5: 더 하이앤드 / 김태양 | L5: Manouchehr Mirzaei | R5: 43140000 | S5: 440000 | T5: =R5+S5 -> 43580000 | V5: 출고 | W5: 삼실 판매보고 완 | X5: 입금완료 | Y5: 30850 | Z5: 1698 | AA5: 1453 | AF5: =SUM(Y5,AB5:AE5) -> 30850 | AG5: =SUM(AL5+AN5+AP5+AQ5-AR5) -> 0 | AH5: =SUM(AG5-AF5) -> -30850 | AS5: 35000 | AT5: 30000 | AX5: =SUM(AS5:AW5) -> 65000 | AY5: =SUM(AF5-AB5)*Z5-AX5 -> 52318300 | AZ5: =SUM(AY5-T5) -> 8738300 | BA5: =SUM(R5*0.09) -> 3882600 | BB5: =SUM(AZ5:BA5)/2 -> 6310450 | BC5: =BB5-(BB5*10%) -> 5679405 | BD5: 50000 | BF5: =SUM(BC5-BD5-BE5) -> 5629405
A6: 5 | B6: 46002 | C6: GLE250d 4Matic | D6: 230주7666 | E6: WDCDA0EB0GA681025 | F6: 차투차 / 진세현 | L6: CERTUS GmbH | M6: CERTUS Industriedienstleistungen GmbH | N6: M34710201A | O6: +491755624915 | P6: James-Watt-Straße 10 / 33334 Gütersloh - Germany | Q6: tm@certus.gmbh | R6: 18200000 | S6: 440000 | T6: =R6+S6 -> 18640000 | V6: 출고 | W6: 삼실 판매보고 완 | X6: 입금완료 | Y6: 12396.07 | Z6: 1698 | AA6: 1455 | AF6: =SUM(Y6,AB6:AE6) -> 12396.07 | AG6: =SUM(AL6+AN6+AP6+AQ6-AR6) -> 0 | AH6: =SUM(AG6-AF6) -> -12396.07 | AS6: 35000 | AT6: 30000 | AX6: =SUM(AS6:AW6) -> 65000 | AY6: =SUM(AF6-AB6)*Z6-AX6 -> 20983527 | AZ6: =SUM(AY6-T6) -> 2343526.9 | BA6: =SUM(R6*0.09) -> 1638000 | BB6: =SUM(AZ6:BA6)/2 -> 1990763.4 | BC6: =BB6-(BB6*10%) -> 1791687.1 | BD6: 50000 | BF6: =SUM(BC6-BD6-BE6) -> 1741687.1
A7: 6 | B7: 46024 | C7: CLA250 4Matic | D7: 31어7979 | E7: WDDSJ4GB5FN150322 | F7: 힐링모터스 / 김의선 | L7: CERTUS GmbH | M7: CERTUS Industriedienstleistungen GmbH | N7: M34710201A | O7: +491755624915 | P7: James-Watt-Straße 10 / 33334 Gütersloh - Germany | Q7: tm@certus.gmbh | R7: 12800000 | S7: 440000 | T7: =R7+S7 -> 13240000 | U7: 1300만원 판매 | V7: 출고 | W7: 삼실 판매보고 완 | X7: 입금완료 | Y7: 9100 | Z7: 1698 | AA7: 1430 | AF7: =SUM(Y7,AB7:AE7) -> 9100 | AG7: =SUM(AL7+AN7+AP7+AQ7-AR7) -> 0 | AH7: =SUM(AG7-AF7) -> -9100 | AS7: 35000 | AT7: 30000 | AX7: =SUM(AS7:AW7) -> 65000 | AY7: =SUM(AF7-AB7)*Z7-AX7 -> 15386800 | AZ7: =SUM(AY7-T7) -> 2146800 | BA7: =SUM(R7*0.09) -> 1152000 | BB7: =SUM(AZ7:BA7)/2 -> 1649400 | BC7: =BB7-(BB7*10%) -> 1484460 | BD7: 50000 | BF7: =SUM(BC7-BD7-BE7) -> 1434460
A8: 7 | B8: 46027 | C8: CLS400 | D8: 34고5999 | E8: WDDL6FB5FA138213 | F8: 오케이모터스 / 서동환 | L8: CERTUS GmbH | M8: CERTUS Industriedienstleistungen GmbH | N8: M34710201A | O8: +491755624915 | P8: James-Watt-Straße 10 / 33334 Gütersloh - Germany | Q8: tm@certus.gmbh | R8: 16000000 | S8: 440000 | T8: =R8+S8 -> 16440000 | U8: 1610만원 판매 | V8: 출고 | W8: 삼실 판매보고 완 | X8: 입금완료 | Y8: 11242 | Z8: 1698 | AA8: 1432 | AF8: =SUM(Y8,AB8:AE8) -> 11242 | AG8: =SUM(AL8+AN8+AP8+AQ8-AR8) -> 0 | AH8: =SUM(AG8-AF8) -> -11242 | AS8: 35000 | AT8: 30000 | AX8: =SUM(AS8:AW8) -> 65000 | AY8: =SUM(AF8-AB8)*Z8-AX8 -> 19023916 | AZ8: =SUM(AY8-T8) -> 2583916 | BA8: =SUM(R8*0.09) -> 1440000 | BB8: =SUM(AZ8:BA8)/2 -> 2011958 | BC8: =BB8-(BB8*10%) -> 1810762.2 | BD8: 50000 | BF8: =SUM(BC8-BD8-BE8) -> 1760762.2
A9: 8 | B9: 46028 | C9: E400 Cabriolet | D9: 18구7174 | E9: WDDKK6FF0GF321194 | F9: 쌍둥이모터스 / 정월출 | L9: CERTUS GmbH | M9: CERTUS Industriedienstleistungen GmbH | N9: M34710201A | O9: +491755624915 | P9: James-Watt-Straße 10 / 33334 Gütersloh - Germany | Q9: tm@certus.gmbh | R9: 16200000 | S9: 0 | T9: =R9+S9 -> 16200000 | U9: 9322URO/1588만원 | V9: 출고 | W9: 삼실 판매보고 완 | X9: 입금완료 | Y9: 10877 | Z9: 1698 | AA9: 1460 | AF9: =SUM(Y9,AB9:AE9) -> 10877 | AG9: =SUM(AL9+AN9+AP9+AQ9-AR9) -> 0 | AH9: =SUM(AG9-AF9) -> -10877 | AJ9: BENZ공센터에서 에어벡 리콜중 | AS9: 35000 | AT9: 30000 | AX9: =SUM(AS9:AW9) -> 65000 | AY9: =SUM(AF9-AB9)*Z9-AX9 -> 18404146 | AZ9: =SUM(AY9-T9) -> 2204146 | BA9: =SUM(R9*0.09) -> 1458000 | BB9: =SUM(AZ9:BA9)/2 -> 1831073 | BC9: =BB9-(BB9*10%) -> 1647965.7 | BD9: 50000 | BF9: =SUM(BC9-BD9-BE9) -> 1597965.7
A10: 9 | B10: 46034 | C10: GLA 45 AMG | D10: 50모0955 | E10: WDCTG5CB7GJ217630 | F10: 카매니저 / 김동규 | L10: CERTUS GmbH | M10: CERTUS Industriedienstleistungen GmbH | N10: M34710201A | O10: +491755624915 | P10: James-Watt-Straße 10 / 33334 Gütersloh - Germany | Q10: tm@certus.gmbh | R10: 16200000 | S10: 0 | T10: =R10+S10 -> 16200000 | U10: 1577만원 판매 | V10: 출고 | W10: 삼실 판매보고 완 | X10: 입금완료 | Y10: 10909 | Z10: 1698 | AA10: 1445 | AF10: =SUM(Y10,AB10:AE10) -> 10909 | AG10: =SUM(AL10+AN10+AP10+AQ10-AR10) -> 0 | AH10: =SUM(AG10-AF10) -> -10909 | AS10: 35000 | AT10: 30000 | AX10: =SUM(AS10:AW10) -> 65000 | AY10: =SUM(AF10-AB10)*Z10-AX10 -> 18458482 | AZ10: =SUM(AY10-T10) -> 2258482 | BA10: =SUM(R10*0.09) -> 1458000 | BB10: =SUM(AZ10:BA10)/2 -> 1858241 | BC10: =BB10-(BB10*10%) -> 1672416.9 | BD10: 50000 | BF10: =SUM(BC10-BD10-BE10) -> 1622416.9
A11: 10 | B11: 46035 | C11: GLE350d 4Maitc | D11: 43라0518 | E11: WDCDA2EB3GA729788 | F11: 왕카 / 한필호 | L11: CERTUS GmbH | M11: CERTUS Industriedienstleistungen GmbH | N11: M34710201A | O11: +491755624915 | P11: James-Watt-Straße 10 / 33334 Gütersloh - Germany | Q11: tm@certus.gmbh | R11: 22800000 | S11: 1000000 | T11: =R11+S11 -> 23800000 | U11: 2214만원 진행 | V11: 출고 | W11: 삼실 판매보고 완 | X11: 입금완료 | Y11: 15113 | Z11: 1698 | AA11: 1465 | AF11: =SUM(Y11,AB11:AE11) -> 15113 | AG11: =SUM(AL11+AN11+AP11+AQ11-AR11) -> 0 | AH11: =SUM(AG11-AF11) -> -15113 | AS11: 35000 | AT11: 30000 | AX11: =SUM(AS11:AW11) -> 65000 | AY11: =SUM(AF11-AB11)*Z11-AX11 -> 25596874 | AZ11: =SUM(AY11-T11) -> 1796874 | BA11: =SUM(R11*0.09) -> 2052000 | BB11: =SUM(AZ11:BA11)/2 -> 1924437 | BC11: =BB11-(BB11*10%) -> 1731993.3 | BD11: 50000 | BF11: =SUM(BC11-BD11-BE11) -> 1681993.3
A12: 11 | B12: 46039 | C12: GLE63 AMG | D12: 291부1888 | E12: WDCDA7EBXGA729350 | F12: 달인중고차 / 김성현 | L12: CERTUS GmbH | M12: CERTUS Industriedienstleistungen GmbH | N12: M34710201A | O12: +491755624915 | P12: James-Watt-Straße 10 / 33334 Gütersloh - Germany | Q12: tm@certus.gmbh | R12: 36200000 | S12: 0 | T12: =R12+S12 -> 36200000 | U12: 3510만원 | V12: 출고 | W12: 삼실 판매보고 완 | X12: 입금완료 | Y12: 24043 | Z12: 1698 | AA12: 1459 | AF12: =SUM(Y12,AB12:AE12) -> 24043 | AG12: =SUM(AL12+AN12+AP12+AQ12-AR12) -> 0 | AH12: =SUM(AG12-AF12) -> -24043 | AS12: 35000 | AT12: 30000 | AX12: =SUM(AS12:AW12) -> 65000 | AY12: =SUM(AF12-AB12)*Z12-AX12 -> 40760014 | AZ12: =SUM(AY12-T12) -> 4560014 | BA12: =SUM(R12*0.09) -> 3258000 | BB12: =SUM(AZ12:BA12)/2 -> 3909007 | BC12: =BB12-(BB12*10%) -> 3518106.3 | BD12: 50000 | BF12: =SUM(BC12-BD12-BE12) -> 3468106.3
A13: 12 | B13: 46072 | C13: Mercedes-benz CLA250 4Matic | D13: 16거0862 | E13: WDDSJ4GB3GN365070 | F13: 오토허브셀카/ 박종기 | G13: 1991CC | H13: Gasoline | I13: R-134a | J13: 30.05.16 | L13: CERTUS GmbH | M13: CERTUS Industriedienstleistungen GmbH | N13: M34710201A | O13: +491755624915 | P13: James-Watt-Straße 10 / 33334 Gütersloh - Germany | Q13: tm@certus.gmbh | R13: 12500000 | S13: 0 | T13: =R13+S13 -> 12500000 | U13: 7135 | V13: 출고 | W13: 삼실 판매보고 완 | Y13: 8442 | Z13: 1698 | AA13: 1436 | AF13: =SUM(Y13,AB13:AE13) -> 8442 | AG13: =SUM(AL13+AN13+AP13+AQ13-AR13) -> 0 | AH13: =SUM(AG13-AF13) -> -8442 | AS13: 35000 | AT13: 30000 | AX13: =SUM(AS13:AW13) -> 65000 | AY13: =SUM(AF13-AB13)*Z13-AX13 -> 14269516 | AZ13: =SUM(AY13-T13) -> 1769516 | BA13: =SUM(R13*0.09) -> 1125000 | BB13: =SUM(AZ13:BA13)/2 -> 1447258 | BC13: =BB13-(BB13*10%) -> 1302532.2 | BD13: 50000 | BF13: =SUM(BC13-BD13-BE13) -> 1252532.2
A14: 13 | B14: 46072 | C14: C63 S | D14: 287머3914 | E14: WDDWF8HB1GF312919 | F14: 빅보스모터스 / 김진현 | L14: Raja Shais Ghani | M14: Raja Shais Ghani | N14: 34101913 | O14: +47 40056349 | P14: Ole Messelts vei 148 | R14: 46000000 | S14: 440000 | T14: =R14+S14 -> 46440000 | U14: USD | V14: 출고 | W14: 삼실 판매보고 완 | X14: 입금완료 | Y14: 32470 | Z14: 1698 | AA14: 1436 | AF14: =SUM(Y14,AB14:AE14) -> 32470 | AG14: =SUM(AL14+AN14+AP14+AQ14-AR14) -> 0 | AH14: =SUM(AG14-AF14) -> -32470 | AS14: 35000 | AT14: 30000 | AX14: =SUM(AS14:AW14) -> 65000 | AY14: =SUM(AF14-AB14)*Z14-AX14 -> 55069060 | AZ14: =SUM(AY14-T14) -> 8629060 | BA14: =SUM(R14*0.09) -> 4140000 | BB14: =SUM(AZ14:BA14)/2 -> 6384530 | BC14: =BB14-(BB14*10%) -> 5746077 | BD14: 50000 | BF14: =SUM(BC14-BD14-BE14) -> 5696077
A15: 14 | B15: 46072 | C15: S-CLASS | D15: 340라5374 | E15: WDDUX8FB7GA226874 | F15: AJ 경매장 | L15: CERTUS GmbH | M15: CERTUS Industriedienstleistungen GmbH | N15: M34710201A | O15: +491755624915 | P15: James-Watt-Straße 10 / 33334 Gütersloh - Germany | Q15: tm@certus.gmbh | R15: 35500000 | S15: 550000 | T15: =R15+S15 -> 36050000 | U15: 3550만원 / 106만원 | V15: 출고 | W15: 삼실 판매보고 완 | X15: 입금완료 | Y15: 25200 | Z15: 1698 | AA15: 1409 | AF15: =SUM(Y15,AB15:AE15) -> 25200 | AG15: =SUM(AL15+AN15+AP15+AQ15-AR15) -> 0 | AH15: =SUM(AG15-AF15) -> -25200 | AS15: 35000 | AT15: 30000 | AX15: =SUM(AS15:AW15) -> 65000 | AY15: =SUM(AF15-AB15)*Z15-AX15 -> 42724600 | AZ15: =SUM(AY15-T15) -> 6674600 | BA15: =SUM(R15*0.09) -> 3195000 | BB15: =SUM(AZ15:BA15)/2 -> 4934800 | BC15: =BB15-(BB15*10%) -> 4441320 | BD15: 50000 | BF15: =SUM(BC15-BD15-BE15) -> 4391320
A16: 15 | B16: 46073 | C16: BMW 750Li xDrive | D16: 31다1036 | E16: WBA7F2104GG523639 | F16: K CAR | G16: 4395cc | H16: Gasoline | I16: R-134a | J16: 03.04.2017 | K16: 경매 수수료 포함 1900만원 판매 | L16: CERTUS GmbH | M16: CERTUS Industriedienstleistungen GmbH | N16: M34710201A | O16: +491755624915 | P16: James-Watt-Straße 10 / 33334 Gütersloh - Germany | Q16: tm@certus.gmbh | R16: 18600000 | S16: 440000 | T16: =R16+S16 -> 19040000 | U16: 11177 | V16: 출고 | W16: 삼실 판매보고 완 | Y16: 13260 | Z16: 1698 | AA16: 1432 | AF16: =SUM(Y16,AB16:AE16) -> 13260 | AG16: =SUM(AL16+AN16+AP16+AQ16-AR16) -> 0 | AH16: =SUM(AG16-AF16) -> -13260 | AS16: 35000 | AT16: 30000 | AX16: =SUM(AS16:AW16) -> 65000 | AY16: =SUM(AF16-AB16)*Z16-AX16 -> 22450480 | AZ16: =SUM(AY16-T16) -> 3410480 | BA16: =SUM(R16*0.09) -> 1674000 | BB16: =SUM(AZ16:BA16)/2 -> 2542240 | BC16: =BB16-(BB16*10%) -> 2288016 | BD16: 50000 | BF16: =SUM(BC16-BD16-BE16) -> 2238016
A17: 16 | B17: 46077 | C17: Mercedes-AMG G65 | D17: 149가3390 | E17: WDCYC7EF8GX259993 | F17: 아이오토스 / 임용진 | L17: CERTUS GmbH | M17: CERTUS Industriedienstleistungen GmbH | N17: M34710201A | O17: +491755624915 | P17: James-Watt-Straße 10 / 33334 Gütersloh - Germany | Q17: tm@certus.gmbh | R17: 121000000 | S17: 0 | T17: =R17+S17 -> 121000000 | V17: 출고 | W17: 삼실 판매보고 완 | Y17: 67648 | Z17: 1698 | AA17: 1443 | AF17: =SUM(Y17,AB17:AE17) -> 67648 | AG17: =SUM(AL17+AN17+AP17+AQ17-AR17) -> 0 | AH17: =SUM(AG17-AF17) -> -67648 | AS17: 35000 | AT17: 30000 | AX17: =SUM(AS17:AW17) -> 65000 | AY17: =SUM(AF17-AB17)*Z17-AX17 -> 114801304 | AZ17: =SUM(AY17-T17) -> -6198696 | BA17: =SUM(R17*0.09) -> 10890000 | BB17: =SUM(AZ17:BA17)/2 -> 2345652 | BC17: =BB17-(BB17*10%) -> 2111086.8 | BD17: 50000 | BF17: =SUM(BC17-BD17-BE17) -> 2061086.8
A18: 17 | B18: 46084 | C18: CLA45 AMG | D18: 181러3700 | E18: WDDSJ5CB4JN518381 | F18: 뉴코리아모터스 / 조광선 | I18: R-134a | L18: Raja Shais Ghani | M18: Raja Shais Ghani | N18: 34101913 | O18: +47 40056349 | P18: Ole Messelts vei 148 | R18: 21900000 | S18: 0 | T18: =R18+S18 -> 21900000 | V18: 출고 | W18: 삼실 판매보고 완 | X18: 입금완료 | Y18: 15200 | Z18: 1443 | AA18: 1443 | AF18: =SUM(Y18,AB18:AE18) -> 15200 | AG18: =SUM(AL18+AN18+AP18+AQ18-AR18) -> 0 | AH18: =SUM(AG18-AF18) -> -15200 | AS18: 35000 | AT18: 30000 | AX18: =SUM(AS18:AW18) -> 65000 | AY18: =SUM(AF18-AB18)*Z18-AX18 -> 21868600 | AZ18: =SUM(AY18-T18) -> -31400 | BA18: =SUM(R18*0.09) -> 1971000 | BB18: =SUM(AZ18:BA18)/2 -> 969800 | BC18: =BB18-(BB18*10%) -> 872820 | BD18: 50000 | BF18: =SUM(BC18-BD18-BE18) -> 822820
A19: 18 | B19: 46089 | C19: Mercedes-benz CLA250 4Matic | D19: 221조3438 | E19: WDDSJ4GB0FN109239 | F19: 유주오토 / 안현우 | G19: 1991CC | H19: Gasoline | I19: R-134a | J19: 26.08.2014 | K19: 1191만원판매 | L19: CERTUS GmbH | M19: CERTUS Industriedienstleistungen GmbH | N19: M34710201A | O19: +491755624915 | P19: James-Watt-Straße 10 / 33334 Gütersloh - Germany | Q19: tm@certus.gmbh | R19: 11950000 | S19: 0 | T19: =R19+S19 -> 11950000 | U19: 7006 | V19: 출고 | W19: 삼실 판매보고 완 | X19: 입금완료 | Y19: 6972 | Z19: 1698 | AA19: 1495 | AF19: =SUM(Y19,AB19:AE19) -> 6972 | AG19: =SUM(AL19+AN19+AP19+AQ19-AR19) -> 0 | AH19: =SUM(AG19-AF19) -> -6972 | AS19: 35000 | AT19: 30000 | AX19: =SUM(AS19:AW19) -> 65000 | AY19: =SUM(AF19-AB19)*Z19-AX19 -> 11773456 | AZ19: =SUM(AY19-T19) -> -176544 | BA19: =SUM(R19*0.09) -> 1075500 | BB19: =SUM(AZ19:BA19)/2 -> 449478 | BC19: =BB19-(BB19*10%) -> 404530.2 | BD19: 50000 | BF19: =SUM(BC19-BD19-BE19) -> 354530.2
A20: 19 | B20: 46118 | C20: Mercedes-Benz GLE350D | D20: 05두3911 | E20: WDCDA2EB8HA912265 | F20: GDCAR/김복기 | G20: 2987CC | H20: Diesel | I20: R-134a | J20: 23.06.2017 | K20: 22144375 | L20: CERTUS GmbH | M20: CERTUS Industriedienstleistungen GmbH | N20: M34710201A | O20: +491755624915 | P20: James-Watt-Straße 10 / 33334 Gütersloh - Germany | Q20: tm@certus.gmbh | R20: 23000000 | S20: 0 | T20: =R20+S20 -> 23000000 | U20: 12822 | V20: 출고 | W20: 삼실 판매보고 완 | X20: 입금완료 | Y20: =12822-50 -> 12772 | Z20: 1727 | AA20: 1467 | AF20: =SUM(Y20,AB20:AE20) -> 12772 | AG20: =SUM(AL20+AN20+AP20+AQ20-AR20) -> 0 | AH20: =SUM(AG20-AF20) -> -12772 | AS20: 35000 | AT20: 30000 | AX20: =SUM(AS20:AW20) -> 65000 | AY20: =SUM(AF20-AB20)*Z20-AX20 -> 21992244 | AZ20: =SUM(AY20-T20) -> -1007756 | BA20: =SUM(R20*0.09) -> 2070000 | BB20: =SUM(AZ20:BA20)/2 -> 531122 | BC20: =BB20-(BB20*10%) -> 478009.8 | BD20: 50000 | BF20: =SUM(BC20-BD20-BE20) -> 428009.8
A21: 20 | B21: 46119 | C21: Mercedes-Benz C 220 d 4MATIC Coupé | D21: 43소6494 | E21: WDDWJ1FB2KF872210 | F21: (주)와이엠모터스 | G21: 1950 | H21: Diesel | I21: R-134a | J21: 26.06.2019 | K21: 19016250 | L21: CERTUS GmbH | M21: CERTUS Industriedienstleistungen GmbH | N21: M34710201A | O21: +491755624915 | P21: James-Watt-Straße 10 / 33334 Gütersloh - Germany | Q21: tm@certus.gmbh | R21: 20300000 | S21: 0 | T21: =R21+S21 -> 20300000 | U21: 11011 | V21: 출고 | W21: 삼실 판매보고 완 | X21: 입금완료 | Y21: =11011-50 -> 10961 | Z21: 1727 | AA21: 1467 | AF21: =SUM(Y21,AB21:AE21) -> 10961 | AG21: =SUM(AL21+AN21+AP21+AQ21-AR21) -> 0 | AH21: =SUM(AG21-AF21) -> -10961 | AS21: 35000 | AT21: 30000 | AX21: =SUM(AS21:AW21) -> 65000 | AY21: =SUM(AF21-AB21)*Z21-AX21 -> 18864647 | AZ21: =SUM(AY21-T21) -> -1435353 | BA21: =SUM(R21*0.09) -> 1827000 | BB21: =SUM(AZ21:BA21)/2 -> 195823.5 | BC21: =BB21-(BB21*10%) -> 176241.15 | BD21: 50000 | BF21: =SUM(BC21-BD21-BE21) -> 126241.15
A22: 21 | B22: 46124 | C22: Mercedes-Benz CLA 45 AMG 4MATIC | D22: 45거3598 | E22: WDDSJ4GB2FN239314 | F22: ㈜명문자동차 | G22: 1991cc | H22: Gasoline | I22: R-134a | J22: 30.07.2015 | K22: 10090000 | L22: CERTUS GmbH | M22: CERTUS Industriedienstleistungen GmbH | N22: M34710201A | O22: +491755624915 | P22: James-Watt-Straße 10 / 33334 Gütersloh - Germany | Q22: tm@certus.gmbh | R22: 10000000 | S22: 440000 | T22: =R22+S22 -> 10440000 | U22: 5843 | V22: 출고 | W22: 삼실 판매보고 완 | X22: 입금완료 | Y22: =5843-50 -> 5793 | Z22: 1727 | AA22: 1467 | AF22: =SUM(Y22,AB22:AE22) -> 5793 | AG22: =SUM(AL22+AN22+AP22+AQ22-AR22) -> 0 | AH22: =SUM(AG22-AF22) -> -5793 | AS22: 35000 | AT22: 30000 | AX22: =SUM(AS22:AW22) -> 65000 | AY22: =SUM(AF22-AB22)*Z22-AX22 -> 9939511 | AZ22: =SUM(AY22-T22) -> -500489 | BA22: =SUM(R22*0.09) -> 900000 | BB22: =SUM(AZ22:BA22)/2 -> 199755.5 | BC22: =BB22-(BB22*10%) -> 179779.95 | BD22: 50000 | BF22: =SUM(BC22-BD22-BE22) -> 129779.95
A23: 22 | T23: =R23+S23 -> 0 | AF23: =SUM(Y23,AB23:AE23) -> 0 | AG23: =SUM(AL23+AN23+AP23+AQ23-AR23) -> 0 | AH23: =SUM(AG23-AF23) -> 0 | AS23: 35000 | AT23: 30000 | AX23: =SUM(AS23:AW23) -> 65000 | AY23: =SUM(AF23-AB23)*Z23-AX23 -> -65000 | AZ23: =SUM(AY23-T23) -> -65000 | BA23: =SUM(R23*0.09) -> 0 | BB23: =SUM(AZ23:BA23)/2 -> -32500 | BC23: =BB23-(BB23*10%) -> -29250 | BD23: 50000 | BF23: =SUM(BC23-BD23-BE23) -> -79250
A24: 23 | T24: =R24+S24 -> 0 | AF24: =SUM(Y24,AB24:AE24) -> 0 | AG24: =SUM(AL24+AN24+AP24+AQ24-AR24) -> 0 | AH24: =SUM(AG24-AF24) -> 0 | AS24: 35000 | AT24: 30000 | AX24: =SUM(AS24:AW24) -> 65000 | AY24: =SUM(AF24-AB24)*Z24-AX24 -> -65000 | AZ24: =SUM(AY24-T24) -> -65000 | BA24: =SUM(R24*0.09) -> 0 | BB24: =SUM(AZ24:BA24)/2 -> -32500 | BC24: =BB24-(BB24*10%) -> -29250 | BD24: 50000 | BF24: =SUM(BC24-BD24-BE24) -> -79250
A25: 24 | T25: =R25+S25 -> 0 | AF25: =SUM(Y25,AB25:AE25) -> 0 | AG25: =SUM(AL25+AN25+AP25+AQ25-AR25) -> 0 | AH25: =SUM(AG25-AF25) -> 0 | AS25: 35000 | AT25: 30000 | AX25: =SUM(AS25:AW25) -> 65000 | AY25: =SUM(AF25-AB25)*Z25-AX25 -> -65000 | AZ25: =SUM(AY25-T25) -> -65000 | BA25: =SUM(R25*0.09) -> 0 | BB25: =SUM(AZ25:BA25)/2 -> -32500 | BC25: =BB25-(BB25*10%) -> -29250 | BD25: 50000 | BF25: =SUM(BC25-BD25-BE25) -> -79250
A26: 25 | T26: =R26+S26 -> 0 | AF26: =SUM(Y26,AB26:AE26) -> 0 | AG26: =SUM(AL26+AN26+AP26+AQ26-AR26) -> 0 | AH26: =SUM(AG26-AF26) -> 0 | AS26: 35000 | AT26: 30000 | AX26: =SUM(AS26:AW26) -> 65000 | AY26: =SUM(AF26-AB26)*Z26-AX26 -> -65000 | AZ26: =SUM(AY26-T26) -> -65000 | BA26: =SUM(R26*0.09) -> 0 | BB26: =SUM(AZ26:BA26)/2 -> -32500 | BC26: =BB26-(BB26*10%) -> -29250 | BD26: 50000 | BF26: =SUM(BC26-BD26-BE26) -> -79250
A27: 26 | T27: =R27+S27 -> 0 | AF27: =SUM(Y27,AB27:AE27) -> 0 | AG27: =SUM(AL27+AN27+AP27+AQ27-AR27) -> 0 | AH27: =SUM(AG27-AF27) -> 0 | AS27: 35000 | AT27: 30000 | AX27: =SUM(AS27:AW27) -> 65000 | AY27: =SUM(AF27-AB27)*Z27-AX27 -> -65000 | AZ27: =SUM(AY27-T27) -> -65000 | BA27: =SUM(R27*0.09) -> 0 | BB27: =SUM(AZ27:BA27)/2 -> -32500 | BC27: =BB27-(BB27*10%) -> -29250 | BD27: 50000 | BF27: =SUM(BC27-BD27-BE27) -> -79250
A28: 27 | T28: =R28+S28 -> 0 | AF28: =SUM(Y28,AB28:AE28) -> 0 | AG28: =SUM(AL28+AN28+AP28+AQ28-AR28) -> 0 | AH28: =SUM(AG28-AF28) -> 0 | AS28: 35000 | AT28: 30000 | AX28: =SUM(AS28:AW28) -> 65000 | AY28: =SUM(AF28-AB28)*Z28-AX28 -> -65000 | AZ28: =SUM(AY28-T28) -> -65000 | BA28: =SUM(R28*0.09) -> 0 | BB28: =SUM(AZ28:BA28)/2 -> -32500 | BC28: =BB28-(BB28*10%) -> -29250 | BD28: 50000 | BF28: =SUM(BC28-BD28-BE28) -> -79250
A29: 28 | T29: =R29+S29 -> 0 | AF29: =SUM(Y29,AB29:AE29) -> 0 | AG29: =SUM(AL29+AN29+AP29+AQ29-AR29) -> 0 | AH29: =SUM(AG29-AF29) -> 0 | AS29: 35000 | AT29: 30000 | AX29: =SUM(AS29:AW29) -> 65000 | AY29: =SUM(AF29-AB29)*Z29-AX29 -> -65000 | AZ29: =SUM(AY29-T29) -> -65000 | BA29: =SUM(R29*0.09) -> 0 | BB29: =SUM(AZ29:BA29)/2 -> -32500 | BC29: =BB29-(BB29*10%) -> -29250 | BD29: 50000 | BF29: =SUM(BC29-BD29-BE29) -> -79250
A30: 29 | T30: =R30+S30 -> 0 | AF30: =SUM(Y30,AB30:AE30) -> 0 | AG30: =SUM(AL30+AN30+AP30+AQ30-AR30) -> 0 | AH30: =SUM(AG30-AF30) -> 0 | AS30: 35000 | AT30: 30000 | AX30: =SUM(AS30:AW30) -> 65000 | AY30: =SUM(AF30-AB30)*Z30-AX30 -> -65000 | AZ30: =SUM(AY30-T30) -> -65000 | BA30: =SUM(R30*0.09) -> 0 | BB30: =SUM(AZ30:BA30)/2 -> -32500 | BC30: =BB30-(BB30*10%) -> -29250 | BD30: 50000 | BF30: =SUM(BC30-BD30-BE30) -> -79250
A31: 30 | T31: =R31+S31 -> 0 | AF31: =SUM(Y31,AB31:AE31) -> 0 | AG31: =SUM(AL31+AN31+AP31+AQ31-AR31) -> 0 | AH31: =SUM(AG31-AF31) -> 0 | AS31: 35000 | AT31: 30000 | AX31: =SUM(AS31:AW31) -> 65000 | AY31: =SUM(AF31-AB31)*Z31-AX31 -> -65000 | AZ31: =SUM(AY31-T31) -> -65000 | BA31: =SUM(R31*0.09) -> 0 | BB31: =SUM(AZ31:BA31)/2 -> -32500 | BC31: =BB31-(BB31*10%) -> -29250 | BD31: 50000 | BF31: =SUM(BC31-BD31-BE31) -> -79250
A32: 31 | T32: =R32+S32 -> 0 | AF32: =SUM(Y32,AB32:AE32) -> 0 | AG32: =SUM(AL32+AN32+AP32+AQ32-AR32) -> 0 | AH32: =SUM(AG32-AF32) -> 0 | AS32: 35000 | AT32: 30000 | AX32: =SUM(AS32:AW32) -> 65000 | AY32: =SUM(AF32-AB32)*Z32-AX32 -> -65000 | AZ32: =SUM(AY32-T32) -> -65000 | BA32: =SUM(R32*0.09) -> 0 | BB32: =SUM(AZ32:BA32)/2 -> -32500 | BC32: =BB32-(BB32*10%) -> -29250 | BD32: 50000 | BF32: =SUM(BC32-BD32-BE32) -> -79250
A33: 32 | T33: =R33+S33 -> 0 | AF33: =SUM(Y33,AB33:AE33) -> 0 | AG33: =SUM(AL33+AN33+AP33+AQ33-AR33) -> 0 | AH33: =SUM(AG33-AF33) -> 0 | AS33: 35000 | AT33: 30000 | AX33: =SUM(AS33:AW33) -> 65000 | AY33: =SUM(AF33-AB33)*Z33-AX33 -> -65000 | AZ33: =SUM(AY33-T33) -> -65000 | BA33: =SUM(R33*0.09) -> 0 | BB33: =SUM(AZ33:BA33)/2 -> -32500 | BC33: =BB33-(BB33*10%) -> -29250 | BD33: 50000 | BF33: =SUM(BC33-BD33-BE33) -> -79250
A34: 33 | T34: =R34+S34 -> 0 | AF34: =SUM(Y34,AB34:AE34) -> 0 | AG34: =SUM(AL34+AN34+AP34+AQ34-AR34) -> 0 | AH34: =SUM(AG34-AF34) -> 0 | AS34: 35000 | AT34: 30000 | AX34: =SUM(AS34:AW34) -> 65000 | AY34: =SUM(AF34-AB34)*Z34-AX34 -> -65000 | AZ34: =SUM(AY34-T34) -> -65000 | BA34: =SUM(R34*0.09) -> 0 | BB34: =SUM(AZ34:BA34)/2 -> -32500 | BC34: =BB34-(BB34*10%) -> -29250 | BD34: 50000 | BF34: =SUM(BC34-BD34-BE34) -> -79250
... A416: 415 | T416: =R416+S416 -> 0 | AF416: =SUM(Y416,AB416:AE416) -> 0 | AG416: =SUM(AL416+AN416+AP416+AQ416-AR416) -> 0 | AH416: =SUM(AG416-AF416) -> 0 | AS416: 35000 | AT416: 30000 | AX416: =SUM(AS416:AW416) -> 65000 | AY416: =SUM(AF416-AB416)*Z416-AX416 -> -65000 | AZ416: =SUM(AY416-T416) -> -65000 | BA416: =SUM(R416*0.09) -> 0 | BB416: =SUM(AZ416:BA416)/2 -> -32500 | BC416: =BB416-(BB416*10%) -> -29250 | BD416: 50000 | BF416: =SUM(BC416-BD416-BE416) -> -79250
A417: 416
A418: 417
A419: 418
A420: 419
A421: 420
A422: 421
A423: 422
A424: 423
A425: 424
A426: 425
A427: 426
A428: 427
... A451: 450

Sheet 독일 노르웨이 인보이스 + 판매보고AUTO
E1: PROFORM INVOICE | H1: 88 | I1: 판매보고 자동화 (AUTO)
A2: Ssancar LTD 46-1, Gakgol-ro 2an-Gil, Sangnok, Ansan-si, Gyeinggi-do, Incheon, Korea. Phone: +82-505-366-9977 | I2: 매매단지 매입➖➖➖➖➖➖➖➖➖➖➖➖➖
E3: Date | F3: =VLOOKUP($H$1,'독일 노르웨이 판매현황'!A2:BF241,2,FALSE) -> 0 | I3: ="차량명 : " & VLOOKUP($H$1,'독일 노르웨이 판매현황'!A2:BF241,3,FALSE) -> 차량명 :
E4: Invoice No. | F4: =VLOOKUP($H$1,'독일 노르웨이 판매현황'!A2:BF241,17,FALSE) -> 0 | I4: ="차량번호 : " & TEXT(VLOOKUP($H$1,'독일 노르웨이 판매현황'!A1:BF240,4,FALSE),"#,##0") -> 차량번호 : ,0
E5: Company Name. | F5: =VLOOKUP($H$1,'독일 노르웨이 판매현황'!A2:BF241,13,FALSE) -> 0 | I5: ="차대번호 : " & TEXT(VLOOKUP($H$1,'독일 노르웨이 판매현황'!A2:BF241,5,FALSE),"#,##0") -> 차대번호 : ,0
E6: Business No. | F6: =VLOOKUP($H$1,'독일 노르웨이 판매현황'!A2:BF241,14,FALSE) -> 0 | I6: 계산서 : 100%
E7: Address | F7: =VLOOKUP($H$1,'독일 노르웨이 판매현황'!A2:BF241,16,FALSE) -> 0 | I7: ="차량대금 : " & TEXT(VLOOKUP($H$1,'독일 노르웨이 판매현황'!A2:BF241,18,FALSE),"#,##0") & "원" -> 차량대금 : ,0원 | N7: ㅇ
E8: Telephone number. | F8: =VLOOKUP($H$1,'독일 노르웨이 판매현황'!A2:BF241,15,FALSE) -> 0 | I8: ="매도비 : "&VLOOKUP($H$1,'독일 노르웨이 판매현황'!A3:BF242,19,FALSE)&"원" -> 매도비 : 원
E9: Email. | F9: =VLOOKUP($H$1,'독일 노르웨이 판매현황'!A2:BF241,17,FALSE) -> 0 | I9: ="판매처 : " & VLOOKUP($H$1,'독일 노르웨이 판매현황'!A1:BF240,6,FALSE) -> 판매처 :
E10: Tax number. | F10: 351/5769/1588 | I10: ="환율 : €" & VLOOKUP($H$1,'독일 노르웨이 판매현황'!A2:AZ246,26,FALSE) -> 환율 : € | J10: ="/ $" & VLOOKUP($H$1,'독일 노르웨이 판매현황'!A2:AZ246,27,FALSE) -> / $
E11: VAT ID number. | F11: DE247052867 | I11: 계산서 : 100% | N11: ㅇ
E12: F-GAS Portal ID No. | F12: 98739 | I12: ="바이어 : " & VLOOKUP($H$1,'독일 노르웨이 판매현황'!A4:AZ244,13,FALSE) -> 바이어 :
E13: EORI No. | F13: DE632486045873121 | I13: ="판매금액 : €" & TEXT(VLOOKUP($H$1,'독일 노르웨이 판매현황'!A1:BF244,21,FALSE),"#,##0") -> 판매금액 : €,0
E14: Dollar exchange rate | F14: =VLOOKUP($H$1,'독일 노르웨이 판매현황'!A2:BF241,26,FALSE) -> 0 | G14: =VLOOKUP($H$1,'독일 노르웨이 판매현황'!A2:BF241,27,FALSE) -> 0 | I14: 배송조건 : 컨테이너
I15: **계약금 : 이용빈 계약 50만**
A16: BANK ACCOUNT INFORMATION
A17: Beneficiary | C17: SSANCAR CO LTD | E17: Bank Name | F17: SHINHAN BANK
A18: Swift Cose | C18: SHBKKRSE | E18: Bank Adress | F18: 20,Sejong-Daero9-Gil,Jung-Gu Seoul South Korea
A19: Bank Account Number | C19: 180-008-400167 | E19: Beneficiary Adress | F19: 65 SEONGHYEON-RO,ILSANDONG-GU,GOYANG-SI, GYEONGGI-DO, SOUTH KOREA
A20: ="Engine Displacemen : " & TEXT(VLOOKUP($H$1,'독일 노르웨이 판매현황'!A2:BF241,7,FALSE),"#,##0") -> Engine Displacemen : ,0 | C20: ="Engine Type : " & TEXT(VLOOKUP($H$1,'독일 노르웨이 판매현황'!A2:BF241,8,FALSE),"#,##0") -> Engine Type : ,0 | D20: Refrigerant Type : R-134a Quantity : 650 grams | E20: ="Date of first registration : " & TEXT(VLOOKUP($H$1,'독일 노르웨이 판매현황'!A2:BF241,10,FALSE),"#,##0") -> Date of first registration : ,0
A21: Code | B21: Model | C21: Chassis Number | D21: CAR PRICE | E21: Shipping Cost | F21: Total
A22: =VLOOKUP($H$1,'독일 노르웨이 판매현황'!A2:BF241,4,FALSE) -> 0 | B22: =VLOOKUP($H$1,'독일 노르웨이 판매현황'!A2:BF241,3,FALSE) -> 0 | C22: =VLOOKUP($H$1,'독일 노르웨이 판매현황'!A2:BF241,5,FALSE) -> 0 | D22: =VLOOKUP($H$1,'독일 노르웨이 판매현황'!A2:BF241,21,FALSE) -> 0 | E22: - | F22: =SUM(D22:E22) -> 0
E35: Subtotal | F35: =SUM(F22:G34) -> 0
E36: replacement cost | F36: -
E37: Commission | F37: -
E39: Total | F39: =SUM(F35:G38) -> 0

Sheet 유로 선적지시서
A1: RORO 선적지시서 | H1: 1
A2: Main Consigne | D2: =VLOOKUP($H$1,'유로 판매현황'!A2:BB238,8,FALSE) -> #N/A
D3: =VLOOKUP($H$1,'유로 판매현황'!A3:BB239,4,FALSE) -> #N/A
D4: =VLOOKUP($H$1,'유로 판매현황'!A4:BB240,4,FALSE) -> #N/A
D5: =VLOOKUP($H$1,'유로 판매현황'!A5:BB241,4,FALSE) -> #N/A
A6: Final Destination | D6: DURRESS, ALBANIA
A7: Forwarding | D7: CIG
A8: VESSEL NAME | D8: -
A9: DOC | D9: -
A10: ETD | D10: -
A11: ETA | D11: -
A12: NO. | B12: Consigne | C12: Commodity | D12: Chassis No. | E12: Unit Price | F12: Shipping | G12: MEMO
A13: 1 | B13: Obiliq,Kosova +38344272242 FESTIM MEXHUANI ID: 1243830547 festim-mexhuani@hotmail.com | C13: =VLOOKUP($H$1,'유로 판매현황'!A2:BB238,13,FALSE) -> #N/A | D13: WAUZZZF27MN004448 | E13: 23345 | F13: 1155
A14: 2 | B14: Valmir Gashi ID:1175553165 +38344157977 valmirgashi2001@gmail.com | C14: 320D | D14: WBA8C5102GK640437 | E14: 7408 | F14: 1242
A15: 3
A16: 4
A17: 5
A18: 6
A19: 7
A20: 8
A21: 9
A22: 10
A23: 11
A24: 12
A25: 13
A26: SUB TOTAL | E26: =SUM(E13:E25) -> 30753 | F26: =SUM(F13:F25) -> 2397
A27: GRAND TOTAL : | C27: GRAND TOTAL : | E27: =SUM(E26:F26) -> 33150
